Workbook
Name \A: #REF!
Name \A: #REF!
Name \A: #REF!
Name \A: #REF!
Name \A: #REF!
Name \C: #REF!
Name \C: #REF!
Name \C: #REF!
Name \C: #REF!
Name \C: #REF!
Name \D: #REF!
Name \D: #REF!
Name \D: #REF!
Name \D: #REF!
Name \D: #REF!
Name \E: #REF!
Name \E: #REF!
Name \E: #REF!
Name \E: #REF!
Name \E: #REF!
Name \F: #REF!
Name \F: #REF!
Name \F: #REF!
Name \F: #REF!
Name \F: #REF!
Name \G: #REF!
Name \G: #REF!
Name \G: #REF!
Name \G: #REF!
Name \G: #REF!
Name \H: #REF!
Name \H: #REF!
Name \H: #REF!
Name \H: #REF!
Name \H: #REF!
Name \J: #REF!
Name \J: #REF!
Name \J: #REF!
Name \J: #REF!
Name \J: #REF!
Name \M: #REF!
Name \M: #REF!
Name \M: #REF!
Name \M: #REF!
Name \M: #REF!
Name \N: #REF!
Name \N: #REF!
Name \N: #REF!
Name \N: #REF!
Name \N: #REF!
Name \P: #REF!
Name \P: #REF!
Name \P: #REF!
Name \P: #REF!
Name \P: #REF!
Name \Q: #REF!
Name \Q: #REF!
Name \Q: #REF!
Name \Q: #REF!
Name \Q: #REF!

Sheet BP Value Comparision
M1: 1st Draft Comparision | P1: 2nd Draft Comparison
A2: Values (Cr.) | C2: FY 24-25 | E2: FY 25-26 | H2: FY 26-27 | M2: Variance BP 26-27 Vs. BP 25-26 (April) | N2: Variance BP 26-27 Vs. BP 25-26 (Aug) | O2: Variance BP 26-27 Vs. Act 25-26 | P2: Variance BP 26-27 Vs. BP 25-26 (April) | Q2: Variance BP 26-27 Vs. BP 25-26 (Aug) | R2: Variance BP 26-27 Vs. Act 25-26 | T2: BP 25-26 Vs. BP 26-27 (2nd V1 Draft)
C3: BP | D3: Act | E3: BP | F3: BP (Aug) | G3: Act | H3: BP (1st Draft) | I3: BP (2nd Draft) | J3: BP (2nd V1 Draft) | K3: 3rd Draft | L3: Act
A4: Dispatch Value (Yearly) | B4: S.F | C4: 702.13 | D4: 576.9 | E4: 554.7 | F4: 472.22 | G4: 502.7601 | H4: 718.06 | I4: 736 | J4: 706.39967 | K4: 714 | M4: =(H4/E4)-1 -> 0.29450153 | N4: =(H4/F4)-1 -> 0.5206048 | O4: =(H4/G4)-1 -> 0.42823585 | P4: =(I4/E4)-1 -> 0.32684334 | Q4: =(I4/F4)-1 -> 0.55859557 | R4: =(I4/G4)-1 -> 0.46391888 | T4: =J4/E4-1 -> 0.27348057
B5: H.F | C5: 433.49 | D5: 208.78 | E5: 183.9 | F5: 130.12 | G5: 70.24 | H5: 38.05 | I5: 53 | J5: 53.239857 | K5: 53 | M5: =(H5/E5)-1 -> -0.79309407 | N5: =(H5/F5)-1 -> -0.70757762 | O5: =(H5/G5)-1 -> -0.45828588 | P5: =(I5/E5)-1 -> -0.71179989 | Q5: =(I5/F5)-1 -> -0.59268368 | R5: =(I5/G5)-1 -> -0.24544419 | T5: =J5/E5-1 -> -0.71049561
B6: Total | C6: =SUM(C4:C5) -> 1135.62 | D6: =SUM(D4:D5) -> 785.68 | E6: =SUM(E4:E5) -> 738.6 | F6: =SUM(F4:F5) -> 602.34 | G6: =SUM(G4:G5) -> 573.0001 | H6: =SUM(H4:H5) -> 756.11 | I6: =SUM(I4:I5) -> 789 | J6: =SUM(J4:J5) -> 759.63953 | K6: =SUM(K4:K5) -> 767 | M6: =(H6/E6)-1 -> 0.023707013 | N6: =(H6/F6)-1 -> 0.25528771 | O6: =(H6/G6)-1 -> 0.31956347 | P6: =(I6/E6)-1 -> 0.068237206 | Q6: =(I6/F6)-1 -> 0.30989142 | R6: =(I6/G6)-1 -> 0.37696311 | T6: =J6/E6-1 -> 0.028485688
A8: Dispatch Value (Monthly) | B8: S.F | C8: =C4/12 -> 58.510833 | D8: =D4/12 -> 48.075 | E8: =E4/12 -> 46.225 | F8: =F4/12 -> 39.351667 | G8: =G4/12 -> 41.896675 | H8: =H4/12 -> 59.838333 | I8: =I4/12 -> 61.333333 | J8: =J4/12 -> 58.866639 | K8: =K4/12 -> 59.5 | M8: =(H8/E8)-1 -> 0.29450153 | N8: =(H8/F8)-1 -> 0.5206048 | O8: =(H8/G8)-1 -> 0.42823585 | P8: =(I8/E8)-1 -> 0.32684334 | Q8: =(I8/F8)-1 -> 0.55859557 | R8: =(I8/G8)-1 -> 0.46391888 | T8: =J8/E8-1 -> 0.27348057
B9: H.F | C9: =C5/12 -> 36.124167 | D9: =D5/12 -> 17.398333 | E9: =E5/12 -> 15.325 | F9: =F5/12 -> 10.843333 | G9: =G5/12 -> 5.8533333 | H9: =H5/12 -> 3.1708333 | I9: =I5/12 -> 4.4166667 | J9: =J5/12 -> 4.4366548 | K9: =K5/12 -> 4.4166667 | M9: =(H9/E9)-1 -> -0.79309407 | N9: =(H9/F9)-1 -> -0.70757762 | O9: =(H9/G9)-1 -> -0.45828588 | P9: =(I9/E9)-1 -> -0.71179989 | Q9: =(I9/F9)-1 -> -0.59268368 | R9: =(I9/G9)-1 -> -0.24544419 | T9: =J9/E9-1 -> -0.71049561
B10: Total | C10: =SUM(C8:C9) -> 94.635 | D10: =SUM(D8:D9) -> 65.473333 | E10: =SUM(E8:E9) -> 61.55 | F10: =SUM(F8:F9) -> 50.195 | G10: =SUM(G8:G9) -> 47.750008 | H10: =SUM(H8:H9) -> 63.009167 | I10: =SUM(I8:I9) -> 65.75 | J10: =SUM(J8:J9) -> 63.303294 | K10: =SUM(K8:K9) -> 63.916667 | M10: =(H10/E10)-1 -> 0.023707013 | N10: =(H10/F10)-1 -> 0.25528771 | O10: =(H10/G10)-1 -> 0.31956347 | P10: =(I10/E10)-1 -> 0.068237206 | Q10: =(I10/F10)-1 -> 0.30989142 | R10: =(I10/G10)-1 -> 0.37696311 | T10: =J10/E10-1 -> 0.028485688
A12: Avg Daily Deployment | B12: S.F. | C12: 1773 | D12: 1660 | E12: 1589.6667 | G12: 1561 | H12: 1607 | I12: 1642.2083 | J12: 1593.875 | T12: =J12/E12-1 -> 0.0026473055
B13: H.F. | C13: 529 | D13: 373 | E13: 245 | G13: 178 | H13: 66 | I13: 66 | J13: 66 | T13: =J13/E13-1 -> -0.73061224
B14: Total | C14: =SUM(C12:C13) -> 2302 | D14: =SUM(D12:D13) -> 2033 | E14: =SUM(E12:E13) -> 1834.6667 | G14: =SUM(G12:G13) -> 1739 | H14: =SUM(H12:H13) -> 1673 | I14: =SUM(I12:I13) -> 1708.2083 | J14: =SUM(J12:J13) -> 1659.875 | T14: =J14/E14-1 -> -0.095271621
A18: Values (Cr.) | C18: BP (1st Draft) | D18: BP (2nd Draft) | E18: BP (2nd V1 Draft)
A20: Dispatch Value (Yearly) | B20: S.F | C20: 718.06 | D20: 736 | E20: 706.39967
B21: H.F | C21: 38.05 | D21: 53 | E21: 53.239857
B22: Total | C22: =SUM(C20:C21) -> 756.11 | D22: =SUM(D20:D21) -> 789 | E22: =SUM(E20:E21) -> 759.63953
A24: Dispatch Value (Monthly) | B24: S.F | C24: =C20/12 -> 59.838333 | D24: =D20/12 -> 61.333333 | E24: =E20/12 -> 58.866639
B25: H.F | C25: =C21/12 -> 3.1708333 | D25: =D21/12 -> 4.4166667 | E25: =E21/12 -> 4.4366548
B26: Total | C26: =SUM(C24:C25) -> 63.009167 | D26: =SUM(D24:D25) -> 65.75 | E26: =SUM(E24:E25) -> 63.303294
A29: Avg Daily Deployment | B29: HC | C29: BP (1st Draft) | D29: BP (2nd Draft) | E29: BP (2nd V1 Draft)
B31: S.F. | C31: 1609 | D31: 1642.2083 | E31: 1593.875
B32: H.F. | C32: 66 | D32: 66 | E32: 66
A33: Total | C33: =SUM(C31:C32) -> 1675 | D33: =SUM(D31:D32) -> 1708.2083 | E33: =SUM(E31:E32) -> 1659.875
A35: Production Planning (Yearly Avg.) | B35: Tufting (SQM) | C35: 1293651.6 | D35: 1425035.1 | E35: 1332969.6
B36: CT | C36: =C40 -> 188021.93 | D36: =D40 -> 180072.81 | E36: =E40 -> 180072.81
B37: W2W | C37: =C41 -> 185651.88 | D37: =D41 -> 186607.73 | E37: =E41 -> 186160.71
B38: AR | C38: =C42+C43 -> 919977.82 | D38: =D42+D43 -> 1058354.5 | E38: =E42+E43 -> 966736.09
B39: Inhouse (AR+W2W+CT) | C39: =SUM(C40:C42) -> 648616.84 | D39: =SUM(D40:D42) -> 620856.68 | E39: =SUM(E40:E42) -> 619313.42
B40: CT | C40: 188021.93 | D40: 180072.81 | E40: 180072.81
B41: W2W | C41: 185651.88 | D41: 186607.73 | E41: 186160.71
B42: AR | C42: 274943.03 | D42: 254176.14 | E42: 253079.89
B43: Vapi | C43: =C35-C39 -> 645034.79 | D43: =D35-D39 -> 804178.41 | E43: =E35-E39 -> 713656.19
C46: =C35/30.5/C31 -> 26.360974 | D46: =D35/30.5/D31 -> 28.450995 | E46: =E35/30.5/E31 -> 27.419918
T48: Values (Cr.) | V48: FY 26-27
V49: BP (1st Draft) | W49: BP (2nd Draft) | X49: BP (2nd V1 Draft) | Y49: HC 1st Draft | Z49: HC 2nd Draft | AA49: HC 2nd V1 Draft
T50: Dispatch Value (Yearly) | U50: S.F | V50: 718 | W50: 736 | X50: 706.39967 | Y50: 1,609 | Z50: 1,642 | AA50: 1593.875
U51: H.F | V51: 38 | W51: 53 | X51: 53.239857 | Y51: 66 | Z51: 66 | AA51: 66
U52: Total | V52: 756 | W52: 789 | X52: 759.63953 | Y52: 1,675 | Z52: 1,708 | AA52: =SUM(AA50:AA51) -> 1659.875

Sheet Comparison BP 25-26 Vs 26-27 
A1: Plant | B1: BP 2025-26 | O1: BP 2026-27 (2nd V1 Draft)
B2: Avg/Day | M2: =ROUNDUP(G2*J2,0)*+M2:M39I2 -> #NAME? | O2: Avg/Day
B3: Section | C3: Capacity | D3: UoM | E3: Prod/Day | F3: HC/Day | G3: Remarks | H3: Associate | I3: NAPs | J3: CLM - MD | K3: CLM - PR | L3: Total | O3: ='Workmen Category'!A2 -> Section | P3: ='Workmen Category'!BW2 -> Avg Prodn | Q3: ='Workmen Category'!BX2 -> Avg | R3: ='Workmen Category'!BY2 -> Associate | S3: ='Workmen Category'!BZ2 -> NAPs | T3: ='Workmen Category'!CA2 -> CLM - MD | U3: ='Workmen Category'!CB2 -> CLM - PR | V3: ='Workmen Category'!CC2 -> Total | W3: ='Workmen Category'!CD2 -> Remarks | X3: Note
A4: S.F. | B4: 1. POY | C4: ='Monthly HC & Prodn Working'!C3 -> 32121.952 | D4: Kg | E4: 26855.666 | F4: 41 | G4: All | H4: 35 | I4: 3.1666667 | J4: 2.8333333 | L4: =SUM(H4:K4) -> 41 | O4: ='Workmen Category'!A3 -> 1. POY | P4: ='Workmen Category'!BW3 -> 37828.86 | Q4: ='Workmen Category'!BX3 -> 43 | R4: ='Workmen Category'!BY3 -> 35 | S4: ='Workmen Category'!BZ3 -> 5 | T4: ='Workmen Category'!CA3 -> 3 | U4: ='Workmen Category'!CB3 | V4: ='Workmen Category'!CC3 -> 43 | W4: ='Workmen Category'!CD3 -> All
A5: S.F. | B5: 2. BCF | C5: ='Monthly HC & Prodn Working'!C4 -> 21686.572 | D5: Kg | E5: 11436.447 | F5: 34.333333 | G5: 10 Winder | H5: 26 | I5: 5.3333333 | J5: 3 | L5: =SUM(H5:K5) -> 34.333333 | O5: ='Workmen Category'!A4 -> 2. BCF | P5: ='Workmen Category'!BW4 -> 11641.995 | Q5: ='Workmen Category'!BX4 -> 28.166667 | R5: ='Workmen Category'!BY4 -> 20.666667 | S5: ='Workmen Category'!BZ4 -> 4.5 | T5: ='Workmen Category'!CA4 -> 3 | U5: ='Workmen Category'!CB4 | V5: ='Workmen Category'!CC4 -> 28.166667 | W5: ='Workmen Category'!CD4 -> 11 Winder | X5: Winder Operator Utilized from POY. Multitasking
A6: S.F. | B6: 3. Texturizing | C6: ='Monthly HC & Prodn Working'!C5 -> 29388.133 | D6: Kg | E6: 26560.254 | F6: 83.333333 | G6: All | H6: 49 | I6: 24 | J6: 9 | L6: =SUM(H6:K6) -> 82 | O6: ='Workmen Category'!A5 -> 3. Texturizing | P6: ='Workmen Category'!BW5 -> 37771.136 | Q6: ='Workmen Category'!BX5 -> 84 | R6: ='Workmen Category'!BY5 | S6: ='Workmen Category'!BZ5 | T6: ='Workmen Category'!CA5 | U6: ='Workmen Category'!CB5 -> 84 | V6: ='Workmen Category'!CC5 -> 84 | W6: ='Workmen Category'!CD5 -> All | X6: 49 Associate, 24 NAPs & 9 CLM-MD Converted to CLM-PR
A7: S.F. | B7: 4. Parallel Winding | C7: ='Monthly HC & Prodn Working'!C6 -> 14098.76 | D7: Kg | E7: 14168.365 | F7: 27 | G7: All | H7: 6 | I7: 21 | L7: =SUM(H7:K7) -> 27 | O7: ='Workmen Category'!A6 -> 4. Parallel Winding | P7: ='Workmen Category'!BW6 -> 21152.914 | Q7: ='Workmen Category'!BX6 -> 27 | R7: ='Workmen Category'!BY6 | S7: ='Workmen Category'!BZ6 | T7: ='Workmen Category'!CA6 | U7: ='Workmen Category'!CB6 -> 27 | V7: ='Workmen Category'!CC6 -> 27 | W7: ='Workmen Category'!CD6 -> All | X7: 6 Associate, 21 CLM-MD Converted to CLM-PR
A8: S.F. | B8: Rewinding | C8: ='Monthly HC & Prodn Working'!C7 -> 0 | D8: Kg | F8: 14 | H8: 2 | I8: 0 | J8: 12 | L8: =SUM(H8:K8) -> 14 | O8: ='Workmen Category'!A7 -> Rewinding | P8: ='Workmen Category'!BW7 -> 0 | Q8: ='Workmen Category'!BX7 -> 15 | R8: ='Workmen Category'!BY7 -> 2 | S8: ='Workmen Category'!BZ7 | T8: ='Workmen Category'!CA7 -> 13 | U8: ='Workmen Category'!CB7 | V8: ='Workmen Category'!CC7 -> 15 | W8: ='Workmen Category'!CD7 -> 0
A9: S.F. | B9: 5. Multiply | C9: ='Monthly HC & Prodn Working'!C8 -> 11869.222 | D9: Kg | E9: 3925.8343 | F9: 104 | K9: 104 | L9: =SUM(H9:K9) -> 104 | O9: ='Workmen Category'!A8 -> 5. Multiply | P9: ='Workmen Category'!BW8 -> 4829.4533 | Q9: ='Workmen Category'!BX8 -> 124.16667 | R9: ='Workmen Category'!BY8 | S9: ='Workmen Category'!BZ8 | T9: ='Workmen Category'!CA8 | U9: ='Workmen Category'!CB8 -> 124.16667 | V9: ='Workmen Category'!CC8 -> 124.16667 | W9: ='Workmen Category'!CD8 -> 0
A10: S.F. | B10: TFO | C10: ='Monthly HC & Prodn Working'!C9 -> 0 | D10: Kg | E10: 5598.9241 | L10: =SUM(H10:K10) -> 0 | O10: ='Workmen Category'!A9 -> TFO | P10: ='Workmen Category'!BW9 -> 7407.3248 | Q10: ='Workmen Category'!BX9 -> 0 | R10: ='Workmen Category'!BY9 | S10: ='Workmen Category'!BZ9 | T10: ='Workmen Category'!CA9 | U10: ='Workmen Category'!CB9 | V10: ='Workmen Category'!CC9 -> 0 | W10: ='Workmen Category'!CD9 -> 0
A11: S.F. | B11: Auto Clave | C11: ='Monthly HC & Prodn Working'!C10 -> 0 | D11: Kg | E11: 1838.4291 | L11: =SUM(H11:K11) -> 0 | O11: ='Workmen Category'!A10 -> Auto Clave | P11: ='Workmen Category'!BW10 -> 2577.8715 | Q11: ='Workmen Category'!BX10 -> 0 | R11: ='Workmen Category'!BY10 | S11: ='Workmen Category'!BZ10 | T11: ='Workmen Category'!CA10 | U11: ='Workmen Category'!CB10 | V11: ='Workmen Category'!CC10 -> 0 | W11: ='Workmen Category'!CD10 -> 0
A12: S.F. | B12: 6. Cabling | C12: ='Monthly HC & Prodn Working'!C11 -> 39644.343 | D12: Kg | E12: 29084.556 | F12: 63.75 | G12: 18 M/C | H12: 34 | I12: 26.75 | J12: 3 | L12: =SUM(H12:K12) -> 63.75 | O12: ='Workmen Category'!A11 -> 6. Cabling | P12: ='Workmen Category'!BW11 -> 36103.398 | Q12: ='Workmen Category'!BX11 -> 64.166667 | R12: ='Workmen Category'!BY11 | S12: ='Workmen Category'!BZ11 | T12: ='Workmen Category'!CA11 | U12: ='Workmen Category'!CB11 -> 64.166667 | V12: ='Workmen Category'!CC11 -> 64.166667 | W12: ='Workmen Category'!CD11 -> 18 M/C | X12: 34 Associate, 27 NAPs, 3 CLM MD Converted to CLM-PR
A13: S.F. | B13: 7. Heat Set | C13: ='Monthly HC & Prodn Working'!C12 -> 22591.213 | D13: Kg | E13: 31488.175 | F13: 80.333333 | G13: 6 M/C | H13: 40 | I13: 39 | J13: 0.33333333 | L13: =SUM(H13:K13) -> 79.333333 | O13: ='Workmen Category'!A12 -> 7. Heat Set | P13: ='Workmen Category'!BW12 -> 33603.811 | Q13: ='Workmen Category'!BX12 -> 59.916667 | R13: ='Workmen Category'!BY12 -> 42 | S13: ='Workmen Category'!BZ12 -> 30.166667 | T13: ='Workmen Category'!CA12 -> 6.6666667 | U13: ='Workmen Category'!CB12 | V13: ='Workmen Category'!CC12 -> 78.833333 | W13: ='Workmen Category'!CD12 -> 5 M/C
A14: S.F. | B14: Yarn Common | C14: ='Monthly HC & Prodn Working'!C13 -> 0 | F14: 24 | H14: 1 | I14: 0 | J14: 6 | K14: 17 | L14: =SUM(H14:K14) -> 24 | O14: ='Workmen Category'!A13 -> Yarn Common | P14: ='Workmen Category'!BW13 -> 0 | Q14: ='Workmen Category'!BX13 -> 24 | R14: ='Workmen Category'!BY13 | S14: ='Workmen Category'!BZ13 | T14: ='Workmen Category'!CA13 -> 6 | U14: ='Workmen Category'!CB13 -> 18 | V14: ='Workmen Category'!CC13 -> 24 | W14: ='Workmen Category'!CD13 -> 0
A15: S.F. | B15: Master Batch | C15: ='Monthly HC & Prodn Working'!C14 -> 0 | D15: Kg | E15: 1124.3683 | F15: 30 | H15: 20.5 | I15: 9.5 | L15: =SUM(H15:K15) -> 30 | O15: ='Workmen Category'!A14 -> Master Batch | P15: ='Workmen Category'!BW14 -> 0 | Q15: ='Workmen Category'!BX14 -> 31 | R15: ='Workmen Category'!BY14 -> 20 | S15: ='Workmen Category'!BZ14 -> 11 | T15: ='Workmen Category'!CA14 | U15: ='Workmen Category'!CB14 | V15: ='Workmen Category'!CC14 -> 31 | W15: ='Workmen Category'!CD14 -> 0
A16: S.F. | B16: 8. Tufting | C16: ='Monthly HC & Prodn Working'!C15 -> 63821.5 | D16: SQM | E16: 39197.819 | F16: 171.25 | G16: 15 M/C | H16: 58 | I16: 64.666667 | J16: 36.833333 | K16: 12 | L16: =SUM(H16:K16) -> 171.5 | O16: ='Workmen Category'!A15 -> 8. Tufting | P16: ='Workmen Category'!BW15 -> 46120.959 | Q16: ='Workmen Category'!BX15 -> 165 | R16: ='Workmen Category'!BY15 -> 60 | S16: ='Workmen Category'!BZ15 -> 66 | T16: ='Workmen Category'!CA15 -> 27 | U16: ='Workmen Category'!CB15 -> 12 | V16: ='Workmen Category'!CC15 -> 165 | W16: ='Workmen Category'!CD15 -> 13 M/C | X16: Prodution on High Output M/C increases
A17: S.F. | B17: 9.1 Printing - Chromojet | C17: ='Monthly HC & Prodn Working'!C16 -> 3314.4422 | D17: SQM | E17: 3507.6153 | F17: 38 | G17: 2.33 Shift | H17: 19 | I17: 19 | L17: =SUM(H17:K17) -> 38 | O17: ='Workmen Category'!A16 -> 9.1 Printing - Chromojet | P17: ='Workmen Category'!BW16 -> 4691.4354 | Q17: ='Workmen Category'!BX16 -> 48.5 | R17: ='Workmen Category'!BY16 -> 30.166667 | S17: ='Workmen Category'!BZ16 -> 15.333333 | T17: ='Workmen Category'!CA16 -> 3 | U17: ='Workmen Category'!CB16 | V17: ='Workmen Category'!CC16 -> 48.5 | W17: ='Workmen Category'!CD16 -> 3 Shift
A18: S.F. | B18: 9.2 Printing - Digital | C18: ='Monthly HC & Prodn Working'!C17 -> 2480.0256 | D18: SQM | E18: 910.8 | G18: 1 Shift | L18: =SUM(H18:K18) -> 0 | O18: ='Workmen Category'!A17 -> 9.2 Printing - Digital | P18: ='Workmen Category'!BW17 -> 1415.1439 | Q18: ='Workmen Category'!BX17 -> 0 | R18: ='Workmen Category'!BY17 | S18: ='Workmen Category'!BZ17 | T18: ='Workmen Category'!CA17 | U18: ='Workmen Category'!CB17 | V18: ='Workmen Category'!CC17 -> 0 | W18: ='Workmen Category'!CD17 -> 2.36 Shift
A19: S.F. | B19: 10.1 Carpet Tiles | C19: ='Monthly HC & Prodn Working'!C18 -> 14758.225 | D19: SQM | E19: 4744.4612 | F19: 91.5 | G19: 1 Shift | H19: 52 | I19: 26 | J19: 13.5 | L19: =SUM(H19:K19) -> 91.5 | O19: ='Workmen Category'!A18 -> 10.1 Carpet Tiles | P19: ='Workmen Category'!BW18 -> 5002.3714 | Q19: ='Workmen Category'!BX18 -> 108.5 | R19: ='Workmen Category'!BY18 -> 58.833333 | S19: ='Workmen Category'!BZ18 -> 32.5 | T19: ='Workmen Category'!CA18 -> 16.333333 | U19: ='Workmen Category'!CB18 | V19: ='Workmen Category'!CC18 -> 107.66667 | W19: ='Workmen Category'!CD18 -> 1.75 Shift | X19: Consider 6 HC for TPR Line
A20: S.F. | B20: 10.2 W2W | C20: ='Monthly HC & Prodn Working'!C19 -> 19608.37 | D20: SQM | E20: 13754.529 | G20: 2 Shift | L20: =SUM(H20:K20) -> 0 | O20: ='Workmen Category'!A19 -> 10.2 W2W | P20: ='Workmen Category'!BW19 -> 18816.099 | Q20: ='Workmen Category'!BX19 -> 0 | R20: ='Workmen Category'!BY19 | S20: ='Workmen Category'!BZ19 | T20: ='Workmen Category'!CA19 | U20: ='Workmen Category'!CB19 | V20: ='Workmen Category'!CC19 -> 0 | W20: ='Workmen Category'!CD19 -> 2.72 Shift
A21: S.F. | B21: CSP | C21: ='Monthly HC & Prodn Working'!C20 -> 11666.667 | D21: SQM | E21: 7360.7232 | F21: 244.16667 | H21: 33 | I21: 35.416667 | J21: 45.75 | K21: 130 | L21: =SUM(H21:K21) -> 244.16667 | O21: ='Workmen Category'!A20 -> CSP | P21: ='Workmen Category'!BW20 -> 9900.8122 | Q21: ='Workmen Category'!BX20 -> 265.70833 | R21: ='Workmen Category'!BY20 -> 42 | S21: ='Workmen Category'!BZ20 -> 34 | T21: ='Workmen Category'!CA20 -> 0 | U21: ='Workmen Category'!CB20 -> 189.70833 | V21: ='Workmen Category'!CC20 -> 265.70833 | W21: ='Workmen Category'!CD20 -> 0
A22: S.F. | B22: Process Control | F22: 12 | I22: 12 | L22: =SUM(H22:K22) -> 12 | O22: ='Workmen Category'!A21 -> Process Control | P22: ='Workmen Category'!BW21 -> 0 | Q22: ='Workmen Category'!BX21 -> 12 | R22: ='Workmen Category'!BY21 -> 8 | S22: ='Workmen Category'!BZ21 -> 4 | T22: ='Workmen Category'!CA21 | U22: ='Workmen Category'!CB21 | V22: ='Workmen Category'!CC21 -> 12 | W22: ='Workmen Category'!CD21 -> 0
A23: S.F. | B23: TQM | F23: 84 | H23: 45 | I23: 39 | J23: 0 | K23: 0 | L23: =SUM(H23:K23) -> 84 | O23: ='Workmen Category'!A22 -> TQM | P23: ='Workmen Category'!BW22 -> 0 | Q23: ='Workmen Category'!BX22 -> 93 | R23: ='Workmen Category'!BY22 -> 53 | S23: ='Workmen Category'!BZ22 -> 40 | T23: ='Workmen Category'!CA22 | U23: ='Workmen Category'!CB22 | V23: ='Workmen Category'!CC22 -> 93 | W23: ='Workmen Category'!CD22 -> 0 | X23: Added 3 TQM for 1 Packing Line, 3 For Printing and 3 For CT
A24: S.F. | B24: Engg. | F24: 50 | H24: 48 | I24: 2 | J24: 0 | K24: 0 | L24: =SUM(H24:K24) -> 50 | O24: ='Workmen Category'!A23 -> Engg. | P24: ='Workmen Category'!BW23 -> 0 | Q24: ='Workmen Category'!BX23 -> 50 | R24: ='Workmen Category'!BY23 -> 40 | S24: ='Workmen Category'!BZ23 -> 5 | T24: ='Workmen Category'!CA23 -> 5 | U24: ='Workmen Category'!CB23 | V24: ='Workmen Category'!CC23 -> 50 | W24: ='Workmen Category'!CD23 -> 0
A25: S.F. | B25: Engg. | F25: 63 | H25: 31 | I25: 2 | J25: 30 | L25: =SUM(H25:K25) -> 63 | O25: ='Workmen Category'!A24 -> Engg. | P25: ='Workmen Category'!BW24 -> 0 | Q25: ='Workmen Category'!BX24 -> 63 | R25: ='Workmen Category'!BY24 -> 32 | S25: ='Workmen Category'!BZ24 -> 8 | T25: ='Workmen Category'!CA24 -> 11 | U25: ='Workmen Category'!CB24 -> 12 | V25: ='Workmen Category'!CC24 -> 63 | W25: ='Workmen Category'!CD24 -> 0
A26: S.F. | B26: R&D (PD) | F26: 33 | H26: 21 | I26: 5 | J26: 7 | L26: =SUM(H26:K26) -> 33 | O26: ='Workmen Category'!A25 -> R&D (PD) | P26: ='Workmen Category'!BW25 -> 0 | Q26: ='Workmen Category'!BX25 -> 38 | R26: ='Workmen Category'!BY25 -> 22 | S26: ='Workmen Category'!BZ25 -> 9 | T26: ='Workmen Category'!CA25 -> 7 | U26: ='Workmen Category'!CB25 | V26: ='Workmen Category'!CC25 -> 38 | W26: ='Workmen Category'!CD25 -> 0 | X26: 1 HC in Yarn, 1 in Tufting and 3 in M-Tuft
A27: S.F. | B27: SCM (Stores & WH) | F27: 72 | H27: 29 | I27: 5 | J27: 38 | L27: =SUM(H27:K27) -> 72 | O27: ='Workmen Category'!A26 -> SCM (Stores & WH) | P27: ='Workmen Category'!BW26 -> 0 | Q27: ='Workmen Category'!BX26 -> 70 | R27: ='Workmen Category'!BY26 -> 28 | S27: ='Workmen Category'!BZ26 -> 5 | T27: ='Workmen Category'!CA26 -> 37 | U27: ='Workmen Category'!CB26 | V27: ='Workmen Category'!CC26 -> 70 | W27: ='Workmen Category'!CD26 -> 0
A28: S.F. | B28: SCM (Stores & WH) | F28: 30 | H28: 2 | I28: 0 | J28: 2 | K28: 26 | L28: =SUM(H28:K28) -> 30 | O28: ='Workmen Category'!A27 -> SCM (Stores & WH) | P28: ='Workmen Category'!BW27 -> 0 | Q28: ='Workmen Category'!BX27 -> 30 | R28: ='Workmen Category'!BY27 -> 2 | S28: ='Workmen Category'!BZ27 | T28: ='Workmen Category'!CA27 -> 2 | U28: ='Workmen Category'!CB27 -> 26 | V28: ='Workmen Category'!CC27 -> 30 | W28: ='Workmen Category'!CD27 -> 0
A29: S.F. | B29: Common | F29: 199 | H29: 28 | I29: 7 | J29: 165 | L29: =SUM(H29:K29) -> 200 | O29: ='Workmen Category'!A28 -> Common | P29: ='Workmen Category'!BW28 -> 0 | Q29: ='Workmen Category'!BX28 -> 175 | R29: ='Workmen Category'!BY28 -> 30 | S29: ='Workmen Category'!BZ28 -> 5 | T29: ='Workmen Category'!CA28 -> 140 | U29: ='Workmen Category'!CB28 | V29: ='Workmen Category'!CC28 -> 175 | W29: ='Workmen Category'!CD28 -> 0 | X29: 2 Reduce in PPC, and 14 in Common Admin
O30: ='Workmen Category'!A29 -> 0
A31: S.F. | B31: Total | F31: =SUM(F4:F29) -> 1589.6667 | H31: =SUM(H4:H29) -> 579.5 | I31: =SUM(I4:I29) -> 345.83333 | J31: =SUM(J4:J29) -> 374.25 | K31: =SUM(K4:K29) -> 289 | L31: =SUM(L4:L29) -> 1588.5833 | Q31: =SUM(Q4:Q29) -> 1619.125 | R31: =SUM(R4:R29) -> 525.66667 | S31: =SUM(S4:S29) -> 274.5 | T31: =SUM(T4:T29) -> 280 | U31: =SUM(U4:U29) -> 557.04167 | V31: =SUM(V4:V29) -> 1637.2083
A36: H.F. | B36: TQM | F36: 34 | H36: 23 | I36: 11 | J36: 0 | K36: 0 | L36: =SUM(H36:K36) -> 34 | O36: ='Workmen Category'!A32 -> TQM | P36: ='Workmen Category'!BW32 -> 0 | Q36: ='Workmen Category'!BX32 -> 4 | R36: ='Workmen Category'!BY32 -> 4 | S36: ='Workmen Category'!BZ32 | T36: ='Workmen Category'!CA32 | U36: ='Workmen Category'!CB32 | V36: ='Workmen Category'!CC32 -> 4 | W36: ='Workmen Category'!CD32 -> 0
A37: H.F. | B37: Engg. | F37: 20 | H37: 20 | I37: 0 | J37: 0 | K37: 0 | L37: =SUM(H37:K37) -> 20 | O37: ='Workmen Category'!A33 -> Engg. | P37: ='Workmen Category'!BW33 -> 0 | Q37: ='Workmen Category'!BX33 -> 4 | R37: ='Workmen Category'!BY33 -> 4 | S37: ='Workmen Category'!BZ33 | T37: ='Workmen Category'!CA33 | U37: ='Workmen Category'!CB33 | V37: ='Workmen Category'!CC33 -> 4 | W37: ='Workmen Category'!CD33 -> 0
A38: H.F. | B38: R&D (PD) | F38: 6 | H38: 5.97 | I38: 0 | J38: 0 | K38: 0 | L38: =SUM(H38:K38) -> 5.97 | O38: ='Workmen Category'!A34 -> R&D (PD) | P38: ='Workmen Category'!BW34 -> 0 | Q38: ='Workmen Category'!BX34 -> 0 | R38: ='Workmen Category'!BY34 | S38: ='Workmen Category'!BZ34 | T38: ='Workmen Category'!CA34 | U38: ='Workmen Category'!CB34 | V38: ='Workmen Category'!CC34 -> 0 | W38: ='Workmen Category'!CD34 -> 0
A39: H.F. | L39: =SUM(H39:K39) -> 0 | O39: ='Workmen Category'!A35 -> Common | P39: ='Workmen Category'!BW35 -> 0 | Q39: ='Workmen Category'!BX35 -> 8 | R39: ='Workmen Category'!BY35 | S39: ='Workmen Category'!BZ35 | T39: ='Workmen Category'!CA35 -> 8 | U39: ='Workmen Category'!CB35 | V39: ='Workmen Category'!CC35 -> 8 | W39: ='Workmen Category'!CD35 -> 0
A40: H.F. | B40: SCM (Stores & WH) | F40: 20 | H40: 8.4098361 | I40: 1 | J40: 10.557377 | L40: =SUM(H40:K40) -> 19.967213 | O40: ='Workmen Category'!A36 -> SCM (Stores & WH) | P40: ='Workmen Category'!BW36 -> 0 | Q40: ='Workmen Category'!BX36 -> 4 | R40: ='Workmen Category'!BY36 -> 4 | S40: ='Workmen Category'!BZ36 | T40: ='Workmen Category'!CA36 | U40: ='Workmen Category'!CB36 | V40: ='Workmen Category'!CC36 -> 4 | W40: ='Workmen Category'!CD36 -> 0
A41: H.F. | B41: SPC | E41: 8131.8648 | F41: 165 | H41: 65.557377 | I41: 35 | J41: 50 | K41: 14 | L41: =SUM(H41:K41) -> 164.55738 | O41: ='Workmen Category'!A37 -> SPC | P41: ='Workmen Category'!BW37 -> 0 | Q41: ='Workmen Category'!BX37 -> 46 | R41: ='Workmen Category'!BY37 -> 20 | S41: ='Workmen Category'!BZ37 | T41: ='Workmen Category'!CA37 -> 12 | U41: ='Workmen Category'!CB37 -> 14 | V41: ='Workmen Category'!CC37 -> 46 | W41: ='Workmen Category'!CD37 -> 0
A42: H.F. | B42: Total | F42: =SUM(F36:F41) -> 245 | H42: =SUM(H36:H41) -> 122.93721 | I42: =SUM(I36:I41) -> 47 | J42: =SUM(J36:J41) -> 60.557377 | K42: =SUM(K36:K41) -> 14 | L42: =SUM(L36:L41) -> 244.49459 | P42: ='Workmen Category'!BW38 -> 0 | Q42: =SUM(Q36:Q41) -> 66 | R42: ='Workmen Category'!BY38 -> 32 | S42: ='Workmen Category'!BZ38 -> 0 | T42: ='Workmen Category'!CA38 -> 20 | U42: ='Workmen Category'!CB38 -> 14 | V42: ='Workmen Category'!CC38 -> 66 | W42: ='Workmen Category'!CD38 -> 0
P43: ='Workmen Category'!BW39 -> 0 | Q43: ='Workmen Category'!BX39 -> 0 | R43: ='Workmen Category'!BY39 -> 0 | S43: ='Workmen Category'!BZ39 -> 0 | T43: ='Workmen Category'!CA39 -> 0 | U43: ='Workmen Category'!CB39 -> 0 | V43: ='Workmen Category'!CC39 -> 0 | W43: ='Workmen Category'!CD39 -> 0
B44: Grand Total | F44: =F42+F31 -> 1834.6667 | H44: =H42+H31 -> 702.43721 | I44: =I42+I31 -> 392.83333 | J44: =J42+J31 -> 434.80738 | K44: =K42+K31 -> 303 | L44: =L42+L31 -> 1833.0779 | P44: ='Workmen Category'!BW40 -> 0 | Q44: =Q42+Q31 -> 1685.125 | R44: ='Workmen Category'!BY40 -> 557.66667 | S44: ='Workmen Category'!BZ40 -> 274.5 | T44: ='Workmen Category'!CA40 -> 300 | U44: ='Workmen Category'!CB40 -> 571.04167 | V44: ='Workmen Category'!CC40 -> 1703.2083 | W44: ='Workmen Category'!CD40 -> 0
I54: Assosiates | J54: 702.43721
I55: Naps | J55: 397.58333
I56: Contractor- MD | J56: 431.80738
I57: Contractor- PR | J57: 303
H59: =SUM(H60:H63) -> 29 | I59: =SUM(I60:I63) -> 5 | J59: =SUM(J60:J63) -> 38
H60: 5 | I60: 0 | J60: 4
H61: 9 | I61: 1 | J61: 12
H62: 2 | I62: 0 | J62: 5
H63: 13 | I63: 4 | J63: 17

Sheet BP_Strucured
A1: Machine | B1: 46113 | C1: 46143 | D1: 46174 | E1: 46204 | F1: 46235 | G1: 46266 | H1: 46296 | I1: 46327 | J1: 46357 | K1: 46388 | L1: 46419 | M1: 46447 | N1: Units
A2: BCF | B2: 190053.56 | C2: 227636.66 | D2: 172736.18 | E2: 205578.85 | F2: 250826.71 | G2: 393717.01 | H2: 288952.27 | I2: 367132.62 | J2: 677193.28 | K2: 528044.36 | L2: 487687.57 | M2: 451556.32 | N2: kgs
A3: Cabling | B3: 1238788.5 | C3: 1080241.1 | D3: 960682.68 | E3: 1073640.3 | F3: 1193689.2 | G3: 1170212.4 | H3: 1054869.5 | I3: 940619.32 | J3: 1170039.7 | K3: 1163897.3 | L3: 1089413.4 | M3: 1033971.3 | N3: kgs
A4: Power Heat Set | B4: 100470.29 | C4: 77390.829 | D4: 46293.578 | E4: 73043.526 | F4: 77436.854 | G4: 86494.713 | H4: 79944.33 | I4: 125987.81 | J4: 124745.62 | K4: 137266.19 | L4: 131559.38 | M4: 129051.08 | N4: kgs
A5: Superba Heat Set | B5: 1108335.2 | C5: 1028009.1 | D5: 939711.64 | E5: 1001669.9 | F5: 1130540.2 | G5: 1056371.1 | H5: 933369.03 | I5: 920141.58 | J5: 1212098.6 | K5: 992702.54 | L5: 995401.92 | M5: 941464.77 | N5: kgs
A6: POY | B6: 1518410 | C6: 1270519.7 | D6: 1070367.6 | E6: 1503729.6 | F6: 1172241.6 | G6: 1069542.6 | H6: 1159497.9 | I6: 1031857.8 | J6: 1045049.7 | K6: 1046607.1 | L6: 999863.76 | M6: 921180.85 | N6: kgs
A7: Texturizing | B7: 1442558.3 | C7: 1246077.2 | D7: 1159707 | E7: 1249148.5 | F7: 1337464.4 | G7: 1140459.2 | H7: 1164411 | I7: 1032182.3 | J7: 1044370.1 | K7: 1045506.5 | L7: 998580.62 | M7: 924243 | N7: kgs
A8: Parallel Winding | B8: 772731.27 | C8: 674690.76 | D8: 607856.38 | E8: 697292.18 | F8: 657301.78 | G8: 634553.79 | H8: 615480.77 | I8: 549635.61 | J8: 663525.89 | K8: 633577.84 | L8: 603487.24 | M8: 608598.74 | N8: kgs
A9: Multiply | B9: 96546.648 | C9: 133921.53 | D9: 145860.51 | E9: 105972.23 | F9: 150546.85 | G9: 135954.38 | H9: 147220.99 | I9: 212414.35 | J9: 222519.97 | K9: 119372.29 | L9: 156342.53 | M9: 110249.83 | N9: kgs
A10: Autoclave | B10: 72130.301 | C10: 79680.976 | D10: 73191.572 | E10: 82743.929 | F10: 70744.122 | G10: 73504.265 | H10: 78371.572 | I10: 32784.196 | J10: 140570.75 | K10: 87002.911 | L10: 66645.339 | M10: 72988.029 | N10: kgs
A11: Assembly Winder | B11: 168676.95 | C11: 213602.51 | D11: 219052.09 | E11: 188716.16 | F11: 221290.97 | G11: 209458.64 | H11: 225592.56 | I11: 245198.55 | J11: 363090.72 | K11: 206375.2 | L11: 222987.87 | M11: 183237.85 | N11: kgs
A12: TFO | B12: 168676.95 | C12: 213602.51 | D12: 219052.09 | E12: 188716.16 | F12: 221290.97 | G12: 209458.64 | H12: 225592.56 | I12: 245198.55 | J12: 363090.72 | K12: 206375.2 | L12: 222987.87 | M12: 183237.85 | N12: kgs
... A19: CSP | B19: 460411.64 | C19: 318864.59 | D19: 276183.07 | E19: 375130.64 | F19: 636810.08 | G19: 340280.32 | H19: 290110.77 | I19: 238101.82 | J19: 162912.39 | K19: 144536.62 | L19: 179386.84 | M19: 197320.78 | N19: sqm
A20: Tufting

Sheet BP_Structured_edit
B1: 30 | C1: =31 -> 31 | D1: 30 | E1: 31 | F1: =31 -> 31 | G1: 30 | H1: =31 -> 31 | I1: 30 | J1: =31 -> 31 | K1: =31 -> 31 | L1: 28 | M1: =31 -> 31
B3: 46113 | C3: 46143 | D3: 46174 | E3: 46204 | F3: 46235 | G3: 46266 | H3: 46296 | I3: 46327 | J3: 46357 | K3: 46388 | L3: 46419 | M3: 46447 | N3: Total | O3: Avg/month
B4: 0 | C4: 0 | D4: 0 | E4: 0 | F4: 0 | G4: 0 | H4: 0 | I4: 0 | J4: 0 | K4: 0 | L4: 0 | M4: 0 | N4: 0 | O4: 0
B5: 93502.583 | C5: 156349.19 | D5: 155894.34 | E5: 240040.35 | F5: 252484.42 | G5: 425898.28 | H5: 295139.61 | I5: 373256.09 | J5: 347552.23 | K5: 430184.88 | L5: 295307.41 | M5: 322960.19 | N5: =SUM(B5:M5) -> 3388569.6 | O5: =N5/12 -> 282380.8
B6: 0 | C6: 0 | D6: 0 | E6: 0 | F6: 0 | G6: 0 | H6: 0 | I6: 0 | J6: 0 | K6: 0 | L6: 0 | M6: 0 | N6: 0 | O6: 0
B7: 3550.8556 | C7: 3104.1259 | D7: 4368.3216 | E7: 3014.3516 | F7: 4468.8351 | G7: 4754.4686 | H7: 8094.8686 | I7: 5637.3563 | J7: 4656.9542 | K7: 5187.7484 | L7: 8777.0581 | M7: 38294.036 | N7: =SUM(B7:M7) -> 93908.98 | O7: =N7/12 -> 7825.7483
B8: 0 | C8: 0 | D8: 0 | E8: 0 | F8: 0 | G8: 0 | H8: 0 | I8: 0 | J8: 0 | K8: 0 | L8: 0 | M8: 0 | N8: 0 | O8: 0
B9: 69765.141 | C9: 67837.092 | D9: 69765.997 | E9: 76270.706 | F9: 74616.141 | G9: 76560.417 | H9: 91231.484 | I9: 128904.55 | J9: 53179.57 | K9: 88747.834 | L9: 88747.834 | M9: 88747.834 | N9: =SUM(B9:M9) -> 974374.6 | O9: =N9/12 -> 81197.883
B10: 0 | C10: 0 | D10: 0 | E10: 0 | F10: 0 | G10: 0 | H10: 0 | I10: 0 | J10: 0 | K10: 0 | L10: 0 | M10: 0 | N10: 0 | O10: 0
B11: 49343.753 | C11: 52361.053 | D11: 55394.758 | E11: 50057.707 | F11: 46007.516 | G11: 45004.454 | H11: 45505.985 | I11: 51870.413 | J11: 33624.717 | K11: 44001.392 | L11: 41995.269 | M11: 41733.915 | N11: =SUM(B11:M11) -> 556900.93 | O11: =N11/12 -> 46408.411
H12: 0 | I12: 0 | J12: 0 | N12: 0 | O12: 0
H13: 0 | I13: 0 | J13: 0 | N13: 0 | O13: 0
A14: BCF | B14: 190053.56 | C14: 227636.66 | D14: 172736.18 | E14: 205578.85 | F14: 250826.71 | G14: 393717.01 | H14: 288952.27 | I14: 367132.62 | J14: 677193.28 | K14: 528044.36 | L14: 487687.57 | M14: 451556.32 | N14: =SUM(B14:M14) -> 4241115.4 | O14: =N14/12 -> 353426.28 | P14: =O14/30 -> 11780.876
B15: 646787.06 | C15: 668346.63 | D15: 646787.06 | E15: 668346.63 | F15: 646787.06 | G15: 668346.63 | H15: 668346.63 | I15: 646787.06 | J15: 668346.63 | K15: 668346.63 | L15: 603667.92 | M15: 668346.63 | N15: =SUM(B15:M15) -> 7869242.5 | O15: =N15/12 -> 655770.21
B17: 421624.73 | C17: 379395.17 | D17: 352363.65 | E17: 289663.51 | F17: 260210.15 | G17: 106829.01 | H17: 219074.68 | I17: 78118.644 | J17: 220033.16 | K17: 90924.771 | L17: 160440.35 | M17: 167310.66 | N17: =SUM(B17:M17) -> 2745988.5 | O17: =N17/12 -> 228832.37
B19: 0.65187564 | C19: 0.56766228 | D19: 0.54479081 | E19: 0.43340311 | F19: 0.40231192 | G19: 0.15984072 | H19: 0.32778602 | I19: 0.12077954 | J19: 0.32922012 | K19: 0.13604433 | L19: 0.26577584 | M19: 0.25033516 | O19: 0.39903933
B22: 0 | C22: 0 | D22: 0 | E22: 0 | F22: 0 | G22: 0 | H22: 0 | I22: 0 | J22: 0 | K22: 0 | L22: 0 | M22: 0 | N22: 0 | O22: 0
B23: 73225.991 | C23: 119752.5 | D23: 139402.93 | E23: 204824.9 | F23: 230734.55 | G23: 351640.95 | H23: 273657.31 | I23: 332524.17 | J23: 252165.31 | K23: 312268.52 | L23: 236283.51 | M23: 310873.84 | N23: 2837354.5 | O23: 236446.21
B24: 0 | C24: 0 | D24: 0 | E24: 0 | F24: 0 | G24: 0 | H24: 0 | I24: 0 | J24: 0 | K24: 0 | L24: 0 | M24: 0 | N24: 0 | O24: 0
B25: 74880.268 | C25: 47432.121 | D25: 54501.178 | E25: 52934.512 | F25: 63570.312 | G25: 51770.758 | H25: 59857.719 | I25: 58618.213 | J25: 46326.396 | K25: 53846.918 | L25: 69556 | M25: 400974.37 | N25: 1034268.8 | O25: 86189.064
B26: 0 | C26: 0 | D26: 0 | E26: 0 | F26: 0 | G26: 0 | H26: 0 | I26: 0 | J26: 0 | K26: 0 | L26: 0 | M26: 0 | N26: 0 | O26: 0
B27: 24226.279 | C27: 24226.279 | D27: 24226.279 | E27: 27980.323 | F27: 27980.323 | G27: 27980.323 | H27: 31708.45 | I27: 31708.45 | J27: 31708.45 | K27: 29481.893 | L27: 29481.893 | M27: 29481.893 | N27: 340190.84 | O27: 28349.236
B28: 0 | C28: 0 | D28: 0 | E28: 0 | F28: 0 | G28: 0 | H28: 0 | I28: 0 | J28: 0 | K28: 0 | L28: 0 | M28: 0 | N28: 0 | O28: 0
B29: 500285.87 | C29: 547076.73 | D29: 497638.64 | E29: 587007.99 | F29: 553891.09 | G29: 578657.39 | H29: 401379.11 | I29: 561813.2 | J29: 581515.61 | K29: 530280.42 | L29: 535627.22 | M29: 527711.44 | N29: 6402884.7 | O29: 533573.73
A30: Cabling | B30: 1238788.5 | C30: 1080241.1 | D30: 960682.68 | E30: 1073640.3 | F30: 1193689.2 | G30: 1170212.4 | H30: 1054869.5 | I30: 940619.32 | J30: 1170039.7 | K30: 1163897.3 | L30: 1089413.4 | M30: 1033971.3 | N30: =SUM(B30:M30) -> 13170065 | P30: =O30/30 -> 0
B31: 0 | C31: 0 | D31: 0 | E31: 0 | F31: 0 | G31: 0 | H31: 0 | I31: 0 | J31: 0 | K31: 0 | L31: 0 | M31: 0 | N31: 0 | O31: 0
B32: 0 | C32: 0 | D32: 0 | E32: 0 | F32: 0 | G32: 0 | H32: 0 | I32: 0 | J32: 0 | K32: 0 | L32: 0 | M32: 0 | N32: 0 | O32: 0
B33: 1077934.5 | C33: 1113865.6 | D33: 1077934.5 | E33: 1113865.6 | F33: 1077934.5 | G33: 1113865.6 | H33: 1113865.6 | I33: 1077934.5 | J33: 1113865.6 | K33: 1113865.6 | L33: 1006072.2 | M33: 1113865.6 | N33: 13114869 | O33: 1092905.8
B34: 405316.06 | C34: 375377.99 | D34: 362165.44 | E34: 241117.89 | F34: 201758.2 | G34: 103816.2 | H34: 347263.02 | I34: 93270.439 | J34: 202149.85 | K34: 187987.87 | L34: 135123.54 | M34: -155175.92 | N34: 2500170.6 | O34: 208347.55
B35: 0 | C35: 0 | D35: 0 | N35: 0 | O35: 0
B36: 22420.613 | C36: 23822.182 | D36: 23858.968 | E36: 28153.152 | F36: 29205.876 | G36: 32582.239 | H36: 24729.116 | I36: 32822.134 | J36: 29410.186 | K36: 29867.024 | L36: 31105.308 | M36: 40936.824 | N36: 348913.62 | O36: 29076.135
B37: 672618.4 | C37: 738487.63 | D37: 715769.03 | E37: 872747.73 | F37: 876176.27 | G37: 1010049.4 | H37: 766602.59 | I37: 984664.03 | J37: 911715.76 | K37: 925877.75 | L37: 870948.63 | M37: 1269041.5 | N37: 10614699 | O37: 884558.23
B38: 22420.613 | C38: 23822.182 | D38: 23858.968 | E38: 28153.152 | F38: 29205.876 | G38: 32582.239 | H38: 24729.116 | I38: 32822.134 | J38: 29410.186 | K38: 29867.024 | L38: 31105.308 | M38: 40936.824 | N38: 348913.62 | O38: 29076.135
B39: 0.37601179 | C39: 0.33700473 | D39: 0.33598094 | E39: 0.21646946 | F39: 0.18717112 | G39: 0.093203521 | H39: 0.31176384 | I39: 0.086527003 | J39: 0.18148496 | K39: 0.16877069 | L39: 0.134308 | M39: -0.13931297 | O39: 0.19063633
B41: 0 | C41: 0 | D41: 0 | E41: 0 | F41: 0 | G41: 0 | H41: 0 | I41: 0 | J41: 0 | K41: 0 | L41: 0 | M41: 0 | N41: 0 | O41: 0
B42: 12842.152 | C42: 49703.587 | D42: 72948.36 | E42: 77053.363 | F42: 87932.922 | G42: 147412.56 | H42: 116284.38 | I42: 81541.796 | J42: 147545.03 | K42: 89597.309 | L42: 110332.44 | M42: 123683.37 | N42: 1116877.3 | O42: 93073.106
B43: 0 | C43: 0 | D43: 0 | E43: 0 | F43: 0 | G43: 0 | H43: 0 | I43: 0 | J43: 0 | K43: 0 | L43: 0 | M43: 0 | N43: 0 | O43: 0
B44: 0 | C44: 0 | D44: 0 | E44: 0 | F44: 0 | G44: 0 | H44: 0 | I44: 0 | J44: 0 | K44: 0 | L44: 0 | M44: 0 | N44: 0 | O44: 0
B45: 0 | C45: 0 | D45: 0 | E45: 0 | F45: 0 | G45: 0 | H45: 0 | I45: 0 | J45: 0 | K45: 0 | L45: 0 | M45: 0 | N45: 0 | O45: 0
B46: 0 | C46: 0 | D46: 0 | E46: 0 | F46: 0 | G46: 0 | H46: 0 | I46: 0 | J46: 0 | K46: 0 | L46: 0 | M46: 0 | N46: 0 | O46: 0
B47: 0 | C47: 0 | D47: 0 | E47: 0 | F47: 0 | G47: 0 | H47: 0 | I47: 0 | J47: 0 | K47: 0 | L47: 0 | M47: 0 | N47: 0 | O47: 0
B48: 54265.917 | C48: 53711.365 | D48: 53723.208 | E48: 34142.59 | F48: 37969.541 | G48: 40415.509 | H48: 44239.335 | I48: 37950.095 | J48: 50962.64 | K48: 39621.531 | L48: 37988.701 | M48: 45024.448 | N48: 530014.88 | O48: 44167.907
A49: PHS | B49: 100470.29 | C49: 77390.829 | D49: 46293.578 | E49: 73043.526 | F49: 77436.854 | G49: 86494.713 | H49: 79944.33 | I49: 125987.81 | J49: 124745.62 | K49: 137266.19 | L49: 131559.38 | M49: 129051.08 | N49: =SUM(B49:M49) -> 1189684.2 | O49: =N49/12 -> 99140.35 | P49: =O49/30 -> 3304.6783
N50: 0 | O50: 0
B51: 259015.52 | C51: 267649.37 | D51: 259015.52 | E51: 267649.37 | F51: 259015.52 | G51: 267649.37 | H51: 267649.37 | I51: 259015.52 | J51: 267649.37 | K51: 267649.37 | L51: 241747.82 | M51: 267649.37 | N51: 3151355.5 | O51: 262612.96
B52: 191907.45 | C52: 164234.42 | D52: 132343.95 | E52: 156453.42 | F52: 133113.06 | G52: 79821.308 | H52: 107125.66 | I52: 139523.63 | J52: 69141.703 | K52: 138430.53 | L52: 93426.675 | M52: 98941.559 | N52: 1504463.4 | O52: 125371.95
B53: 0.74091101 | C53: 0.6136178 | D53: 0.5109499 | E53: 0.58454619 | F53: 0.51391923 | G53: 0.29823088 | H53: 0.40024625 | I53: 0.538669 | J53: 0.2583294 | K53: 0.51720851 | L53: 0.38646336 | M53: 0.36966856 | O53: 0.47740198
D54: 8.5337718 | E54: 7.4874181
B55: 0 | C55: 0 | D55: 0 | E55: 0 | F55: 0 | G55: 0 | H55: 0 | I55: 0 | J55: 0 | K55: 0 | L55: 0 | M55: 0 | N55: 0 | O55: 0
B56: 51793.089 | C56: 47373.026 | D56: 60621 | E56: 110850.18 | F56: 127762.62 | G56: 198558.77 | H56: 152931.99 | I56: 181493.1 | J56: 165288.63 | K56: 198101.93 | L56: 140194.62 | M56: 174530.68 | N56: 1609499.6 | O56: 134124.97
B57: 0 | C57: 0 | D57: 0 | E57: 0 | F57: 0 | G57: 0 | H57: 0 | I57: 0 | J57: 0 | K57: 0 | L57: 0 | M57: 0 | N57: 0 | O57: 0
B58: 87967.841 | C58: 53477.58 | D58: 59980.001 | E58: 59709.04 | F58: 71679.967 | G58: 58393.216 | H58: 65030.146 | I58: 59438.384 | J58: 58917.066 | K58: 54071.334 | L58: 81675.085 | M58: 447696.01 | N58: 1158035.7 | O58: 96502.972
B59: 0 | C59: 0 | D59: 0 | E59: 0 | F59: 0 | G59: 0 | H59: 0 | I59: 0 | J59: 0 | K59: 0 | L59: 0 | M59: 0 | N59: 0 | O59: 0
B60: 27335.401 | C60: 27335.401 | D60: 27335.401 | E60: 31571.227 | F60: 31571.227 | G60: 31571.227 | H60: 35777.81 | I60: 35777.81 | J60: 35777.81 | K60: 33265.503 | L60: 33265.503 | M60: 33265.503 | N60: 383849.82 | O60: 31987.485
B61: 0 | C61: 0 | D61: 0 | E61: 0 | F61: 0 | G61: 0 | H61: 0 | I61: 0 | J61: 0 | K61: 0 | L61: 0 | M61: 0 | N61: 0 | O61: 0
B62: 739601.16 | C62: 753807.43 | D62: 689171.55 | E62: 761037.5 | F62: 728011.76 | G62: 746329.32 | H62: 714655.44 | I62: 720840.84 | J62: 764314.48 | K62: 749835.2 | L62: 737717.51 | M62: 767557.82 | N62: 8872880 | O62: 739406.67
N63: 0 | O63: 0
A64: SHS | B64: 1108335.2 | C64: 1028009.1 | D64: 939711.64 | E64: 1001669.9 | F64: 1130540.2 | G64: 1056371.1 | H64: 933369.03 | I64: 920141.58 | J64: 1212098.6 | K64: 992702.54 | L64: 995401.92 | M64: 941464.77 | N64: =SUM(B64:M64) -> 12259816 | O64: =N64/12 -> 1021651.3 | P64: =O64/30 -> 34055.043
B66: 1065170.1 | C66: 1100675.8 | D66: 1065170.1 | E66: 1100675.8 | F66: 1065170.1 | G66: 1100675.8 | H66: 1100675.8 | I66: 1065170.1 | J66: 1100675.8 | K66: 1100675.8 | L66: 994158.76 | M66: 1100675.8 | N66: 12959569 | O66: 1079964.1
B67: 53472.601 | C67: 110182.33 | D67: 123062.14 | E67: 29007.818 | F67: 1144.5159 | G67: -42676.769 | H67: 23780.373 | I67: -37380.04 | J67: -32122.23 | K67: -43098.206 | L67: -96693.966 | M67: -430874.24 | N67: 935304.33 | O67: 77942.027
B68: 0.050200998 | C68: 0.10010426 | D68: 0.11553286 | E68: 0.026354553 | F68: 0.0010744912 | G68: -0.038773243 | H68: 0.021605249 | I68: -0.035093024 | J68: -0.029184098 | K68: -0.039156133 | L68: -0.097262098 | M68: -0.39146337 | N68: 0.072170941 | O68: 0.072170941
B69: 30223.25 | C69: 28451.401 | D69: 27903.598 | E69: 31069.934 | F69: 31967.519 | G69: 33382.34 | H69: 31238.561 | I69: 33251.671 | J69: 33041.871 | K69: 33395.935 | L69: 35459.026 | M69: 45904.839 | N69: 395289.94 | O69: 32940.829
D70: -14.56638 | O70: 0
B71: 62374.76 | C71: 89781.904 | D71: 114152.18 | E71: 90207.092 | F71: 111535.55 | G71: 124103.27 | H71: 139722.03 | I71: 87630.675 | J71: 138026.1 | K71: 95085.364 | L71: 133232.68 | M71: 120116.19 | N71: =SUM(B71:M71) -> 1305967.8 | O71: =N71/12 -> 108830.65
B72: 653821.24 | C72: 599940.2 | D72: 628023.89 | E72: 638850.96 | F72: 670236.8 | G72: 671198.78 | H72: 657134.58 | I72: 678418.3 | J72: 655729.29 | K72: 686605.05 | L72: 677298.79 | M72: 963664.55 | N72: =SUM(B72:M72) -> 8180922.4 | O72: =N72/12 -> 681743.54
B73: 716196 | C73: 689722.11 | D73: 742176.07 | E73: 729058.05 | F73: 781772.35 | G73: 795302.05 | H73: 796856.62 | I73: 766048.97 | J73: 793755.39 | K73: 781690.41 | L73: 810531.46 | M73: 1083780.7 | N73: =SUM(B73:M73) -> 9486890.2 | O73: =N73/12 -> 790574.19
N74: =SUM(B74:M74) -> 0 | O74: =N74/12 -> 0
B75: 716196 | C75: 689722.11 | D75: 742176.07 | E75: 729058.05 | F75: 781772.35 | G75: 795302.05 | H75: 796856.62 | I75: 766048.97 | J75: 793755.39 | K75: 781690.41 | L75: 810531.46 | M75: 1083780.7 | N75: =SUM(B75:M75) -> 9486890.2 | O75: =N75/12 -> 790574.19
B76: 918000 | C76: 948600 | D76: 918000 | E76: 948600 | F76: 918000 | G76: 948600 | H76: 948600 | I76: 918000 | J76: 948600 | K76: 948600 | L76: 856800 | M76: 948600 | N76: =SUM(B76:M76) -> 11169000 | O76: =N76/12 -> 930750
B77: 201804 | C77: 258877.89 | D77: 175823.93 | E77: 219541.95 | F77: 136227.65 | G77: 153297.95 | H77: 151743.38 | I77: 151951.03 | J77: 154844.61 | K77: 166909.59 | L77: 46268.535 | M77: -135180.74 | N77: =SUM(B77:M77) -> 1682109.8 | O77: =N77/12 -> 140175.81
B78: 0.21983007 | C78: 0.27290522 | D78: 0.19152933 | E78: 0.23143785 | F78: 0.14839613 | G78: 0.16160442 | H78: 0.15996562 | I78: 0.165524 | J78: 0.16323488 | K78: 0.1759536 | L78: 0.054001559 | M78: -0.14250553 | N78: =SUM(B78:M78) -> 1.8018771 | O78: =N78/12 -> 0.15015643
B79: 23873.2 | C79: 22249.1 | D79: 24739.202 | E79: 23518.002 | F79: 26059.078 | G79: 25654.905 | H79: 25705.052 | I79: 25534.966 | J79: 25605.013 | K79: 25215.82 | L79: 28947.552 | M79: 34960.669 | N79: =SUM(B79:M79) -> 312062.56 | O79: =N79/12 -> 26005.213
B80: 23873.2 | C80: 23047.838 | D80: 23605.431 | E80: 23583.215 | F80: 24071.872 | G80: 24340.036 | H80: 24537.772 | I80: 24660.378 | J80: 24766.864 | K80: 24812.346 | L80: 25159.01 | M80: 25991.48 | N80: =SUM(B80:M80) -> 292449.44 | O80: =N80/12 -> 24370.787
N81: 0 | O81: 0
B82: 0 | C82: 0 | D82: 0 | E82: 0 | F82: 0 | G82: 0 | H82: 0 | I82: 0 | J82: 0 | K82: 0 | L82: 0 | M82: 0 | N82: 0 | O82: 0
B83: 16893.498 | C83: 16893.498 | D83: 13643.963 | E83: 5572.7554 | F83: 24323.839 | G83: 16120.743 | H83: 12642.724 | I83: 19453.87 | J83: 15743.034 | K83: 13003.096 | L83: 9823.5294 | M83: 7346.7492 | N83: 171461.3 | O83: 14288.442
B84: 0 | C84: 0 | D84: 0 | E84: 0 | F84: 0 | G84: 0 | H84: 0 | I84: 0 | J84: 0 | K84: 0 | L84: 0 | M84: 0 | N84: 0 | O84: 0
B85: 65263.429 | C85: 78177.465 | D85: 67978.785 | E85: 74641.563 | F85: 69480.358 | G85: 95659.696 | H85: 96263.338 | I85: 115085.33 | J85: 68555.343 | K85: 123024.68 | L85: 484257.1 | M85: 80258.827 | N85: 1418645.9 | O85: 118220.49
B86: 0 | C86: 0 | D86: 0 | E86: 0 | F86: 0 | G86: 0 | H86: 0 | I86: 0 | J86: 0 | K86: 0 | L86: 0 | M86: 0 | N86: 0 | O86: 0
B87: 0 | C87: 0 | D87: 0 | E87: 0 | F87: 0 | G87: 0 | H87: 0 | I87: 0 | J87: 0 | K87: 0 | L87: 0 | M87: 0 | N87: 0 | O87: 0
B88: 0 | C88: 0 | D88: 0 | E88: 0 | F88: 0 | G88: 0 | H88: 0 | I88: 0 | J88: 0 | K88: 0 | L88: 0 | M88: 0 | N88: 0 | O88: 0
B89: 881861.31 | C89: 884885.75 | D89: 822448.93 | E89: 840464.13 | F89: 805227.85 | G89: 836670.86 | H89: 806210.7 | I89: 1331136.8 | J89: 499518.22 | K89: 1209297.3 | L89: 292957.25 | M89: 862796.21 | N89: 10073475 | O89: 839456.27
A90: POY | B90: 1518410 | C90: 1270519.7 | D90: 1070367.6 | E90: 1503729.6 | F90: 1172241.6 | G90: 1069542.6 | H90: 1159497.9 | I90: 1031857.8 | J90: 1045049.7 | K90: 1046607.1 | L90: 999863.76 | M90: 921180.85 | N90: =SUM(B90:M90) -> 13808868 | O90: =N90/12 -> 1150739 | P90: =O90/30 -> 38357.967
N91: 0 | O91: 0
B92: 854696.39 | C92: 883186.27 | D92: 854696.39 | E92: 883186.27 | F92: 854696.39 | G92: 883186.27 | H92: 883186.27 | I92: 854696.39 | J92: 883186.27 | K92: 883186.27 | L92: 797716.63 | M92: 883186.27 | N92: 10398806 | O92: 866567.17 | P92: =N92/12/30 -> 28885.572 | Q92: =N14/12/30 -> 11780.876 | R92: =SUM(P92:Q92) -> 40666.448
B93: -109321.85 | C93: -96770.441 | D93: -49375.293 | E93: -37492.176 | F93: -44335.661 | G93: -65265.032 | H93: -31930.494 | I93: -610979.58 | J93: 299369.68 | K93: -462138.82 | L93: 10678.755 | M93: -67215.515 | N93: -1264776.4 | O93: -105398.04 | R93: =R92/519 -> 78.355392
B94: -0.12790723 | C94: -0.10956968 | D94: -0.057769394 | E94: -0.04245104 | F94: -0.051872994 | G94: -0.073897245 | H94: -0.036153748 | I94: -0.71484985 | J94: 0.3389655 | K94: -0.52326314 | L94: 0.013386652 | M94: -0.076105707 | N94: -0.12162708 | O94: -0.12162708
B97: 0 | C97: 0 | D97: 0 | E97: 0 | F97: 0 | G97: 0 | H97: 0 | I97: 0 | J97: 0 | K97: 0 | L97: 0 | M97: 0 | N97: 0 | O97: 0
B98: 16893.498 | C98: 16893.498 | D98: 7346.7492 | E98: 13643.963 | F98: 22549.845 | G98: 7346.7492 | H98: 25667.492 | I98: 20073.065 | J98: 2476.7802 | K98: 23173.375 | L98: 5572.7554 | M98: 9823.5294 | N98: 171461.3 | O98: 14288.442
B99: 0 | C99: 0 | D99: 0 | E99: 0 | F99: 0 | G99: 0 | H99: 0 | I99: 0 | J99: 0 | K99: 0 | L99: 0 | M99: 0 | N99: 0 | O99: 0
B100: 77926.259 | C100: 65036.468 | D100: 72971.191 | E100: 71477.942 | F100: 81053.306 | G100: 69966.705 | H100: 93790.168 | I100: 153485.99 | J100: 34708.997 | K100: 85975.337 | L100: 109827.29 | M100: 502521.35 | N100: 1418741 | O100: 118228.42
B101: 0 | C101: 0 | D101: 0 | E101: 0 | F101: 0 | G101: 0 | H101: 0 | I101: 0 | J101: 0 | K101: 0 | L101: 0 | M101: 0 | N101: 0 | O101: 0
B102: 0 | C102: 0 | D102: 0 | E102: 0 | F102: 0 | G102: 0 | H102: 0 | I102: 0 | J102: 0 | K102: 0 | L102: 0 | M102: 0 | N102: 0 | O102: 0
B103: 0 | C103: 0 | D103: 0 | E103: 0 | F103: 0 | G103: 0 | H103: 0 | I103: 0 | J103: 0 | K103: 0 | L103: 0 | M103: 0 | N103: 0 | O103: 0
B104: 882421.01 | C104: 882766.72 | D104: 827637.6 | E104: 840464.13 | F104: 805227.85 | G104: 828470.07 | H104: 813601.72 | I104: 816438.09 | J104: 850590.73 | K104: 817054.82 | L104: 831124.7 | M104: 865059.02 | N104: 10060856 | O104: 838404.71
A105: TEXT | B105: 1442558.3 | C105: 1246077.2 | D105: 1159707 | E105: 1249148.5 | F105: 1337464.4 | G105: 1140459.2 | H105: 1164411 | I105: 1032182.3 | J105: 1044370.1 | K105: 1045506.5 | L105: 998580.62 | M105: 924243 | N105: =SUM(B105:M105) -> 13784708 | O105: =N105/12 -> 1148725.7 | P105: =O105/30 -> 38290.856
N106: 0 | O106: 0
B107: 840000 | C107: 868000 | D107: 840000 | E107: 868000 | F107: 840000 | G107: 868000 | H107: 868000 | I107: 840000 | J107: 868000 | K107: 868000 | L107: 784000 | M107: 868000 | N107: 10220000 | O107: 851666.67
B108: -137240.77 | C108: -96696.69 | D108: -67955.539 | E108: -57586.03 | F108: -68831.003 | G108: -37783.529 | H108: -65059.38 | I108: -149997.14 | J108: -19776.512 | K108: -58203.528 | L108: -162524.75 | M108: -509403.9 | N108: -1431058.8 | O108: -119254.9
B109: -0.16338187 | C109: -0.11140172 | D109: -0.080899451 | E109: -0.066343353 | F109: -0.081941671 | G109: -0.043529411 | H109: -0.074953203 | I109: -0.17856803 | J109: -0.022783999 | K109: -0.067054755 | L109: -0.20730197 | M109: -0.58687085 | N109: -0.14002532 | O109: -0.14002532
...

Sheet Sectionwise Working
A3: Section | B3: Machine | C3: Month | D3: Avg. Speed | E3: Avg. Denier | F3: Total Spindle | G3: Utilization | H3: Efficiency | I3: Capacity Per Day | J3: BP | L3: Spinder Req. | M3: Spinder Req. | N3: Winder Req. | O3: Winder Req. | P3: MP Req./Shift | Q3: MP Req./Day | R3: MP Req./Day | S3: Standard HC (Fix) | T3: Total Manpower Req. | U3: Capacity/machine | V3: Available M/C | W3: Available Spindles | X3: Req. M/C | Y3: Req. Spindles | Z3: HC Deployed/M/C | AA3: Total HC Req. /Shift | AB3: Total HC Req. /Shift | AC3: Total HC Req. /Day | AD3: Remarks | AF3: Line | AG3: Winder | AH3: Ends | AN3: Associate | AO3: NAPS | AP3: CLM MD | AW3: Avg MP | AY3: 45748 | AZ3: 45778 | BA3: 45809 | BB3: 45839 | BC3: 45870 | BD3: 45901 | BE3: 45931 | BF3: 45962 | BG3: 45992 | BH3: 46023 | BI3: 46054 | BJ3: 46082
A4: 2. BCF | B4: 2. BCF | C4: 46113 | D4: ='YN01'!$J$31 -> 2576.9311 | E4: ='YN01'!$B$31 -> 1247.7786 | F4: 48 | G4: ='YN01'!$H$10 -> 0.93424658 | H4: ='YN01'!$I$10 -> 0.94 | I4: =D4*E4*F4*G4*H4*0.00016 -> 21686.572 | J4: =BP!E14/DAY(EOMONTH(C4,0)) -> 6335.1186 | L4: =J4/I4 -> 0.29212171 | M4: =L4*F4 -> 14.021842 | N4: =M4/3 -> 4.6739474 | O4: =ROUNDUP(N4,0) -> 5 | P4: =O4/2.5 -> 2 | Q4: =P4*3 -> 6 | R4: =ROUNDUP(Q4,0) -> 6 | S4: ='Manpower Allocation'!$D$9 -> 17 | T4: =R4+S4 -> 23 | U4: =I4/V4 -> 2710.8215 | V4: 8 | W4: =8*2*3 -> 48 | X4: =IF(J4>I4,V4,J4/U4) -> 2.3369737 | Y4: =ROUND(L4*W4,0) -> 14 | Z4: 0.8 | AA4: =X4*Z4 -> 1.869579 | AB4: =ROUNDUP(AA4,0) -> 2 | AC4: =AB4*3 -> 6 | AD4: 1 M/C ~ 6 Spindle (Ends) = 1 Opt ~ 7.5 Spindles (Ends) | AF4: Tri color | AG4: 3 | AH4: =AG4*3 -> 9 | AI4: 2 HC/Shift | AN4: 24 | AO4: =T4-AN4-AP4 -> -4 | AP4: 3 | AT4: =(5*3)+'Manpower Allocation'!G9 -> 15 | AU4: Operator | AV4: =R31 -> 11.166667 | AW4: =AW13/2*3 -> 15 | AX4: For 10 Winders | AY4: =AY13/2*3 -> 9 | AZ4: =AZ13/2*3 -> 10.5 | BA4: =BA13/2*3 -> 10.5 | BB4: =BB13/2*3 -> 13.5 | BC4: =BC13/2*3 -> 13.5 | BD4: =BD13/2*3 -> 19.5 | BE4: =BE13/2*3 -> 16.5 | BF4: =BF13/2*3 -> 21 | ... BJ4: =BJ13/2*3 -> 18
A5: 2. BCF | B5: 2. BCF | C5: 46143 | D5: ='YN01'!$J$31 -> 2576.9311 | E5: ='YN01'!$B$31 -> 1247.7786 | F5: 48 | G5: ='YN01'!$H$10 -> 0.93424658 | H5: ='YN01'!$I$10 -> 0.94 | I5: =D5*E5*F5*G5*H5*0.00016 -> 21686.572 | J5: =BP!F14/DAY(EOMONTH(C5,0)) -> 7343.1179 | L5: =J5/I5 -> 0.33860206 | M5: =L5*F5 -> 16.252899 | N5: =M5/3 -> 5.4176329 | O5: =ROUNDUP(N5,0) -> 6 | P5: =O5/2.5 -> 2.4 | Q5: =P5*3 -> 7.2 | R5: =ROUNDUP(Q5,0) -> 8 | S5: ='Manpower Allocation'!$D$9 -> 17 | T5: =R5+S5 -> 25 | U5: =I5/V5 -> 2710.8215 | V5: 8 | W5: =8*2*3 -> 48 | X5: =IF(J5>I5,V5,J5/U5) -> 2.7088165 | Y5: =ROUND(L5*W5,0) -> 16 | Z5: 0.8 | AA5: =X5*Z5 -> 2.1670532 | AB5: =ROUNDUP(AA5,0) -> 3 | AC5: =ROUNDUP(AA5*3,0) -> 7 | AD5: =IF(MOD(AA5,1)<0.3,ROUNDUP(AA5*3,0),AB5*3) -> 7 | AE5: =IF(MOD(X5*Z5,1)<0.3,ROUNDUP(X5*Z5*3,0),ROUNDUP(X5*Z5,0)*3) -> 7 | AF5: Mono 1 | AG5: 2 | AH5: =AG5*3 -> 6 | AI5: 1 HC/Shift | AN5: 24 | AO5: =T5-AN5-AP5 -> -2 | AP5: 3 | AU5: Material Handling | AV5: 3 | AW5: 3 | AY5: 3 | AZ5: 3 | BA5: 3 | BB5: 3 | BC5: 3 | BD5: 3 | BE5: 3 | BF5: 3 | BG5: 3 | BH5: 3 | BI5: 3 | BJ5: 3
A6: 2. BCF | B6: 2. BCF | C6: 46174 | D6: ='YN01'!$J$31 -> 2576.9311 | E6: ='YN01'!$B$31 -> 1247.7786 | F6: 48 | G6: ='YN01'!$H$10 -> 0.93424658 | H6: ='YN01'!$I$10 -> 0.94 | I6: =D6*E6*F6*G6*H6*0.00016 -> 21686.572 | J6: =BP!G14/DAY(EOMONTH(C6,0)) -> 5757.8727 | L6: =J6/I6 -> 0.26550405 | M6: =L6*F6 -> 12.744194 | N6: =M6/3 -> 4.2480648 | O6: =ROUNDUP(N6,0) -> 5 | P6: =O6/2.5 -> 2 | Q6: =P6*3 -> 6 | R6: =ROUNDUP(Q6,0) -> 6 | S6: ='Manpower Allocation'!$D$9 -> 17 | T6: =R6+S6 -> 23 | U6: =I6/V6 -> 2710.8215 | V6: 8 | W6: =8*2*3 -> 48 | X6: =IF(J6>I6,V6,J6/U6) -> 2.1240324 | Y6: =ROUND(L6*W6,0) -> 13 | Z6: 0.8 | AA6: =X6*Z6 -> 1.6992259 | AB6: =ROUNDUP(AA6,0) -> 2 | AC6: =AB6*3 -> 6 | AD6: =IF(MOD(AA6,1)<0.3,ROUNDUP(AA6*3,0),AB6*3) -> 6 | AE6: =IF(MOD(X6*Z6,1)<0.3,ROUNDUP(X6*Z6*3,0),ROUNDUP(X6*Z6,0)*3) -> 6 | AF6: Mono 2 | AG6: 2 | AH6: =AG6*3 -> 6 | AI6: 1 HC/Shift | AN6: 24 | AO6: =T6-AN6-AP6 -> -4 | AP6: 3 | AU6: Spinning - Operator | AV6: 6 | AW6: =3*2-1 -> 5 | AY6: =3*2-1 -> 5 | AZ6: =3*2-1 -> 5 | BA6: =3*2-1 -> 5 | BB6: =3*2-1 -> 5 | BC6: =3*2-1 -> 5 | BD6: =3*2-1 -> 5 | BE6: =3*2-1 -> 5 | BF6: =3*2-1 -> 5 | ... BJ6: =3*2-1 -> 5
A7: 2. BCF | B7: 2. BCF | C7: 46204 | D7: ='YN01'!$J$31 -> 2576.9311 | E7: ='YN01'!$B$31 -> 1247.7786 | F7: 48 | G7: ='YN01'!$H$10 -> 0.93424658 | H7: ='YN01'!$I$10 -> 0.94 | I7: =D7*E7*F7*G7*H7*0.00016 -> 21686.572 | J7: =BP!H14/DAY(EOMONTH(C7,0)) -> 6631.5757 | L7: =J7/I7 -> 0.30579179 | M7: =L7*F7 -> 14.678006 | N7: =M7/3 -> 4.8926687 | O7: =ROUNDUP(N7,0) -> 5 | P7: =O7/2.5 -> 2 | Q7: =P7*3 -> 6 | R7: =ROUNDUP(Q7,0) -> 6 | S7: ='Manpower Allocation'!$D$9 -> 17 | T7: =R7+S7 -> 23 | U7: =I7/V7 -> 2710.8215 | V7: 8 | W7: =8*2*3 -> 48 | X7: =IF(J7>I7,V7,J7/U7) -> 2.4463343 | Y7: =ROUND(L7*W7,0) -> 15 | Z7: 0.8 | AA7: =X7*Z7 -> 1.9570675 | AB7: =ROUNDUP(AA7,0) -> 2 | AC7: =AB7*3 -> 6 | AD7: =IF(MOD(AA7,1)<0.3,ROUNDUP(AA7*3,0),AB7*3) -> 6 | AE7: =IF(MOD(X7*Z7,1)<0.3,ROUNDUP(X7*Z7*3,0),ROUNDUP(X7*Z7,0)*3) -> 6 | AF7: Mono 3 | AG7: 2 | AH7: =AG7*3 -> 6 | AI7: 1 HC/Shift | AN7: 24 | AO7: =T7-AN7-AP7 -> -4 | AP7: 3 | AU7: Data Entry | AV7: 2 | AW7: 1 | AX7: ** Workload of DEO should be Digitized. And Shared with Spinning Operator | AY7: 1 | AZ7: 1 | BA7: 1 | BB7: 1 | BC7: 1 | BD7: 1 | BE7: 1 | BF7: 1 | BG7: 1 | BH7: 1 | BI7: 1 | BJ7: 1
A8: 2. BCF | B8: 2. BCF | C8: 46235 | D8: ='YN01'!$J$31 -> 2576.9311 | E8: ='YN01'!$B$31 -> 1247.7786 | F8: 48 | G8: ='YN01'!$H$10 -> 0.93424658 | H8: ='YN01'!$I$10 -> 0.94 | I8: =D8*E8*F8*G8*H8*0.00016 -> 21686.572 | J8: =BP!I14/DAY(EOMONTH(C8,0)) -> 8091.1841 | L8: =J8/I8 -> 0.3730965 | M8: =L8*F8 -> 17.908632 | N8: =M8/3 -> 5.969544 | O8: =ROUNDUP(N8,0) -> 6 | P8: =O8/2.5 -> 2.4 | Q8: =P8*3 -> 7.2 | R8: =ROUNDUP(Q8,0) -> 8 | S8: ='Manpower Allocation'!$D$9 -> 17 | T8: =R8+S8 -> 25 | U8: =I8/V8 -> 2710.8215 | V8: 8 | W8: =8*2*3 -> 48 | X8: =IF(J8>I8,V8,J8/U8) -> 2.984772 | Y8: =ROUND(L8*W8,0) -> 18 | Z8: 0.8 | AA8: =X8*Z8 -> 2.3878176 | AB8: =ROUNDUP(AA8,0) -> 3 | AC8: =AB8*3 -> 9 | AD8: =IF(MOD(AA8,1)<0.3,ROUNDUP(AA8*3,0),AB8*3) -> 9 | AE8: =IF(MOD(X8*Z8,1)<0.3,ROUNDUP(X8*Z8*3,0),ROUNDUP(X8*Z8,0)*3) -> 9 | AF8: Mono 4 | AG8: 2 | AH8: =AG8*3 -> 6 | AI8: 1 HC/Shift | AN8: 24 | AO8: =T8-AN8-AP8 -> -2 | AP8: 3 | AU8: G-Burnout | AV8: 5 | AW8: 5 | AY8: 5 | AZ8: 5 | BA8: 5 | BB8: 5 | BC8: 5 | BD8: 5 | BE8: 5 | BF8: 5 | BG8: 5 | BH8: 5 | BI8: 5 | BJ8: 5
A9: 2. BCF | B9: 2. BCF | C9: 46266 | D9: ='YN01'!$J$31 -> 2576.9311 | E9: ='YN01'!$B$31 -> 1247.7786 | F9: 48 | G9: ='YN01'!$H$10 -> 0.93424658 | H9: ='YN01'!$I$10 -> 0.94 | I9: =D9*E9*F9*G9*H9*0.00016 -> 21686.572 | J9: =BP!J14/DAY(EOMONTH(C9,0)) -> 13123.9 | L9: =J9/I9 -> 0.60516251 | M9: =L9*F9 -> 29.0478 | N9: =M9/3 -> 9.6826001 | O9: =ROUNDUP(N9,0) -> 10 | P9: =O9/2.5 -> 4 | Q9: =P9*3 -> 12 | R9: =ROUNDUP(Q9,0) -> 12 | S9: ='Manpower Allocation'!$D$9 -> 17 | T9: =R9+S9 -> 29 | U9: =I9/V9 -> 2710.8215 | V9: 8 | W9: =8*2*3 -> 48 | X9: =IF(J9>I9,V9,J9/U9) -> 4.8413001 | Y9: =ROUND(L9*W9,0) -> 29 | Z9: 0.8 | AA9: =X9*Z9 -> 3.8730401 | AB9: =ROUNDUP(AA9,0) -> 4 | AC9: =AB9*3 -> 12 | AD9: =IF(MOD(AA9,1)<0.3,ROUNDUP(AA9*3,0),AB9*3) -> 12 | AE9: =IF(MOD(X9*Z9,1)<0.3,ROUNDUP(X9*Z9*3,0),ROUNDUP(X9*Z9,0)*3) -> 12 | AF9: Mono 5 | AG9: 2 | AH9: =AG9*3 -> 6 | AI9: 1 HC/Shift | AN9: 30 | AO9: =T9-AN9-AP9 -> -4 | AP9: 3 | AU9: H-DRYER (BCF+POY) | AV9: 5 | AW9: 5 | AY9: 5 | AZ9: 5 | BA9: 5 | BB9: 5 | BC9: 5 | BD9: 5 | BE9: 5 | BF9: 5 | BG9: 5 | BH9: 5 | BI9: 5 | BJ9: 5
A10: 2. BCF | B10: 2. BCF | C10: 46296 | D10: ='YN01'!$J$31 -> 2576.9311 | E10: ='YN01'!$B$31 -> 1247.7786 | F10: 48 | G10: ='YN01'!$H$10 -> 0.93424658 | H10: ='YN01'!$I$10 -> 0.94 | I10: =D10*E10*F10*G10*H10*0.00016 -> 21686.572 | J10: =BP!K14/DAY(EOMONTH(C10,0)) -> 9321.041 | L10: =J10/I10 -> 0.42980702 | M10: =L10*F10 -> 20.630737 | N10: =M10/3 -> 6.8769124 | O10: =ROUNDUP(N10,0) -> 7 | P10: =O10/2.5 -> 2.8 | Q10: =P10*3 -> 8.4 | R10: =ROUNDUP(Q10,0) -> 9 | S10: ='Manpower Allocation'!$D$9 -> 17 | T10: =R10+S10 -> 26 | U10: =I10/V10 -> 2710.8215 | V10: 8 | W10: =8*2*3 -> 48 | X10: =IF(J10>I10,V10,J10/U10) -> 3.4384562 | Y10: =ROUND(L10*W10,0) -> 21 | Z10: 0.8 | AA10: =X10*Z10 -> 2.750765 | AB10: =ROUNDUP(AA10,0) -> 3 | AC10: =AB10*3 -> 9 | AD10: =IF(MOD(AA10,1)<0.3,ROUNDUP(AA10*3,0),AB10*3) -> 9 | AE10: =IF(MOD(X10*Z10,1)<0.3,ROUNDUP(X10*Z10*3,0),ROUNDUP(X10*Z10,0)*3) -> 9 | AF10: Mono 6 | AG10: 2 | AH10: =AG10*3 -> 6 | AI10: 1 HC/Shift | AN10: 30 | AO10: =T10-AN10-AP10 -> -7 | AP10: 3 | AU10: Chips Charging | AV10: 3 | AW10: 3 | AY10: 3 | AZ10: 3 | BA10: 3 | BB10: 3 | BC10: 3 | BD10: 3 | BE10: 3 | BF10: 3 | BG10: 3 | BH10: 3 | BI10: 3 | BJ10: 3
A11: 2. BCF | B11: 2. BCF | C11: 46327 | D11: ='YN01'!$J$31 -> 2576.9311 | E11: ='YN01'!$B$31 -> 1247.7786 | F11: 48 | G11: ='YN01'!$H$10 -> 0.93424658 | H11: ='YN01'!$I$10 -> 0.94 | I11: =D11*E11*F11*G11*H11*0.00016 -> 21686.572 | J11: =BP!L14/DAY(EOMONTH(C11,0)) -> 12237.754 | L11: =J11/I11 -> 0.56430099 | M11: =L11*F11 -> 27.086448 | N11: =M11/3 -> 9.0288158 | O11: =ROUNDUP(N11,0) -> 10 | P11: =O11/2.5 -> 4 | Q11: =P11*3 -> 12 | R11: =ROUNDUP(Q11,0) -> 12 | S11: ='Manpower Allocation'!$D$9 -> 17 | T11: =R11+S11 -> 29 | U11: =I11/V11 -> 2710.8215 | V11: 8 | W11: =8*2*3 -> 48 | X11: =IF(J11>I11,V11,J11/U11) -> 4.5144079 | Y11: =ROUND(L11*W11,0) -> 27 | Z11: 0.8 | AA11: =X11*Z11 -> 3.6115263 | AB11: =ROUNDUP(AA11,0) -> 4 | AC11: =AB11*3 -> 12 | AD11: =IF(MOD(AA11,1)<0.3,ROUNDUP(AA11*3,0),AB11*3) -> 12 | AE11: =IF(MOD(X11*Z11,1)<0.3,ROUNDUP(X11*Z11*3,0),ROUNDUP(X11*Z11,0)*3) -> 12 | AF11: BI Component | AG11: 1 | AH11: =AG11*3 -> 3 | AI11: 1 HC/Shift | AN11: 30 | AO11: =T11-AN11-AP11 -> -4 | AP11: 3 | AU11: TOTAL | AV11: =SUM(AV4:AV10) -> 35.166667 | AW11: =SUM(AW4:AW10) -> 37 | AY11: =SUM(AY4:AY10) -> 31 | AZ11: =SUM(AZ4:AZ10) -> 32.5 | BA11: =SUM(BA4:BA10) -> 32.5 | BB11: =SUM(BB4:BB10) -> 35.5 | BC11: =SUM(BC4:BC10) -> 35.5 | BD11: =SUM(BD4:BD10) -> 41.5 | BE11: =SUM(BE4:BE10) -> 38.5 | BF11: =SUM(BF4:BF10) -> 43 | ... BJ11: =SUM(BJ4:BJ10) -> 40
A12: 2. BCF | B12: 2. BCF | C12: 46357 | D12: ='YN01'!$J$31 -> 2576.9311 | E12: ='YN01'!$B$31 -> 1247.7786 | F12: 48 | G12: ='YN01'!$H$10 -> 0.93424658 | H12: ='YN01'!$I$10 -> 0.94 | I12: =D12*E12*F12*G12*H12*0.00016 -> 21686.572 | J12: =BP!M14/DAY(EOMONTH(C12,0)) -> 21844.945 | L12: =J12/I12 -> 1.0073028 | M12: =L12*F12 -> 48.350534 | N12: =M12/3 -> 16.116845 | O12: =ROUNDUP(N12,0) -> 17 | P12: =O12/2.5 -> 6.8 | Q12: =P12*3 -> 20.4 | R12: =ROUNDUP(Q12,0) -> 21 | S12: ='Manpower Allocation'!$D$9 -> 17 | T12: =R12+S12 -> 38 | U12: =I12/V12 -> 2710.8215 | V12: 8 | W12: =8*2*3 -> 48 | X12: =IF(J12>I12,V12,J12/U12) -> 8 | Y12: =ROUND(L12*W12,0) -> 48 | Z12: 0.8 | AA12: =X12*Z12 -> 6.4 | AB12: =ROUNDUP(AA12,0) -> 7 | AC12: =AB12*3 -> 21 | AD12: =IF(MOD(AA12,1)<0.3,ROUNDUP(AA12*3,0),AB12*3) -> 21 | AE12: =IF(MOD(X12*Z12,1)<0.3,ROUNDUP(X12*Z12*3,0),ROUNDUP(X12*Z12,0)*3) -> 21 | AN12: 30 | AO12: =T12-AN12-AP12 -> 5 | AP12: 3 | CI12: Yarn | CJ12: 3
A13: 2. BCF | B13: 2. BCF | C13: 46388 | D13: ='YN01'!$J$31 -> 2576.9311 | E13: ='YN01'!$B$31 -> 1247.7786 | F13: 48 | G13: ='YN01'!$H$10 -> 0.93424658 | H13: ='YN01'!$I$10 -> 0.94 | I13: =D13*E13*F13*G13*H13*0.00016 -> 21686.572 | J13: =BP!N14/DAY(EOMONTH(C13,0)) -> 17033.689 | L13: =J13/I13 -> 0.78544866 | M13: =L13*F13 -> 37.701536 | N13: =M13/3 -> 12.567179 | O13: =ROUNDUP(N13,0) -> 13 | P13: =O13/2.5 -> 5.2 | Q13: =P13*3 -> 15.6 | R13: =ROUNDUP(Q13,0) -> 16 | S13: ='Manpower Allocation'!$D$9 -> 17 | T13: =R13+S13 -> 33 | U13: =I13/V13 -> 2710.8215 | V13: 8 | W13: =8*2*3 -> 48 | X13: =IF(J13>I13,V13,J13/U13) -> 6.2835893 | Y13: =ROUND(L13*W13,0) -> 38 | Z13: 0.8 | AA13: =X13*Z13 -> 5.0268715 | AB13: =ROUNDUP(AA13,0) -> 6 | AC13: =ROUNDUP(AA13*3,0) -> 16 | AD13: =IF(MOD(AA13,1)<0.3,ROUNDUP(AA13*3,0),AB13*3) -> 16 | AE13: =IF(MOD(X13*Z13,1)<0.3,ROUNDUP(X13*Z13*3,0),ROUNDUP(X13*Z13,0)*3) -> 16 | AN13: 30 | AO13: =T13-AN13-AP13 -> 0 | AP13: 3 | AW13: 10 | AY13: 6 | AZ13: 7 | BA13: 7 | BB13: 9 | BC13: 9 | BD13: 13 | BE13: 11 | BF13: 14 | BG13: 11 | BH13: 14 | BI13: 11 | BJ13: 12 | CI13: Tufting | CJ13: 3
A14: 2. BCF | B14: 2. BCF | C14: 46419 | D14: ='YN01'!$J$31 -> 2576.9311 | E14: ='YN01'!$B$31 -> 1247.7786 | F14: 48 | G14: ='YN01'!$H$10 -> 0.93424658 | H14: ='YN01'!$I$10 -> 0.94 | I14: =D14*E14*F14*G14*H14*0.00016 -> 21686.572 | J14: =BP!O14/DAY(EOMONTH(C14,0)) -> 17417.413 | L14: =J14/I14 -> 0.80314275 | M14: =L14*F14 -> 38.550852 | N14: =M14/3 -> 12.850284 | O14: =ROUNDUP(N14,0) -> 13 | P14: =O14/2.5 -> 5.2 | Q14: =P14*3 -> 15.6 | R14: =ROUNDUP(Q14,0) -> 16 | S14: ='Manpower Allocation'!$D$9 -> 17 | T14: =R14+S14 -> 33 | U14: =I14/V14 -> 2710.8215 | V14: 8 | W14: =8*2*3 -> 48 | X14: =IF(J14>I14,V14,J14/U14) -> 6.425142 | Y14: =ROUND(L14*W14,0) -> 39 | Z14: 0.8 | AA14: =X14*Z14 -> 5.1401136 | AB14: =ROUNDUP(AA14,0) -> 6 | AC14: =ROUNDUP(AA14*3,0) -> 16 | AD14: =IF(MOD(AA14,1)<0.3,ROUNDUP(AA14*3,0),AB14*3) -> 16 | AE14: =IF(MOD(X14*Z14,1)<0.3,ROUNDUP(X14*Z14*3,0),ROUNDUP(X14*Z14,0)*3) -> 16 | AN14: 30 | AO14: =T14-AN14-AP14 -> 0 | AP14: 3 | CI14: Coating | CJ14: 3
A15: 2. BCF | B15: 2. BCF | C15: 46447 | D15: ='YN01'!$J$31 -> 2576.9311 | E15: ='YN01'!$B$31 -> 1247.7786 | F15: 48 | G15: ='YN01'!$H$10 -> 0.93424658 | H15: ='YN01'!$I$10 -> 0.94 | I15: =D15*E15*F15*G15*H15*0.00016 -> 21686.572 | J15: =BP!P14/DAY(EOMONTH(C15,0)) -> 14566.333 | L15: =J15/I15 -> 0.67167521 | M15: =L15*F15 -> 32.24041 | N15: =M15/3 -> 10.746803 | O15: =ROUNDUP(N15,0) -> 11 | P15: =O15/2.5 -> 4.4 | Q15: =P15*3 -> 13.2 | R15: =ROUNDUP(Q15,0) -> 14 | S15: ='Manpower Allocation'!$D$9 -> 17 | T15: =R15+S15 -> 31 | U15: =I15/V15 -> 2710.8215 | V15: 8 | W15: =8*2*3 -> 48 | X15: =IF(J15>I15,V15,J15/U15) -> 5.3734017 | Y15: =ROUND(L15*W15,0) -> 32 | Z15: 0.8 | AA15: =X15*Z15 -> 4.2987214 | AB15: =ROUNDUP(AA15,0) -> 5 | AC15: =ROUNDUP(AA15*3,0) -> 13 | AD15: =IF(MOD(AA15,1)<0.3,ROUNDUP(AA15*3,0),AB15*3) -> 13 | AE15: =IF(MOD(X15*Z15,1)<0.3,ROUNDUP(X15*Z15*3,0),ROUNDUP(X15*Z15,0)*3) -> 13 | AN15: 30 | AO15: =T15-AN15-AP15 -> -2 | AP15: 3 | CI15: CSP | CJ15: 3
A17: Section | B17: Machine | C17: Month | D17: Avg. Speed | E17: Avg. Denier | F17: Total Spindle | G17: Utilization | H17: Efficiency | I17: Capacity Per Day | J17: BP | L17: Spinder Req. | M17: Spinder Req. | N17: Winder Req. | O17: Winder Req. | P17: MP Req./Shift | Q17: MP Req./Day | R17: MP Req./Day | S17: Standard HC (Fix) | T17: Total Manpower Req. | U17: Capacity/machine | V17: Available Line | W17: Available Spindles | X17: Req. M/C | Y17: Req. Spindles | Z17: HC Deployed/M/C | AA17: Total HC Req. /Shift | AB17: Total HC Req. /Shift | AC17: Total HC Req. /Day | AD17: Remarks | AE17: =AVERAGE(AE18:AE29) -> 71.166667 | AF17: Line | AG17: Winder | AH17: Ends | AJ17: =AVERAGE(AJ18:AJ29) -> 71.166667 | AW17: Avg MP | AY17: 45748 | AZ17: 45778 | BA17: 45809 | BB17: 45839 | BC17: 45870 | BD17: 45901 | BE17: 45931 | BF17: 45962 | BG17: 45992 | BH17: 46023 | BI17: 46054 | BJ17: 46082
A18: 1. POY | B18: 1. POY | C18: 46113 | D18: ='YN01'!$J$51 -> 2967.7287 | E18: ='YN01'!$B$51 -> 270.46771 | F18: =24*12-12 -> 276 | G18: ='YN01'!$H$43 -> 0.93424658 | H18: ='YN01'!$I$43 -> 0.97 | I18: =D18*E18*F18*G18*H18*0.00016 -> 32121.952 | J18: =(BP!E90+BP!E91)/DAY(EOMONTH(C18,0)) -> 50613.668 | L18: =J18/I18 -> 1.5756722 | M18: =IF((L18*F18)>F18,F18,(L18*F18)) -> 276 | N18: =M18/11.5 -> 24 | O18: =ROUNDUP(N18,0) -> 24 | P18: =O18*0.25 -> 6 | Q18: =P18*3 -> 18 | R18: =ROUNDUP(Q18,0) -> 18 | S18: ='Manpower Allocation'!$D$18 -> 25 | T18: =R18+S18 -> 43 | U18: =I18/V18 -> 2676.8293 | V18: 12 | W18: =(11*12*2)+(1*6*2) -> 276 | X18: =IF(J18>I18,V18,J18/U18) -> 12 | Y18: =ROUND(L18*W18,0) -> 435 | Z18: 0.5 | AA18: =Z18*X18 -> 6 | AB18: =ROUNDUP(AA18,0) -> 6 | AC18: =AB18*3 -> 18 | AD18: 1 M/C ~ 24 Spindles (Ends) = 1 Opt ~48 Spindles | AE18: =T18+T4 -> 66 | AF18: P1 | AG18: 1 | AH18: 6 | AJ18: =T18+T4 -> 66 | AT18: =J18/T18 -> 1177.062 | AU18: Operator | AV18: =Q30 -> 17.9375 | AW18: =6*3 -> 18 | AX18: For 24 Winders | AY18: =6*3 -> 18 | AZ18: =6*3 -> 18 | BA18: =6*3 -> 18 | BB18: =6*3 -> 18 | BC18: =6*3 -> 18 | BD18: =6*3 -> 18 | BE18: =6*3 -> 18 | BF18: =6*3 -> 18 | BG18: =4*3 -> 12 | BH18: =6*3 -> 18 | BI18: =6*3 -> 18 | BJ18: =6*3 -> 18
A19: 1. POY | B19: 1. POY | C19: 46143 | D19: ='YN01'!$J$51 -> 2967.7287 | E19: ='YN01'!$B$51 -> 270.46771 | F19: =24*12-12 -> 276 | G19: ='YN01'!$H$43 -> 0.93424658 | H19: ='YN01'!$I$43 -> 0.97 | I19: =D19*E19*F19*G19*H19*0.00016 -> 32121.952 | J19: =(BP!F90+BP!F91)/DAY(EOMONTH(C19,0)) -> 40984.507 | L19: =J19/I19 -> 1.2759034 | M19: =IF((L19*F19)>F19,F19,(L19*F19)) -> 276 | N19: =M19/11.5 -> 24 | O19: =ROUNDUP(N19,0) -> 24 | P19: =O19*0.25 -> 6 | Q19: =P19*3 -> 18 | R19: =ROUNDUP(Q19,0) -> 18 | S19: ='Manpower Allocation'!$D$18 -> 25 | T19: =R19+S19 -> 43 | U19: =I19/V19 -> 2676.8293 | V19: 12 | W19: =(11*12*2)+(1*6*2) -> 276 | X19: =IF(J19>I19,V19,J19/U19) -> 12 | Y19: =ROUND(L19*W19,0) -> 352 | Z19: 0.5 | AA19: =Z19*X19 -> 6 | AB19: =ROUNDUP(AA19,0) -> 6 | AC19: =AB19*3 -> 18 | AE19: =T19+T5 -> 68 | AF19: P2 | AG19: 1 | AH19: 6 | AJ19: =T19+T5 -> 68 | AU19: Chips Charging | AV19: 3 | AW19: 3 | AY19: 3 | AZ19: 3 | BA19: 3 | BB19: 3 | BC19: 3 | BD19: 3 | BE19: 3 | BF19: 3 | BG19: 3 | BH19: 3 | BI19: 3 | BJ19: 3
A20: 1. POY | B20: 1. POY | C20: 46174 | D20: ='YN01'!$J$51 -> 2967.7287 | E20: ='YN01'!$B$51 -> 270.46771 | F20: =24*12-12 -> 276 | G20: ='YN01'!$H$43 -> 0.93424658 | H20: ='YN01'!$I$43 -> 0.97 | I20: =D20*E20*F20*G20*H20*0.00016 -> 32121.952 | J20: =(BP!G90+BP!G91)/DAY(EOMONTH(C20,0)) -> 35678.92 | L20: =J20/I20 -> 1.1107333 | M20: =IF((L20*F20)>F20,F20,(L20*F20)) -> 276 | N20: =M20/11.5 -> 24 | O20: =ROUNDUP(N20,0) -> 24 | P20: =O20*0.25 -> 6 | Q20: =P20*3 -> 18 | R20: =ROUNDUP(Q20,0) -> 18 | S20: ='Manpower Allocation'!$D$18 -> 25 | T20: =R20+S20 -> 43 | U20: =I20/V20 -> 2676.8293 | V20: 12 | W20: =(11*12*2)+(1*6*2) -> 276 | X20: =IF(J20>I20,V20,J20/U20) -> 12 | Y20: =ROUND(L20*W20,0) -> 307 | Z20: 0.5 | AA20: =Z20*X20 -> 6 | AB20: =ROUNDUP(AA20,0) -> 6 | AC20: =AB20*3 -> 18 | AE20: =T20+T6 -> 66 | AF20: P3 | AG20: 1 | AH20: 12 | AJ20: =T20+T6 -> 66 | AU20: Dryer | AV20: 6 | AW20: 3 | AX20: ** 2 persons (one person on each floor) continuously monitor the utility part on every mc. & the level of infeed material in every vessels. And if there is any uncertainity found, they inform their supervisor @ it and ask them to do the corrections. This can be covered in EMS, with One or No person required to seperately monitor and update the readings. | AY20: 3 | AZ20: 3 | BA20: 3 | BB20: 3 | BC20: 3 | BD20: 3 | BE20: 3 | BF20: 3 | BG20: 3 | BH20: 3 | BI20: 3 | BJ20: 3
A21: 1. POY | B21: 1. POY | C21: 46204 | D21: ='YN01'!$J$51 -> 2967.7287 | E21: ='YN01'!$B$51 -> 270.46771 | F21: =24*12-12 -> 276 | G21: ='YN01'!$H$43 -> 0.93424658 | H21: ='YN01'!$I$43 -> 0.97 | I21: =D21*E21*F21*G21*H21*0.00016 -> 32121.952 | J21: =(BP!H90+BP!H91)/DAY(EOMONTH(C21,0)) -> 48507.406 | L21: =J21/I21 -> 1.5101014 | M21: =IF((L21*F21)>F21,F21,(L21*F21)) -> 276 | N21: =M21/11.5 -> 24 | O21: =ROUNDUP(N21,0) -> 24 | P21: =O21*0.25 -> 6 | Q21: =P21*3 -> 18 | R21: =ROUNDUP(Q21,0) -> 18 | S21: ='Manpower Allocation'!$D$18 -> 25 | T21: =R21+S21 -> 43 | U21: =I21/V21 -> 2676.8293 | V21: 12 | W21: =(11*12*2)+(1*6*2) -> 276 | X21: =IF(J21>I21,V21,J21/U21) -> 12 | Y21: =ROUND(L21*W21,0) -> 417 | Z21: 0.5 | AA21: =Z21*X21 -> 6 | AB21: =ROUNDUP(AA21,0) -> 6 | AC21: =AB21*3 -> 18 | AE21: =T21+T7 -> 66 | AF21: P4 | AG21: 1 | AH21: 12 | AJ21: =T21+T7 -> 66 | AU21: Spinning + Control Room | AV21: 9 | AW21: =(2*3)+(1*2) -> 8 | AY21: =(2*3)+(1*2) -> 8 | AZ21: =(2*3)+(1*2) -> 8 | BA21: =(2*3)+(1*2) -> 8 | BB21: =(2*3)+(1*2) -> 8 | BC21: =(2*3)+(1*2) -> 8 | BD21: =(2*3)+(1*2) -> 8 | BE21: =(2*3)+(1*2) -> 8 | BF21: =(2*3)+(1*2) -> 8 | ... BJ21: =(2*3)+(1*2) -> 8
A22: 1. POY | B22: 1. POY | C22: 46235 | D22: ='YN01'!$J$51 -> 2967.7287 | E22: ='YN01'!$B$51 -> 270.46771 | F22: =24*12-12 -> 276 | G22: ='YN01'!$H$43 -> 0.93424658 | H22: ='YN01'!$I$43 -> 0.97 | I22: =D22*E22*F22*G22*H22*0.00016 -> 32121.952 | J22: =(BP!I90+BP!I91)/DAY(EOMONTH(C22,0)) -> 37814.245 | L22: =J22/I22 -> 1.1772088 | M22: =IF((L22*F22)>F22,F22,(L22*F22)) -> 276 | N22: =M22/11.5 -> 24 | O22: =ROUNDUP(N22,0) -> 24 | P22: =O22*0.25 -> 6 | Q22: =P22*3 -> 18 | R22: =ROUNDUP(Q22,0) -> 18 | S22: ='Manpower Allocation'!$D$18 -> 25 | T22: =R22+S22 -> 43 | U22: =I22/V22 -> 2676.8293 | V22: 12 | W22: =(11*12*2)+(1*6*2) -> 276 | X22: =IF(J22>I22,V22,J22/U22) -> 12 | Y22: =ROUND(L22*W22,0) -> 325 | Z22: 0.5 | AA22: =Z22*X22 -> 6 | AB22: =ROUNDUP(AA22,0) -> 6 | AC22: =AB22*3 -> 18 | AE22: =T22+T8 -> 68 | AF22: P5 | AG22: 1 | AH22: 12 | AJ22: =T22+T8 -> 68 | AU22: Data Entry | AV22: 1 | AW22: 1 | AX22: ** DEO can be asked to sit in Control Room to monitor the Spinning parameters while he does the DE's. Also, his current workload should be minimized through Digitization. | AY22: 1 | AZ22: 1 | BA22: 1 | BB22: 1 | BC22: 1 | BD22: 1 | BE22: 1 | BF22: 1 | BG22: 1 | BH22: 1 | BI22: 1 | BJ22: 1
A23: 1. POY | B23: 1. POY | C23: 46266 | D23: ='YN01'!$J$51 -> 2967.7287 | E23: ='YN01'!$B$51 -> 270.46771 | F23: =24*12-12 -> 276 | G23: ='YN01'!$H$43 -> 0.93424658 | H23: ='YN01'!$I$43 -> 0.97 | I23: =D23*E23*F23*G23*H23*0.00016 -> 32121.952 | J23: =(BP!J90+BP!J91)/DAY(EOMONTH(C23,0)) -> 35651.419 | L23: =J23/I23 -> 1.1098771 | M23: =IF((L23*F23)>F23,F23,(L23*F23)) -> 276 | N23: =M23/11.5 -> 24 | O23: =ROUNDUP(N23,0) -> 24 | P23: =O23*0.25 -> 6 | Q23: =P23*3 -> 18 | R23: =ROUNDUP(Q23,0) -> 18 | S23: ='Manpower Allocation'!$D$18 -> 25 | T23: =R23+S23 -> 43 | U23: =I23/V23 -> 2676.8293 | V23: 12 | W23: =(11*12*2)+(1*6*2) -> 276 | X23: =IF(J23>I23,V23,J23/U23) -> 12 | Y23: =ROUND(L23*W23,0) -> 306 | Z23: 0.5 | AA23: =Z23*X23 -> 6 | AB23: =ROUNDUP(AA23,0) -> 6 | AC23: =AB23*3 -> 18 | AE23: =T23+T9 -> 72 | AF23: P6 | AG23: 1 | AH23: 12 | AJ23: =T23+T9 -> 72 | AU23: Burn Out | AV23: 6 | AW23: 6 | AY23: 6 | AZ23: 6 | BA23: 6 | BB23: 6 | BC23: 6 | BD23: 6 | BE23: 6 | BF23: 6 | BG23: 6 | BH23: 6 | BI23: 6 | BJ23: 6
A24: 1. POY | B24: 1. POY | C24: 46296 | D24: ='YN01'!$J$51 -> 2967.7287 | E24: ='YN01'!$B$51 -> 270.46771 | F24: =24*12-12 -> 276 | G24: ='YN01'!$H$43 -> 0.93424658 | H24: ='YN01'!$I$43 -> 0.97 | I24: =D24*E24*F24*G24*H24*0.00016 -> 32121.952 | J24: =(BP!K90+BP!K91)/DAY(EOMONTH(C24,0)) -> 37403.159 | L24: =J24/I24 -> 1.1644111 | M24: =IF((L24*F24)>F24,F24,(L24*F24)) -> 276 | N24: =M24/11.5 -> 24 | O24: =ROUNDUP(N24,0) -> 24 | P24: =O24*0.25 -> 6 | Q24: =P24*3 -> 18 | R24: =ROUNDUP(Q24,0) -> 18 | S24: ='Manpower Allocation'!$D$18 -> 25 | T24: =R24+S24 -> 43 | U24: =I24/V24 -> 2676.8293 | V24: 12 | W24: =(11*12*2)+(1*6*2) -> 276 | X24: =IF(J24>I24,V24,J24/U24) -> 12 | Y24: =ROUND(L24*W24,0) -> 321 | Z24: 0.5 | AA24: =Z24*X24 -> 6 | AB24: =ROUNDUP(AA24,0) -> 6 | AC24: =AB24*3 -> 18 | AE24: =T24+T10 -> 69 | AF24: P7 | AG24: 2 | AH24: =AG24*12 -> 24 | AJ24: =T24+T10 -> 69 | AU24: PD Sample (M/C will install after 5 Month) | AV24: 3 | AW24: 3 | AY24: 3 | AZ24: 3 | BA24: 3 | BB24: 3 | BC24: 3 | BD24: 3 | BE24: 3 | BF24: 3 | BG24: 3 | BH24: 3 | BI24: 3 | BJ24: 3
A25: 1. POY | B25: 1. POY | C25: 46327 | D25: ='YN01'!$J$51 -> 2967.7287 | E25: ='YN01'!$B$51 -> 270.46771 | F25: =24*12-12 -> 276 | G25: ='YN01'!$H$43 -> 0.93424658 | H25: ='YN01'!$I$43 -> 0.97 | I25: =D25*E25*F25*G25*H25*0.00016 -> 32121.952 | J25: =(BP!L90+BP!L91)/DAY(EOMONTH(C25,0)) -> 34395.261 | L25: =J25/I25 -> 1.0707712 | M25: =IF((L25*F25)>F25,F25,(L25*F25)) -> 276 | N25: =M25/11.5 -> 24 | O25: =ROUNDUP(N25,0) -> 24 | P25: =O25*0.25 -> 6 | Q25: =P25*3 -> 18 | R25: =ROUNDUP(Q25,0) -> 18 | S25: ='Manpower Allocation'!$D$18 -> 25 | T25: =R25+S25 -> 43 | U25: =I25/V25 -> 2676.8293 | V25: 12 | W25: =(11*12*2)+(1*6*2) -> 276 | X25: =IF(J25>I25,V25,J25/U25) -> 12 | Y25: =ROUND(L25*W25,0) -> 296 | Z25: 0.5 | AA25: =Z25*X25 -> 6 | AB25: =ROUNDUP(AA25,0) -> 6 | AC25: =AB25*3 -> 18 | AE25: =T25+T11 -> 72 | AF25: P8 | AG25: 2 | AH25: =AG25*12 -> 24 | AJ25: =T25+T11 -> 72 | AU25: TOTAL | AV25: =SUM(AV18:AV24) -> 45.9375 | AW25: =SUM(AW18:AW24) -> 42 | AY25: =SUM(AY18:AY24) -> 42 | AZ25: =SUM(AZ18:AZ24) -> 42 | BA25: =SUM(BA18:BA24) -> 42 | BB25: =SUM(BB18:BB24) -> 42 | BC25: =SUM(BC18:BC24) -> 42 | BD25: =SUM(BD18:BD24) -> 42 | BE25: =SUM(BE18:BE24) -> 42 | BF25: =SUM(BF18:BF24) -> 42 | ... BJ25: =SUM(BJ18:BJ24) -> 42
A26: 1. POY | B26: 1. POY | C26: 46357 | D26: ='YN01'!$J$51 -> 2967.7287 | E26: ='YN01'!$B$51 -> 270.46771 | F26: =24*12-12 -> 276 | G26: ='YN01'!$H$43 -> 0.93424658 | H26: ='YN01'!$I$43 -> 0.97 | I26: =D26*E26*F26*G26*H26*0.00016 -> 32121.952 | J26: =(BP!M90+BP!M91)/DAY(EOMONTH(C26,0)) -> 33711.281 | L26: =J26/I26 -> 1.049478 | M26: =IF((L26*F26)>F26,F26,(L26*F26)) -> 276 | N26: =M26/11.5 -> 24 | O26: =ROUNDUP(N26,0) -> 24 | P26: =O26*0.25 -> 6 | Q26: =P26*3 -> 18 | R26: =ROUNDUP(Q26,0) -> 18 | S26: ='Manpower Allocation'!$D$18 -> 25 | T26: =R26+S26 -> 43 | U26: =I26/V26 -> 2676.8293 | V26: 12 | W26: =(11*12*2)+(1*6*2) -> 276 | X26: =IF(J26>I26,V26,J26/U26) -> 12 | Y26: =ROUND(L26*W26,0) -> 290 | Z26: 0.5 | AA26: =Z26*X26 -> 6 | AB26: =ROUNDUP(AA26,0) -> 6 | AC26: =AB26*3 -> 18 | AE26: =T26+T12 -> 81 | AF26: P9 | AG26: 2 | AH26: =AG26*12 -> 24 | AJ26: =T26+T12 -> 81
A27: 1. POY | B27: 1. POY | C27: 46388 | D27: ='YN01'!$J$51 -> 2967.7287 | E27: ='YN01'!$B$51 -> 270.46771 | F27: =24*12-12 -> 276 | G27: ='YN01'!$H$43 -> 0.93424658 | H27: ='YN01'!$I$43 -> 0.97 | I27: =D27*E27*F27*G27*H27*0.00016 -> 32121.952 | J27: =(BP!N90+BP!N91)/DAY(EOMONTH(C27,0)) -> 33761.519 | L27: =J27/I27 -> 1.0510419 | M27: =IF((L27*F27)>F27,F27,(L27*F27)) -> 276 | N27: =M27/11.5 -> 24 | O27: =ROUNDUP(N27,0) -> 24 | P27: =O27*0.25 -> 6 | Q27: =P27*3 -> 18 | R27: =ROUNDUP(Q27,0) -> 18 | S27: ='Manpower Allocation'!$D$18 -> 25 | T27: =R27+S27 -> 43 | U27: =I27/V27 -> 2676.8293 | V27: 12 | W27: =(11*12*2)+(1*6*2) -> 276 | X27: =IF(J27>I27,V27,J27/U27) -> 12 | Y27: =ROUND(L27*W27,0) -> 290 | Z27: 0.5 | AA27: =Z27*X27 -> 6 | AB27: =ROUNDUP(AA27,0) -> 6 | AC27: =AB27*3 -> 18 | AE27: =T27+T13 -> 76 | AF27: P10 | AG27: 4 | AH27: =AG27*12 -> 48 | AJ27: =T27+T13 -> 76
A28: 1. POY | B28: 1. POY | C28: 46419 | D28: ='YN01'!$J$51 -> 2967.7287 | E28: ='YN01'!$B$51 -> 270.46771 | F28: =24*12-12 -> 276 | G28: ='YN01'!$H$43 -> 0.93424658 | H28: ='YN01'!$I$43 -> 0.97 | I28: =D28*E28*F28*G28*H28*0.00016 -> 32121.952 | J28: =(BP!O90+BP!O91)/DAY(EOMONTH(C28,0)) -> 35709.42 | L28: =J28/I28 -> 1.1116827 | M28: =IF((L28*F28)>F28,F28,(L28*F28)) -> 276 | N28: =M28/11.5 -> 24 | O28: =ROUNDUP(N28,0) -> 24 | P28: =O28*0.25 -> 6 | Q28: =P28*3 -> 18 | R28: =ROUNDUP(Q28,0) -> 18 | S28: ='Manpower Allocation'!$D$18 -> 25 | T28: =R28+S28 -> 43 | U28: =I28/V28 -> 2676.8293 | V28: 12 | W28: =(11*12*2)+(1*6*2) -> 276 | X28: =IF(J28>I28,V28,J28/U28) -> 12 | Y28: =ROUND(L28*W28,0) -> 307 | Z28: 0.5 | AA28: =Z28*X28 -> 6 | AB28: =ROUNDUP(AA28,0) -> 6 | AC28: =AB28*3 -> 18 | AE28: =T28+T14 -> 76 | AF28: P11 | AG28: 4 | AH28: =AG28*12 -> 48 | AJ28: =T28+T14 -> 76
A29: 1. POY | B29: 1. POY | C29: 46447 | D29: ='YN01'!$J$51 -> 2967.7287 | E29: ='YN01'!$B$51 -> 270.46771 | F29: =24*12-12 -> 276 | G29: ='YN01'!$H$43 -> 0.93424658 | H29: ='YN01'!$I$43 -> 0.97 | I29: =D29*E29*F29*G29*H29*0.00016 -> 32121.952 | J29: =(BP!P90+BP!P91)/DAY(EOMONTH(C29,0)) -> 29715.511 | L29: =J29/I29 -> 0.92508422 | M29: =IF((L29*F29)>F29,F29,(L29*F29)) -> 255.32325 | N29: =M29/11.5 -> 22.202021 | O29: =ROUNDUP(N29,0) -> 23 | P29: =O29*0.25 -> 5.75 | Q29: =P29*3 -> 17.25 | R29: =ROUNDUP(Q29,0) -> 18 | S29: ='Manpower Allocation'!$D$18 -> 25 | T29: =R29+S29 -> 43 | U29: =I29/V29 -> 2676.8293 | V29: 12 | W29: =(11*12*2)+(1*6*2) -> 276 | X29: =IF(J29>I29,V29,J29/U29) -> 11.101011 | Y29: =ROUND(L29*W29,0) -> 255 | Z29: 0.5 | AA29: =Z29*X29 -> 5.5505053 | AB29: =ROUNDUP(AA29,0) -> 6 | AC29: =AB29*3 -> 18 | AE29: =T29+T15 -> 74 | AF29: P12 | AG29: 4 | AH29: =AG29*12 -> 48 | AI29: 250/144 - 1 Opt - 48 Ends 480 - 1 Opt - 48 Ends | AJ29: =T29+T15 -> 74
Q30: =AVERAGE(Q18:Q29) -> 17.9375 | R30: =AVERAGE(R18:R29) -> 18 | AF30: P13 | AG30: 1 | AH30: =AG30*6 -> 6
N31: =AVERAGE(N4:N15) -> 8.5892747 | O31: =AVERAGE(O4:O15) -> 9 | P31: =O31/2 -> 4.5 | Q31: =P31*3 -> 13.5 | R31: =AVERAGE(R4:R15) -> 11.166667
A32: Section | B32: Machine | C32: Month | D32: Avg. Speed | E32: Avg. Denier | F32: Total Spindle | G32: Utilization | H32: Efficiency | I32: Capacity Per Day | J32: BP | L32: Spinder Req. | M32: Spinder Req. | N32: Winder Req. | O32: Winder Req. | P32: MP Req./Shift | Q32: MP Req./Day | R32: MP Req./Day | S32: Standard HC (Fix) | T32: Total Manpower Req. | U32: Capacity/machine | V32: Available M/C | W32: Available Spindles | X32: Req. M/C | Y32: Req. Spindles | Z32: HC Deployed/M/C | AA32: Total HC Req. /Shift | AB32: Total HC Req. /Shift | AC32: Total HC Req. /Day | AD32: Remarks | AE32: M/C | AF32: M/C | AG32: HC / M.C | AH32: HC / M.C | AW32: Avg MP | AY32: 45748 | AZ32: 45778 | BA32: 45809 | BB32: 45839 | BC32: 45870 | BD32: 45901 | BE32: 45931 | BF32: 45962 | BG32: 45992 | BH32: 46023 | BI32: 46054 | BJ32: 46082
A33: 3. Texturizing | B33: 3. Texturizing | C33: 46113 | D33: ='YN01'!$J$74 -> 546.20058 | E33: ='YN01'!$E$74 -> 284.63751 | F33: 1296 | G33: ='YN01'!$H$64 -> 0.94957983 | H33: ='YN01'!$I$64 -> 0.96 | I33: =D33*E33*F33*G33*H33*0.00016 -> 29388.133 | J33: =(BP!E105+BP!E106)/DAY(EOMONTH(C33,0)) -> 48085.277 | L33: =J33/I33 -> 1.6362141 | M33: =IF((L33*F33)>F33,F33,(L33*F33)) -> 1296 | N33: =M33 -> 1296 | O33: =ROUNDUP(N33,0) -> 1296 | P33: ='Manpower Allocation'!$S$30 -> 20.5 | Q33: =P33*3 -> 61.5 | R33: =ROUNDUP(Q33,0) -> 62 | S33: ='Manpower Allocation'!$D$28 -> 22 | T33: =R33+S33 -> 84 | U33: =I33/V33 -> 3673.5166 | V33: =6+2 -> 8 | W33: =(4*224)+(2*336)+32+32 -> 1632 | X33: =IF(J33>I33,V33,J33/U33) -> 8 | Y33: =W33*L33 -> 2670.3014 | Z33: =$AH$36 -> 2.5625 | AA33: =Z33*X33 -> 20.5 | AB33: =ROUNDUP(AA33,0) -> 21 | AC33: =AB33*3 -> 63 | AD33: 1 M/C ~ 204 Spindles = 1 Opt ~ 80 Spindles | AE33: 4.5 | AF33: 4 | AG33: 3 | AH33: 3 | AI33: =224*AF33 -> 896 | AJ33: =AI33/AF33 -> 224 | AT33: =(6*1*3*3)+6 -> 60 | AU33: Operator | AV33: =(P47*3) -> 61.5 | AW33: =20*3 -> 60 | AY33: =20*3 -> 60 | AZ33: =20*3 -> 60 | BA33: =20*3 -> 60 | BB33: =20*3 -> 60 | BC33: =20*3 -> 60 | BD33: =20*3 -> 60 | BE33: =20*3 -> 60 | BF33: =20*3 -> 60 | ... BJ33: =20*3 -> 60 | BK33: =15*3 -> 45 | BP33: =J33/1.2 -> 40071.064
A34: 3. Texturizing | B34: 3. Texturizing | C34: 46143 | D34: ='YN01'!$J$74 -> 546.20058 | E34: ='YN01'!$E$74 -> 284.63751 | F34: 1296 | G34: ='YN01'!$H$64 -> 0.94957983 | H34: ='YN01'!$I$64 -> 0.96 | I34: =D34*E34*F34*G34*H34*0.00016 -> 29388.133 | J34: =(BP!F105+BP!F106)/DAY(EOMONTH(C34,0)) -> 40196.04 | L34: =J34/I34 -> 1.3677643 | M34: =IF((L34*F34)>F34,F34,(L34*F34)) -> 1296 | N34: =M34 -> 1296 | O34: =ROUNDUP(N34,0) -> 1296 | P34: ='Manpower Allocation'!$S$30 -> 20.5 | Q34: =P34*3 -> 61.5 | R34: =ROUNDUP(Q34,0) -> 62 | S34: ='Manpower Allocation'!$D$28 -> 22 | T34: =R34+S34 -> 84 | U34: =I34/V34 -> 3673.5166 | V34: =6+2 -> 8 | W34: =(4*224)+(2*336)+32+32 -> 1632 | X34: =IF(J34>I34,V34,J34/U34) -> 8 | Y34: =W34*L34 -> 2232.1914 | Z34: =$AH$36 -> 2.5625 | AA34: =Z34*X34 -> 20.5 | AB34: =ROUNDUP(AA34,0) -> 21 | AC34: =AB34*3 -> 63 | AE34: 1.5 | AF34: 2 | AG34: 4 | AH34: 4 | AI34: =336*AF34 -> 672 | AJ34: =AI34/AF34 -> 336 | AU34: Helper | AV34: 12 | AW34: 9 | AY34: 9 | AZ34: 9 | BA34: 9 | BB34: 9 | BC34: 9 | BD34: 9 | BE34: 9 | BF34: 9 | BG34: 9 | BH34: 9 | BI34: 9 | BJ34: 9 | BK34: 9
A35: 3. Texturizing | B35: 3. Texturizing | C35: 46174 | D35: ='YN01'!$J$74 -> 546.20058 | E35: ='YN01'!$E$74 -> 284.63751 | F35: 1296 | G35: ='YN01'!$H$64 -> 0.94957983 | H35: ='YN01'!$I$64 -> 0.96 | I35: =D35*E35*F35*G35*H35*0.00016 -> 29388.133 | J35: =(BP!G105+BP!G106)/DAY(EOMONTH(C35,0)) -> 38656.901 | L35: =J35/I35 -> 1.3153915 | M35: =IF((L35*F35)>F35,F35,(L35*F35)) -> 1296 | N35: =M35 -> 1296 | O35: =ROUNDUP(N35,0) -> 1296 | P35: ='Manpower Allocation'!$S$30 -> 20.5 | Q35: =P35*3 -> 61.5 | R35: =ROUNDUP(Q35,0) -> 62 | S35: ='Manpower Allocation'!$D$28 -> 22 | T35: =R35+S35 -> 84 | U35: =I35/V35 -> 3673.5166 | V35: =6+2 -> 8 | W35: =(4*224)+(2*336)+32+32 -> 1632 | X35: =IF(J35>I35,V35,J35/U35) -> 8 | Y35: =W35*L35 -> 2146.7189 | Z35: =$AH$36 -> 2.5625 | AA35: =Z35*X35 -> 20.5 | AB35: =ROUNDUP(AA35,0) -> 21 | AC35: =AB35*3 -> 63 | AE35: 2 | AF35: 2 | AG35: 0.5 | AH35: 0.5 | AI35: =32+32 -> 64 | AJ35: =AI35/AF35 -> 32 | AU35: DOE | AV35: 3 | AW35: 0 | AY35: 0 | AZ35: 0 | BA35: 0 | BB35: 0 | BC35: 0 | BD35: 0 | BE35: 0 | BF35: 0 | BG35: 0 | BH35: 0 | BI35: 0 | BJ35: 0 | BK35: 0
A36: 3. Texturizing | B36: 3. Texturizing | C36: 46204 | D36: ='YN01'!$J$74 -> 546.20058 | E36: ='YN01'!$E$74 -> 284.63751 | F36: 1296 | G36: ='YN01'!$H$64 -> 0.94957983 | H36: ='YN01'!$I$64 -> 0.96 | I36: =D36*E36*F36*G36*H36*0.00016 -> 29388.133 | J36: =(BP!H105+BP!H106)/DAY(EOMONTH(C36,0)) -> 40295.114 | L36: =J36/I36 -> 1.3711355 | M36: =IF((L36*F36)>F36,F36,(L36*F36)) -> 1296 | N36: =M36 -> 1296 | O36: =ROUNDUP(N36,0) -> 1296 | P36: ='Manpower Allocation'!$S$30 -> 20.5 | Q36: =P36*3 -> 61.5 | R36: =ROUNDUP(Q36,0) -> 62 | S36: ='Manpower Allocation'!$D$28 -> 22 | T36: =R36+S36 -> 84 | U36: =I36/V36 -> 3673.5166 | V36: =6+2 -> 8 | W36: =(4*224)+(2*336)+32+32 -> 1632 | X36: =IF(J36>I36,V36,J36/U36) -> 8 | Y36: =W36*L36 -> 2237.6932 | Z36: =$AH$36 -> 2.5625 | AA36: =Z36*X36 -> 20.5 | AB36: =ROUNDUP(AA36,0) -> 21 | AC36: =AB36*3 -> 63 | AG36: =SUMPRODUCT(AG33:AG35,AF33:AF35)/SUM(AF33:AF35) -> 2.625 | AH36: =SUMPRODUCT(AH33:AH35,AE33:AE35)/SUM(AE33:AE35) -> 2.5625 | AJ36: =SUMPRODUCT(AJ33:AJ35,AF33:AF35)/SUM(AF33:AF35) -> 204 | AU36: Jobber | AV36: 3 | AW36: 3 | AY36: 3 | AZ36: 3 | BA36: 3 | BB36: 3 | BC36: 3 | BD36: 3 | BE36: 3 | BF36: 3 | BG36: 3 | BH36: 3 | BI36: 3 | BJ36: 3 | BK36: 3
A37: 3. Texturizing | B37: 3. Texturizing | C37: 46235 | D37: ='YN01'!$J$74 -> 546.20058 | E37: ='YN01'!$E$74 -> 284.63751 | F37: 1296 | G37: ='YN01'!$H$64 -> 0.94957983 | H37: ='YN01'!$I$64 -> 0.96 | I37: =D37*E37*F37*G37*H37*0.00016 -> 29388.133 | J37: =(BP!I105+BP!I106)/DAY(EOMONTH(C37,0)) -> 43144.011 | L37: =J37/I37 -> 1.468076 | M37: =IF((L37*F37)>F37,F37,(L37*F37)) -> 1296 | N37: =M37 -> 1296 | O37: =ROUNDUP(N37,0) -> 1296 | P37: ='Manpower Allocation'!$S$30 -> 20.5 | Q37: =P37*3 -> 61.5 | R37: =ROUNDUP(Q37,0) -> 62 | S37: ='Manpower Allocation'!$D$28 -> 22 | T37: =R37+S37 -> 84 | U37: =I37/V37 -> 3673.5166 | V37: =6+2 -> 8 | W37: =(4*224)+(2*336)+32+32 -> 1632 | X37: =IF(J37>I37,V37,J37/U37) -> 8 | Y37: =W37*L37 -> 2395.9 | Z37: =$AH$36 -> 2.5625 | AA37: =Z37*X37 -> 20.5 | AB37: =ROUNDUP(AA37,0) -> 21 | AC37: =AB37*3 -> 63 | AJ37: =AJ36/AH36 -> 79.609756 | AU37: Fitter | AV37: 3 | AW37: 3 | AY37: 3 | AZ37: 3 | BA37: 3 | BB37: 3 | BC37: 3 | BD37: 3 | BE37: 3 | BF37: 3 | BG37: 3 | BH37: 3 | BI37: 3 | BJ37: 3 | BK37: 3
A38: 3. Texturizing | B38: 3. Texturizing | C38: 46266 | D38: ='YN01'!$J$74 -> 546.20058 | E38: ='YN01'!$E$74 -> 284.63751 | F38: 1296 | G38: ='YN01'!$H$64 -> 0.94957983 | H38: ='YN01'!$I$64 -> 0.96 | I38: =D38*E38*F38*G38*H38*0.00016 -> 29388.133 | J38: =(BP!J105+BP!J106)/DAY(EOMONTH(C38,0)) -> 38015.306 | L38: =J38/I38 -> 1.2935597 | M38: =IF((L38*F38)>F38,F38,(L38*F38)) -> 1296 | N38: =M38 -> 1296 | O38: =ROUNDUP(N38,0) -> 1296 | P38: ='Manpower Allocation'!$S$30 -> 20.5 | Q38: =P38*3 -> 61.5 | R38: =ROUNDUP(Q38,0) -> 62 | S38: ='Manpower Allocation'!$D$28 -> 22 | T38: =R38+S38 -> 84 | U38: =I38/V38 -> 3673.5166 | V38: =6+2 -> 8 | W38: =(4*224)+(2*336)+32+32 -> 1632 | X38: =IF(J38>I38,V38,J38/U38) -> 8 | Y38: =W38*L38 -> 2111.0895 | Z38: =$AH$36 -> 2.5625 | AA38: =Z38*X38 -> 20.5 | AB38: =ROUNDUP(AA38,0) -> 21 | AC38: =AB38*3 -> 63 | AT38: 5 M/C | AU38: Material Handler | AV38: 3 | AW38: 3 | AY38: 3 | AZ38: 3 | BA38: 3 | BB38: 3 | BC38: 3 | BD38: 3 | BE38: 3 | BF38: 3 | BG38: 3 | BH38: 3 | BI38: 3 | BJ38: 3 | BK38: 3
A39: 3. Texturizing | B39: 3. Texturizing | C39: 46296 | D39: ='YN01'!$J$74 -> 546.20058 | E39: ='YN01'!$E$74 -> 284.63751 | F39: 1296 | G39: ='YN01'!$H$64 -> 0.94957983 | H39: ='YN01'!$I$64 -> 0.96 | I39: =D39*E39*F39*G39*H39*0.00016 -> 29388.133 | J39: =(BP!K105+BP!K106)/DAY(EOMONTH(C39,0)) -> 37561.646 | L39: =J39/I39 -> 1.2781229 | M39: =IF((L39*F39)>F39,F39,(L39*F39)) -> 1296 | N39: =M39 -> 1296 | O39: =ROUNDUP(N39,0) -> 1296 | P39: ='Manpower Allocation'!$S$30 -> 20.5 | Q39: =P39*3 -> 61.5 | R39: =ROUNDUP(Q39,0) -> 62 | S39: ='Manpower Allocation'!$D$28 -> 22 | T39: =R39+S39 -> 84 | U39: =I39/V39 -> 3673.5166 | V39: =6+2 -> 8 | W39: =(4*224)+(2*336)+32+32 -> 1632 | X39: =IF(J39>I39,V39,J39/U39) -> 8 | Y39: =W39*L39 -> 2085.8966 | Z39: =$AH$36 -> 2.5625 | AA39: =Z39*X39 -> 20.5 | AB39: =ROUNDUP(AA39,0) -> 21 | AC39: =AB39*3 -> 63 | AU39: Paper Tube Sagrigation | AV39: 3 | AW39: 1 | AX39: ** Segregation to be done at common station with uniform & justified workload distribution. | AY39: 1 | AZ39: 1 | BA39: 1 | BB39: 1 | BC39: 1 | BD39: 1 | BE39: 1 | BF39: 1 | BG39: 1 | BH39: 1 | BI39: 1 | BJ39: 1 | BK39: 1
A40: 3. Texturizing | B40: 3. Texturizing | C40: 46327 | D40: ='YN01'!$J$74 -> 546.20058 | E40: ='YN01'!$E$74 -> 284.63751 | F40: 1296 | G40: ='YN01'!$H$64 -> 0.94957983 | H40: ='YN01'!$I$64 -> 0.96 | I40: =D40*E40*F40*G40*H40*0.00016 -> 29388.133 | J40: =(BP!L105+BP!L106)/DAY(EOMONTH(C40,0)) -> 34406.077 | L40: =J40/I40 -> 1.1707473 | M40: =IF((L40*F40)>F40,F40,(L40*F40)) -> 1296 | N40: =M40 -> 1296 | O40: =ROUNDUP(N40,0) -> 1296 | P40: ='Manpower Allocation'!$S$30 -> 20.5 | Q40: =P40*3 -> 61.5 | R40: =ROUNDUP(Q40,0) -> 62 | S40: ='Manpower Allocation'!$D$28 -> 22 | T40: =R40+S40 -> 84 | U40: =I40/V40 -> 3673.5166 | V40: =6+2 -> 8 | W40: =(4*224)+(2*336)+32+32 -> 1632 | X40: =IF(J40>I40,V40,J40/U40) -> 8 | Y40: =W40*L40 -> 1910.6596 | Z40: =$AH$36 -> 2.5625 | AA40: =Z40*X40 -> 20.5 | AB40: =ROUNDUP(AA40,0) -> 21 | AC40: =AB40*3 -> 63 | AU40: Roping (Mandays) | AV40: 3 | AW40: 3 | AY40: 3 | AZ40: 3 | BA40: 3 | BB40: 3 | BC40: 3 | BD40: 3 | BE40: 3 | BF40: 3 | BG40: 3 | BH40: 3 | BI40: 3 | BJ40: 3 | BK40: 3
A41: 3. Texturizing | B41: 3. Texturizing | C41: 46357 | D41: ='YN01'!$J$74 -> 546.20058 | E41: ='YN01'!$E$74 -> 284.63751 | F41: 1296 | G41: ='YN01'!$H$64 -> 0.94957983 | H41: ='YN01'!$I$64 -> 0.96 | I41: =D41*E41*F41*G41*H41*0.00016 -> 29388.133 | J41: =(BP!M105+BP!M106)/DAY(EOMONTH(C41,0)) -> 33689.359 | L41: =J41/I41 -> 1.1463593 | M41: =IF((L41*F41)>F41,F41,(L41*F41)) -> 1296 | N41: =M41 -> 1296 | O41: =ROUNDUP(N41,0) -> 1296 | P41: ='Manpower Allocation'!$S$30 -> 20.5 | Q41: =P41*3 -> 61.5 | R41: =ROUNDUP(Q41,0) -> 62 | S41: ='Manpower Allocation'!$D$28 -> 22 | T41: =R41+S41 -> 84 | U41: =I41/V41 -> 3673.5166 | V41: =6+2 -> 8 | W41: =(4*224)+(2*336)+32+32 -> 1632 | X41: =IF(J41>I41,V41,J41/U41) -> 8 | Y41: =W41*L41 -> 1870.8583 | Z41: =$AH$36 -> 2.5625 | AA41: =Z41*X41 -> 20.5 | AB41: =ROUNDUP(AA41,0) -> 21 | AC41: =AB41*3 -> 63 | AU41: TOTAL | AV41: =SUM(AV33:AV40) -> 91.5 | AW41: =SUM(AW33:AW40) -> 82 | AY41: =SUM(AY33:AY40) -> 82 | AZ41: =SUM(AZ33:AZ40) -> 82 | BA41: =SUM(BA33:BA40) -> 82 | BB41: =SUM(BB33:BB40) -> 82 | BC41: =SUM(BC33:BC40) -> 82 | BD41: =SUM(BD33:BD40) -> 82 | BE41: =SUM(BE33:BE40) -> 82 | BF41: =SUM(BF33:BF40) -> 82 | ... BK41: =SUM(BK33:BK40) -> 67
A42: 3. Texturizing | B42: 3. Texturizing | C42: 46388 | D42: ='YN01'!$J$74 -> 546.20058 | E42: ='YN01'!$E$74 -> 284.63751 | F42: 1296 | G42: ='YN01'!$H$64 -> 0.94957983 | H42: ='YN01'!$I$64 -> 0.96 | I42: =D42*E42*F42*G42*H42*0.00016 -> 29388.133 | J42: =(BP!N105+BP!N106)/DAY(EOMONTH(C42,0)) -> 33726.016 | L42: =J42/I42 -> 1.1476066 | M42: =IF((L42*F42)>F42,F42,(L42*F42)) -> 1296 | N42: =M42 -> 1296 | O42: =ROUNDUP(N42,0) -> 1296 | P42: ='Manpower Allocation'!$S$30 -> 20.5 | Q42: =P42*3 -> 61.5 | R42: =ROUNDUP(Q42,0) -> 62 | S42: ='Manpower Allocation'!$D$28 -> 22 | T42: =R42+S42 -> 84 | U42: =I42/V42 -> 3673.5166 | V42: =6+2 -> 8 | W42: =(4*224)+(2*336)+32+32 -> 1632 | X42: =IF(J42>I42,V42,J42/U42) -> 8 | Y42: =W42*L42 -> 1872.894 | Z42: =$AH$36 -> 2.5625 | AA42: =Z42*X42 -> 20.5 | AB42: =ROUNDUP(AA42,0) -> 21 | AC42: =AB42*3 -> 63
A43: 3. Texturizing | B43: 3. Texturizing | C43: 46419 | D43: ='YN01'!$J$74 -> 546.20058 | E43: ='YN01'!$E$74 -> 284.63751 | F43: 1296 | G43: ='YN01'!$H$64 -> 0.94957983 | H43: ='YN01'!$I$64 -> 0.96 | I43: =D43*E43*F43*G43*H43*0.00016 -> 29388.133 | J43: =(BP!O105+BP!O106)/DAY(EOMONTH(C43,0)) -> 35663.594 | L43: =J43/I43 -> 1.2135372 | M43: =IF((L43*F43)>F43,F43,(L43*F43)) -> 1296 | N43: =M43 -> 1296 | O43: =ROUNDUP(N43,0) -> 1296 | P43: ='Manpower Allocation'!$S$30 -> 20.5 | Q43: =P43*3 -> 61.5 | R43: =ROUNDUP(Q43,0) -> 62 | S43: ='Manpower Allocation'!$D$28 -> 22 | T43: =R43+S43 -> 84 | U43: =I43/V43 -> 3673.5166 | V43: =6+2 -> 8 | W43: =(4*224)+(2*336)+32+32 -> 1632 | X43: =IF(J43>I43,V43,J43/U43) -> 8 | Y43: =W43*L43 -> 1980.4928 | Z43: =$AH$36 -> 2.5625 | AA43: =Z43*X43 -> 20.5 | AB43: =ROUNDUP(AA43,0) -> 21 | AC43: =AB43*3 -> 63
A44: 3. Texturizing | B44: 3. Texturizing | C44: 46447 | D44: ='YN01'!$J$74 -> 546.20058 | E44: ='YN01'!$E$74 -> 284.63751 | F44: 1296 | G44: ='YN01'!$H$64 -> 0.94957983 | H44: ='YN01'!$I$64 -> 0.96 | I44: =D44*E44*F44*G44*H44*0.00016 -> 29388.133 | J44: =(BP!P105+BP!P106)/DAY(EOMONTH(C44,0)) -> 29814.29 | L44: =J44/I44 -> 1.014501 | M44: =IF((L44*F44)>F44,F44,(L44*F44)) -> 1296 | N44: =M44 -> 1296 | O44: =ROUNDUP(N44,0) -> 1296 | P44: ='Manpower Allocation'!$S$30 -> 20.5 | Q44: =P44*3 -> 61.5 | R44: =ROUNDUP(Q44,0) -> 62 | S44: ='Manpower Allocation'!$D$28 -> 22 | T44: =R44+S44 -> 84 | U44: =I44/V44 -> 3673.5166 | V44: =6+2 -> 8 | W44: =(4*224)+(2*336)+32+32 -> 1632 | X44: =IF(J44>I44,V44,J44/U44) -> 8 | Y44: =W44*L44 -> 1655.6656 | Z44: =$AH$36 -> 2.5625 | AA44: =Z44*X44 -> 20.5 | AB44: =ROUNDUP(AA44,0) -> 21 | AC44: =AB44*3 -> 63
P47: =AVERAGE(P33:P44) -> 20.5
A48: Section | B48: Machine | C48: Month | D48: Avg. Speed | E48: Avg. Denier | F48: Total Spindle | G48: Utilization | H48: Efficiency | I48: Capacity Per Day | J48: BP | L48: Spinder Req. | M48: Spinder Req. | N48: Winder Req. | O48: Winder Req. | P48: MP Req./Shift | Q48: MP Req./Day | R48: MP Req./Day | S48: Standard HC (Fix) | T48: Total Manpower Req. | U48: Capacity/machine | V48: Available M/C | W48: Available Spindles | X48: Req. M/C | Y48: Req. Spindles | Z48: HC Deployed/M/C | AA48: Total HC Req. /Shift | AB48: Total HC Req. /Shift | AC48: Total HC Req. /Day | AD48: Remarks | AW48: Avg MP | AY48: 45748 | AZ48: 45778 | BA48: 45809 | BB48: 45839 | BC48: 45870 | BD48: 45901 | BE48: 45931 | BF48: 45962 | BG48: 45992 | BH48: 46023 | BI48: 46054 | BJ48: 46082
A49: 4. Parallel Winding | B49: 4. PW | C49: 46113 | D49: ='YN01'!$J$94 -> 520.63123 | E49: ='YN01'!$E$94 -> 1446.7335 | F49: 176 | G49: ='YN01'!$H$94 -> 0.94957983 | H49: ='YN01'!$I$94 -> 0.7 | I49: =D49*E49*F49*G49*H49*0.00016 -> 14098.76 | J49: =BP!E115/DAY(EOMONTH(C49,0)) -> 25757.709 | L49: =J49/I49 -> 1.8269485 | M49: =IF((L49*F49)>F49,F49,(L49*F49)) -> 176 | N49: =M49 -> 176 | O49: =ROUNDUP(N49,0) -> 176 | P49: =2*4 -> 8 | Q49: =P49*3 -> 24 | R49: =ROUNDUP(Q49,0) -> 24 | S49: ='Manpower Allocation'!$D$33 -> 3 | T49: =R49+S49 -> 27 | U49: =I49/V49 -> 3524.69 | V49: 4 | W49: =4*44 -> 176 | X49: =IF(J49>I49,V49,J49/U49) -> 4 | Y49: =L49*W49 -> 321.54294 | Z49: 2 | AA49: =Z49*X49 -> 8 | AB49: =ROUNDUP(AA49,0) -> 8 | AC49: =AB49*3 -> 24 | AD49: 1 M/C ~ 44 Spindle = 1 Opt. ~ 22 Spindle | AT49: =(4*3)+(2*3)+(1*2) -> 20 | AU49: Operator | AV49: =ROUNDUP(Q62,0) -> 24 | AW49: =(2*3*3) -> 18 | AY49: =4*2*3 -> 24 | AZ49: =4*2*3 -> 24 | BA49: =4*2*3 -> 24 | BB49: =4*2*3 -> 24 | BC49: =4*2*3 -> 24 | BD49: =4*2*3 -> 24 | BE49: =4*2*3 -> 24 | BF49: =4*2*3 -> 24 | ... BJ49: =4*2*3 -> 24 | BP49: 1 Jobber in Gel. + 1 Jobber Night
A50: 4. Parallel Winding | B50: 4. PW | C50: 46143 | D50: ='YN01'!$J$94 -> 520.63123 | E50: ='YN01'!$E$94 -> 1446.7335 | F50: 176 | G50: ='YN01'!$H$94 -> 0.94957983 | H50: ='YN01'!$I$94 -> 0.7 | I50: =D50*E50*F50*G50*H50*0.00016 -> 14098.76 | J50: =BP!F115/DAY(EOMONTH(C50,0)) -> 21764.218 | L50: =J50/I50 -> 1.5436973 | M50: =IF((L50*F50)>F50,F50,(L50*F50)) -> 176 | N50: =M50 -> 176 | O50: =ROUNDUP(N50,0) -> 176 | P50: =2*4 -> 8 | Q50: =P50*3 -> 24 | R50: =ROUNDUP(Q50,0) -> 24 | S50: ='Manpower Allocation'!$D$33 -> 3 | T50: =R50+S50 -> 27 | U50: =I50/V50 -> 3524.69 | V50: 4 | W50: =4*44 -> 176 | X50: =IF(J50>I50,V50,J50/U50) -> 4 | Y50: =L50*W50 -> 271.69073 | Z50: 2 | AA50: =Z50*X50 -> 8 | AB50: =ROUNDUP(AA50,0) -> 8 | AC50: =AB50*3 -> 24 | AU50: Jobber | AV50: =1*3 -> 3 | AW50: =(1*2) -> 2 | AY50: 3 | AZ50: 3 | BA50: 3 | BB50: 3 | BC50: 3 | BD50: 3 | BE50: 3 | BF50: 3 | BG50: 3 | BH50: 3 | BI50: 3 | BJ50: 3
A51: 4. Parallel Winding | B51: 4. PW | C51: 46174 | D51: ='YN01'!$J$94 -> 520.63123 | E51: ='YN01'!$E$94 -> 1446.7335 | F51: 176 | G51: ='YN01'!$H$94 -> 0.94957983 | H51: ='YN01'!$I$94 -> 0.7 | I51: =D51*E51*F51*G51*H51*0.00016 -> 14098.76 | J51: =BP!G115/DAY(EOMONTH(C51,0)) -> 20261.879 | L51: =J51/I51 -> 1.4371391 | M51: =IF((L51*F51)>F51,F51,(L51*F51)) -> 176 | N51: =M51 -> 176 | O51: =ROUNDUP(N51,0) -> 176 | P51: =2*4 -> 8 | Q51: =P51*3 -> 24 | R51: =ROUNDUP(Q51,0) -> 24 | S51: ='Manpower Allocation'!$D$33 -> 3 | T51: =R51+S51 -> 27 | U51: =I51/V51 -> 3524.69 | V51: 4 | W51: =4*44 -> 176 | X51: =IF(J51>I51,V51,J51/U51) -> 4 | Y51: =L51*W51 -> 252.93648 | Z51: 2 | AA51: =Z51*X51 -> 8 | AB51: =ROUNDUP(AA51,0) -> 8 | AC51: =AB51*3 -> 24 | AU51: TOTAL | AV51: =SUM(AV49:AV50) -> 27 | AW51: =SUM(AW49:AW50)+7 -> 27 | AY51: =SUM(AY49:AY50) -> 27 | AZ51: =SUM(AZ49:AZ50) -> 27 | BA51: =SUM(BA49:BA50) -> 27 | BB51: =SUM(BB49:BB50) -> 27 | BC51: =SUM(BC49:BC50) -> 27 | BD51: =SUM(BD49:BD50) -> 27 | BE51: =SUM(BE49:BE50) -> 27 | BF51: =SUM(BF49:BF50) -> 27 | ... BJ51: =SUM(BJ49:BJ50) -> 27
A52: 4. Parallel Winding | B52: 4. PW | C52: 46204 | D52: ='YN01'!$J$94 -> 520.63123 | E52: ='YN01'!$E$94 -> 1446.7335 | F52: 176 | G52: ='YN01'!$H$94 -> 0.94957983 | H52: ='YN01'!$I$94 -> 0.7 | I52: =D52*E52*F52*G52*H52*0.00016 -> 14098.76 | J52: =BP!H115/DAY(EOMONTH(C52,0)) -> 22493.296 | L52: =J52/I52 -> 1.5954095 | M52: =IF((L52*F52)>F52,F52,(L52*F52)) -> 176 | N52: =M52 -> 176 | O52: =ROUNDUP(N52,0) -> 176 | P52: =2*4 -> 8 | Q52: =P52*3 -> 24 | R52: =ROUNDUP(Q52,0) -> 24 | S52: ='Manpower Allocation'!$D$33 -> 3 | T52: =R52+S52 -> 27 | U52: =I52/V52 -> 3524.69 | V52: 4 | W52: =4*44 -> 176 | X52: =IF(J52>I52,V52,J52/U52) -> 4 | Y52: =L52*W52 -> 280.79208 | Z52: 2 | AA52: =Z52*X52 -> 8 | AB52: =ROUNDUP(AA52,0) -> 8 | AC52: =AB52*3 -> 24
A53: 4. Parallel Winding | B53: 4. PW | C53: 46235 | D53: ='YN01'!$J$94 -> 520.63123 | E53: ='YN01'!$E$94 -> 1446.7335 | F53: 176 | G53: ='YN01'!$H$94 -> 0.94957983 | H53: ='YN01'!$I$94 -> 0.7 | I53: =D53*E53*F53*G53*H53*0.00016 -> 14098.76 | J53: =BP!I115/DAY(EOMONTH(C53,0)) -> 21203.283 | L53: =J53/I53 -> 1.5039112 | M53: =IF((L53*F53)>F53,F53,(L53*F53)) -> 176 | N53: =M53 -> 176 | O53: =ROUNDUP(N53,0) -> 176 | P53: =2*4 -> 8 | Q53: =P53*3 -> 24 | R53: =ROUNDUP(Q53,0) -> 24 | S53: ='Manpower Allocation'!$D$33 -> 3 | T53: =R53+S53 -> 27 | U53: =I53/V53 -> 3524.69 | V53: 4 | W53: =4*44 -> 176 | X53: =IF(J53>I53,V53,J53/U53) -> 4 | Y53: =L53*W53 -> 264.68837 | Z53: 2 | AA53: =Z53*X53 -> 8 | AB53: =ROUNDUP(AA53,0) -> 8 | AC53: =AB53*3 -> 24
A54: 4. Parallel Winding | B54: 4. PW | C54: 46266 | D54: ='YN01'!$J$94 -> 520.63123 | E54: ='YN01'!$E$94 -> 1446.7335 | F54: 176 | G54: ='YN01'!$H$94 -> 0.94957983 | H54: ='YN01'!$I$94 -> 0.7 | I54: =D54*E54*F54*G54*H54*0.00016 -> 14098.76 | J54: =BP!J115/DAY(EOMONTH(C54,0)) -> 21151.793 | L54: =J54/I54 -> 1.5002591 | M54: =IF((L54*F54)>F54,F54,(L54*F54)) -> 176 | N54: =M54 -> 176 | O54: =ROUNDUP(N54,0) -> 176 | P54: =2*4 -> 8 | Q54: =P54*3 -> 24 | R54: =ROUNDUP(Q54,0) -> 24 | S54: ='Manpower Allocation'!$D$33 -> 3 | T54: =R54+S54 -> 27 | U54: =I54/V54 -> 3524.69 | V54: 4 | W54: =4*44 -> 176 | X54: =IF(J54>I54,V54,J54/U54) -> 4 | Y54: =L54*W54 -> 264.0456 | Z54: 2 | AA54: =Z54*X54 -> 8 | AB54: =ROUNDUP(AA54,0) -> 8 | AC54: =AB54*3 -> 24
A55: 4. Parallel Winding | B55: 4. PW | C55: 46296 | D55: ='YN01'!$J$94 -> 520.63123 | E55: ='YN01'!$E$94 -> 1446.7335 | F55: 176 | G55: ='YN01'!$H$94 -> 0.94957983 | H55: ='YN01'!$I$94 -> 0.7 | I55: =D55*E55*F55*G55*H55*0.00016 -> 14098.76 | J55: =BP!K115/DAY(EOMONTH(C55,0)) -> 19854.218 | L55: =J55/I55 -> 1.4082244 | M55: =IF((L55*F55)>F55,F55,(L55*F55)) -> 176 | N55: =M55 -> 176 | O55: =ROUNDUP(N55,0) -> 176 | P55: =2*4 -> 8 | Q55: =P55*3 -> 24 | R55: =ROUNDUP(Q55,0) -> 24 | S55: ='Manpower Allocation'!$D$33 -> 3 | T55: =R55+S55 -> 27 | U55: =I55/V55 -> 3524.69 | V55: 4 | W55: =4*44 -> 176 | X55: =IF(J55>I55,V55,J55/U55) -> 4 | Y55: =L55*W55 -> 247.8475 | Z55: 2 | AA55: =Z55*X55 -> 8 | AB55: =ROUNDUP(AA55,0) -> 8 | AC55: =AB55*3 -> 24
A56: 4. Parallel Winding | B56: 4. PW | C56: 46327 | D56: ='YN01'!$J$94 -> 520.63123 | E56: ='YN01'!$E$94 -> 1446.7335 | F56: 176 | G56: ='YN01'!$H$94 -> 0.94957983 | H56: ='YN01'!$I$94 -> 0.7 | I56: =D56*E56*F56*G56*H56*0.00016 -> 14098.76 | J56: =BP!L115/DAY(EOMONTH(C56,0)) -> 18321.187 | L56: =J56/I56 -> 1.2994892 | M56: =IF((L56*F56)>F56,F56,(L56*F56)) -> 176 | N56: =M56 -> 176 | O56: =ROUNDUP(N56,0) -> 176 | P56: =2*4 -> 8 | Q56: =P56*3 -> 24 | R56: =ROUNDUP(Q56,0) -> 24 | S56: ='Manpower Allocation'!$D$33 -> 3 | T56: =R56+S56 -> 27 | U56: =I56/V56 -> 3524.69 | V56: 4 | W56: =4*44 -> 176 | X56: =IF(J56>I56,V56,J56/U56) -> 4 | Y56: =L56*W56 -> 228.7101 | Z56: 2 | AA56: =Z56*X56 -> 8 | AB56: =ROUNDUP(AA56,0) -> 8 | AC56: =AB56*3 -> 24
A57: 4. Parallel Winding | B57: 4. PW | C57: 46357 | D57: ='YN01'!$J$94 -> 520.63123 | E57: ='YN01'!$E$94 -> 1446.7335 | F57: 176 | G57: ='YN01'!$H$94 -> 0.94957983 | H57: ='YN01'!$I$94 -> 0.7 | I57: =D57*E57*F57*G57*H57*0.00016 -> 14098.76 | J57: =BP!M115/DAY(EOMONTH(C57,0)) -> 21404.061 | L57: =J57/I57 -> 1.518152 | M57: =IF((L57*F57)>F57,F57,(L57*F57)) -> 176 | N57: =M57 -> 176 | O57: =ROUNDUP(N57,0) -> 176 | P57: =2*4 -> 8 | Q57: =P57*3 -> 24 | R57: =ROUNDUP(Q57,0) -> 24 | S57: ='Manpower Allocation'!$D$33 -> 3 | T57: =R57+S57 -> 27 | U57: =I57/V57 -> 3524.69 | V57: 4 | W57: =4*44 -> 176 | X57: =IF(J57>I57,V57,J57/U57) -> 4 | Y57: =L57*W57 -> 267.19475 | Z57: 2 | AA57: =Z57*X57 -> 8 | AB57: =ROUNDUP(AA57,0) -> 8 | AC57: =AB57*3 -> 24
A58: 4. Parallel Winding | B58: 4. PW | C58: 46388 | D58: ='YN01'!$J$94 -> 520.63123 | E58: ='YN01'!$E$94 -> 1446.7335 | F58: 176 | G58: ='YN01'!$H$94 -> 0.94957983 | H58: ='YN01'!$I$94 -> 0.7 | I58: =D58*E58*F58*G58*H58*0.00016 -> 14098.76 | J58: =BP!N115/DAY(EOMONTH(C58,0)) -> 20437.995 | L58: =J58/I58 -> 1.4496306 | M58: =IF((L58*F58)>F58,F58,(L58*F58)) -> 176 | N58: =M58 -> 176 | O58: =ROUNDUP(N58,0) -> 176 | P58: =2*4 -> 8 | Q58: =P58*3 -> 24 | R58: =ROUNDUP(Q58,0) -> 24 | S58: ='Manpower Allocation'!$D$33 -> 3 | T58: =R58+S58 -> 27 | U58: =I58/V58 -> 3524.69 | V58: 4 | W58: =4*44 -> 176 | X58: =IF(J58>I58,V58,J58/U58) -> 4 | Y58: =L58*W58 -> 255.13499 | Z58: 2 | AA58: =Z58*X58 -> 8 | AB58: =ROUNDUP(AA58,0) -> 8 | AC58: =AB58*3 -> 24
A59: 4. Parallel Winding | B59: 4. PW | C59: 46419 | D59: ='YN01'!$J$94 -> 520.63123 | E59: ='YN01'!$E$94 -> 1446.7335 | F59: 176 | G59: ='YN01'!$H$94 -> 0.94957983 | H59: ='YN01'!$I$94 -> 0.7 | I59: =D59*E59*F59*G59*H59*0.00016 -> 14098.76 | J59: =BP!O115/DAY(EOMONTH(C59,0)) -> 21553.116 | L59: =J59/I59 -> 1.5287242 | M59: =IF((L59*F59)>F59,F59,(L59*F59)) -> 176 | N59: =M59 -> 176 | O59: =ROUNDUP(N59,0) -> 176 | P59: =2*4 -> 8 | Q59: =P59*3 -> 24 | R59: =ROUNDUP(Q59,0) -> 24 | S59: ='Manpower Allocation'!$D$33 -> 3 | T59: =R59+S59 -> 27 | U59: =I59/V59 -> 3524.69 | V59: 4 | W59: =4*44 -> 176 | X59: =IF(J59>I59,V59,J59/U59) -> 4 | Y59: =L59*W59 -> 269.05546 | Z59: 2 | AA59: =Z59*X59 -> 8 | AB59: =ROUNDUP(AA59,0) -> 8 | AC59: =AB59*3 -> 24
A60: 4. Parallel Winding | B60: 4. PW | C60: 46447 | D60: ='YN01'!$J$94 -> 520.63123 | E60: ='YN01'!$E$94 -> 1446.7335 | F60: 176 | G60: ='YN01'!$H$94 -> 0.94957983 | H60: ='YN01'!$I$94 -> 0.7 | I60: =D60*E60*F60*G60*H60*0.00016 -> 14098.76 | J60: =BP!P115/DAY(EOMONTH(C60,0)) -> 19632.218 | L60: =J60/I60 -> 1.3924783 | M60: =IF((L60*F60)>F60,F60,(L60*F60)) -> 176 | N60: =M60 -> 176 | O60: =ROUNDUP(N60,0) -> 176 | P60: =2*4 -> 8 | Q60: =P60*3 -> 24 | R60: =ROUNDUP(Q60,0) -> 24 | S60: ='Manpower Allocation'!$D$33 -> 3 | T60: =R60+S60 -> 27 | U60: =I60/V60 -> 3524.69 | V60: 4 | W60: =4*44 -> 176 | X60: =IF(J60>I60,V60,J60/U60) -> 4 | Y60: =L60*W60 -> 245.07618 | Z60: 2 | AA60: =Z60*X60 -> 8 | AB60: =ROUNDUP(AA60,0) -> 8 | AC60: =AB60*3 -> 24
P62: =AVERAGE(P49:P60) -> 8 | Q62: =AVERAGE(Q49:Q60) -> 24
A63: Section | B63: Machine | C63: Month | D63: Avg. Speed | E63: Avg. Denier | F63: Total Spindle | G63: Utilization | H63: Efficiency | I63: Capacity Per Day | J63: BP | L63: Spinder Req. | M63: Spinder Req. | N63: Winder Req. | O63: Winder Req. | P63: MP Req./Shift | Q63: MP Req./Day | R63: MP Req./Day | S63: Standard HC (Fix) | T63: Total Manpower Req. | U63: Capacity/machine | V63: Available M/C | W63: Available Spindles | X63: Req. M/C | Y63: Req. Spindles | Z63: HC Deployed/M/C | AA63: Total HC Req. /Shift | AB63: Total HC Req. /Shift | AC63: Total HC Req. /Day | AD63: Remarks | AW63: Avg MP | AY63: 45748 | AZ63: 45778 | BA63: 45809 | BB63: 45839 | BC63: 45870 | BD63: 45901 | BE63: 45931 | BF63: 45962 | BG63: 45992 | BH63: 46023 | BI63: 46054 | BJ63: 46082 | BK63: 46082
A64: 6. Cabling | B64: 6. Cabling | C64: 46113 | D64: ='YN01'!$J$162 -> 37.378368 | E64: ='YN01'!$C$163 -> 2649.3919 | F64: =(16*176)+(3*144) -> 3248 | G64: ='YN01'!$H$162 -> 0.91596639 | H64: ='YN01'!$I$162 -> 0.84100611 | I64: =D64*E64*F64*G64*H64*0.00016 -> 39644.343 | J64: =BP!E30/DAY(EOMONTH(C64,0)) -> 41292.949 | L64: =J64/I64 -> 1.0415849 | M64: =IF((L64*F64)>F64,F64,(L64*F64)) -> 3248 | N64: =M64 -> 3248 | O64: =ROUNDUP(N64,0) -> 3248 | P64: =O64*'Manpower Allocation'!$D$38 -> 19 | Q64: =P64*3 -> 57 | R64: =ROUNDUP(Q64,0) -> 57 | S64: ='Manpower Allocation'!$D$44 -> 12 | T64: =R64+S64 -> 69 | U64: =I64/V64 -> 2086.5444 | V64: 19 | W64: =(16*88*2)+(3*72*2) -> 3248 | X64: =IF(J64>I64,V64,J64/U64) -> 19 | Y64: =W64*L64 -> 3383.0677 | Z64: 1 | AA64: =Z64*X64 -> 19 | AB64: =ROUNDUP(AA64,0) -> 19 | AC64: =AB64*3 -> 57 | AD64: 1 M/C ~ 176 Spndl. = 1 Opt. ~ 176 Spindle | AU64: Operator | AV64: =R76 -> 52 | AW64: =(17/1.5)*3 -> 34 | AX64: 1.5 M/C Per Operator (264 Spindles) | AY64: =AY72*1*3 -> 42 | AZ64: =AZ72*1*3 -> 45 | BA64: =BA72*1*3 -> 45 | BB64: =BB72*1*3 -> 54 | BC64: =BC72*1*3 -> 54 | BD64: =BD72*1*3 -> 57 | BE64: =BE72*1*3 -> 48 | BF64: =BF72*1*3 -> 57 | ... BK64: =BK72*1*3 -> 33 | BO64: =P64/1.5 -> 12.666667 | BP64: =BO64*3 -> 38
A65: 6. Cabling | B65: 6. Cabling | C65: 46143 | D65: ='YN01'!$J$162 -> 37.378368 | E65: ='YN01'!$C$163 -> 2649.3919 | F65: =(16*176)+(3*144) -> 3248 | G65: ='YN01'!$H$162 -> 0.91596639 | H65: ='YN01'!$I$162 -> 0.84100611 | I65: =D65*E65*F65*G65*H65*0.00016 -> 39644.343 | J65: =BP!F30/DAY(EOMONTH(C65,0)) -> 34846.489 | L65: =J65/I65 -> 0.87897758 | M65: =IF((L65*F65)>F65,F65,(L65*F65)) -> 2854.9192 | N65: =M65 -> 2854.9192 | O65: =ROUNDUP(N65,0) -> 2855 | P65: =O65*'Manpower Allocation'!$D$38 -> 16.701047 | Q65: =P65*3 -> 50.10314 | R65: =ROUNDUP(Q65,0) -> 51 | S65: ='Manpower Allocation'!$D$44 -> 12 | T65: =R65+S65 -> 63 | U65: =I65/V65 -> 2086.5444 | V65: 19 | W65: =(16*88*2)+(3*72*2) -> 3248 | X65: =IF(J65>I65,V65,J65/U65) -> 16.700574 | Y65: =W65*L65 -> 2854.9192 | Z65: 1 | AA65: =Z65*X65 -> 16.700574 | AB65: =ROUNDUP(AA65,0) -> 17 | AC65: =AB65*3 -> 51 | AU65: DOE | AV65: 3 | AW65: 0 | AX65: Data Automation | AY65: 0 | AZ65: 0 | BA65: 0 | BB65: 0 | BC65: 0 | BD65: 0 | BE65: 0 | BF65: 0 | BG65: 0 | BH65: 0 | BI65: 0 | BJ65: 0 | BK65: 0 | BO65: =P65/1.5 -> 11.134031 | BP65: =BO65*3 -> 33.402094 | BR65: =480/(176) -> 2.7272727 | BS65: min
A66: 6. Cabling | B66: 6. Cabling | C66: 46174 | D66: ='YN01'!$J$162 -> 37.378368 | E66: ='YN01'!$C$163 -> 2649.3919 | F66: =(16*176)+(3*144) -> 3248 | G66: ='YN01'!$H$162 -> 0.91596639 | H66: ='YN01'!$I$162 -> 0.84100611 | I66: =D66*E66*F66*G66*H66*0.00016 -> 39644.343 | J66: =BP!G30/DAY(EOMONTH(C66,0)) -> 32022.756 | L66: =J66/I66 -> 0.80775096 | M66: =IF((L66*F66)>F66,F66,(L66*F66)) -> 2623.5751 | N66: =M66 -> 2623.5751 | O66: =ROUNDUP(N66,0) -> 2624 | P66: =O66*'Manpower Allocation'!$D$38 -> 15.349754 | Q66: =P66*3 -> 46.049261 | R66: =ROUNDUP(Q66,0) -> 47 | S66: ='Manpower Allocation'!$D$44 -> 12 | T66: =R66+S66 -> 59 | U66: =I66/V66 -> 2086.5444 | V66: 19 | W66: =(16*88*2)+(3*72*2) -> 3248 | X66: =IF(J66>I66,V66,J66/U66) -> 15.347268 | Y66: =W66*L66 -> 2623.5751 | Z66: 1 | AA66: =Z66*X66 -> 15.347268 | AB66: =ROUNDUP(AA66,0) -> 16 | AC66: =AB66*3 -> 48 | AD66: Has considered decimal value equal to or below .3 for ROUNDUP at MP/day | AU66: Jobber | AV66: 3 | AW66: 3 | AX66: Balance Data Entries after Data Automation, taken care by jobber | AY66: 3 | AZ66: 3 | BA66: 3 | BB66: 3 | BC66: 3 | BD66: 3 | BE66: 3 | BF66: 3 | BG66: 3 | BH66: 3 | BI66: 3 | BJ66: 3 | BK66: 3 | BO66: =P66/1.5 -> 10.233169 | BP66: =BO66*3 -> 30.699507 | BR66: Papertube Feeding
A67: 6. Cabling | B67: 6. Cabling | C67: 46204 | D67: ='YN01'!$J$162 -> 37.378368 | E67: ='YN01'!$C$163 -> 2649.3919 | F67: =(16*176)+(3*144) -> 3248 | G67: ='YN01'!$H$162 -> 0.91596639 | H67: ='YN01'!$I$162 -> 0.84100611 | I67: =D67*E67*F67*G67*H67*0.00016 -> 39644.343 | J67: =BP!H30/DAY(EOMONTH(C67,0)) -> 34633.558 | L67: =J67/I67 -> 0.87360657 | M67: =IF((L67*F67)>F67,F67,(L67*F67)) -> 2837.4741 | N67: =M67 -> 2837.4741 | O67: =ROUNDUP(N67,0) -> 2838 | P67: =O67*'Manpower Allocation'!$D$38 -> 16.601601 | Q67: =P67*3 -> 49.804803 | R67: =ROUNDUP(Q67,0) -> 50 | S67: ='Manpower Allocation'!$D$44 -> 12 | T67: =R67+S67 -> 62 | U67: =I67/V67 -> 2086.5444 | V67: 19 | W67: =(16*88*2)+(3*72*2) -> 3248 | X67: =IF(J67>I67,V67,J67/U67) -> 16.598525 | Y67: =W67*L67 -> 2837.4741 | Z67: 1 | AA67: =Z67*X67 -> 16.598525 | AB67: =ROUNDUP(AA67,0) -> 17 | AC67: =AB67*3 -> 51 | AD67: Standard formula will be followed from here onwards | AU67: Fitter | AV67: 3 | AW67: 3 | AY67: 0 | AZ67: 0 | BA67: 0 | BB67: 0 | BC67: 0 | BD67: 0 | BE67: 0 | BF67: 0 | BG67: 0 | BH67: 0 | BI67: 0 | BJ67: 0 | BK67: 0 | BO67: =P67/1.5 -> 11.067734 | BP67: =BO67*3 -> 33.203202 | BR67: Pallet Handling
A68: 6. Cabling | B68: 6. Cabling | C68: 46235 | D68: ='YN01'!$J$162 -> 37.378368 | E68: ='YN01'!$C$163 -> 2649.3919 | F68: =(16*176)+(3*144) -> 3248 | G68: ='YN01'!$H$162 -> 0.91596639 | H68: ='YN01'!$I$162 -> 0.84100611 | I68: =D68*E68*F68*G68*H68*0.00016 -> 39644.343 | J68: =BP!I30/DAY(EOMONTH(C68,0)) -> 38506.102 | L68: =J68/I68 -> 0.97128868 | M68: =IF((L68*F68)>F68,F68,(L68*F68)) -> 3154.7456 | N68: =M68 -> 3154.7456 | O68: =ROUNDUP(N68,0) -> 3155 | P68: =O68*'Manpower Allocation'!$D$38 -> 18.455973 | Q68: =P68*3 -> 55.367919 | R68: =ROUNDUP(Q68,0) -> 56 | S68: ='Manpower Allocation'!$D$44 -> 12 | T68: =R68+S68 -> 68 | U68: =I68/V68 -> 2086.5444 | V68: 19 | W68: =(16*88*2)+(3*72*2) -> 3248 | X68: =IF(J68>I68,V68,J68/U68) -> 18.454485 | Y68: =W68*L68 -> 3154.7456 | Z68: 1 | AA68: =Z68*X68 -> 18.454485 | AB68: =ROUNDUP(AA68,0) -> 19 | AC68: =AB68*3 -> 57 | AD68: Standard formula will be followed from here onwards | AU68: Material Handler | AV68: 3 | AW68: 3 | AY68: 3 | AZ68: 3 | BA68: 3 | BB68: 3 | BC68: 3 | BD68: 3 | BE68: 3 | BF68: 3 | BG68: 3 | BH68: 3 | BI68: 3 | BJ68: 3 | BK68: 3 | BO68: =P68/1.5 -> 12.303982 | BP68: =BO68*3 -> 36.911946 | BR68: Doffing and Threading
A69: 6. Cabling | B69: 6. Cabling | C69: 46266 | D69: ='YN01'!$J$162 -> 37.378368 | E69: ='YN01'!$C$163 -> 2649.3919 | F69: =(16*176)+(3*144) -> 3248 | G69: ='YN01'!$H$162 -> 0.91596639 | H69: ='YN01'!$I$162 -> 0.84100611 | I69: =D69*E69*F69*G69*H69*0.00016 -> 39644.343 | J69: =BP!J30/DAY(EOMONTH(C69,0)) -> 39007.078 | L69: =J69/I69 -> 0.98392546 | M69: =IF((L69*F69)>F69,F69,(L69*F69)) -> 3195.7899 | N69: =M69 -> 3195.7899 | O69: =ROUNDUP(N69,0) -> 3196 | P69: =O69*'Manpower Allocation'!$D$38 -> 18.695813 | Q69: =P69*3 -> 56.087438 | R69: =ROUNDUP(Q69,0) -> 57 | S69: ='Manpower Allocation'!$D$44 -> 12 | T69: =R69+S69 -> 69 | U69: =I69/V69 -> 2086.5444 | V69: 19 | W69: =(16*88*2)+(3*72*2) -> 3248 | X69: =IF(J69>I69,V69,J69/U69) -> 18.694584 | Y69: =W69*L69 -> 3195.7899 | Z69: 1 | AA69: =Z69*X69 -> 18.694584 | AB69: =ROUNDUP(AA69,0) -> 19 | AC69: =AB69*3 -> 57 | AT69: 2 M/C for Sample | AU69: Helper | AV69: 3 | AW69: 3 | AY69: 3 | AZ69: 3 | BA69: 3 | BB69: 3 | BC69: 3 | BD69: 3 | BE69: 3 | BF69: 3 | BG69: 3 | BH69: 3 | BI69: 3 | BJ69: 3 | BK69: 3 | BO69: =P69/1.5 -> 12.463875 | BP69: =BO69*3 -> 37.391626 | BR69: Bottom Running
A70: 6. Cabling | B70: 6. Cabling | C70: 46296 | D70: ='YN01'!$J$162 -> 37.378368 | E70: ='YN01'!$C$163 -> 2649.3919 | F70: =(16*176)+(3*144) -> 3248 | G70: ='YN01'!$H$162 -> 0.91596639 | H70: ='YN01'!$I$162 -> 0.84100611 | I70: =D70*E70*F70*G70*H70*0.00016 -> 39644.343 | J70: =BP!K30/DAY(EOMONTH(C70,0)) -> 34028.048 | L70: =J70/I70 -> 0.85833299 | M70: =IF((L70*F70)>F70,F70,(L70*F70)) -> 2787.8656 | N70: =M70 -> 2787.8656 | O70: =ROUNDUP(N70,0) -> 2788 | P70: =O70*'Manpower Allocation'!$D$38 -> 16.309113 | Q70: =P70*3 -> 48.92734 | R70: =ROUNDUP(Q70,0) -> 49 | S70: ='Manpower Allocation'!$D$44 -> 12 | T70: =R70+S70 -> 61 | U70: =I70/V70 -> 2086.5444 | V70: 19 | W70: =(16*88*2)+(3*72*2) -> 3248 | X70: =IF(J70>I70,V70,J70/U70) -> 16.308327 | Y70: =W70*L70 -> 2787.8656 | Z70: 1 | AA70: =Z70*X70 -> 16.308327 | AB70: =ROUNDUP(AA70,0) -> 17 | AC70: =AB70*3 -> 51 | AD70: Has considered decimal value equal to or below .3 for ROUNDUP at MP/day | AU70: TOTAL | AV70: =SUM(AV64:AV69) -> 67 | AW70: =SUM(AW64:AW69) -> 46 | AY70: =SUM(AY64:AY69) -> 51 | AZ70: =SUM(AZ64:AZ69) -> 54 | BA70: =SUM(BA64:BA69) -> 54 | BB70: =SUM(BB64:BB69) -> 63 | BC70: =SUM(BC64:BC69) -> 63 | BD70: =SUM(BD64:BD69) -> 66 | BE70: =SUM(BE64:BE69) -> 57 | BF70: =SUM(BF64:BF69) -> 66 | ... BK70: =SUM(BK64:BK69) -> 42 | BO70: =P70/1.5 -> 10.872742 | BP70: =BO70*3 -> 32.618227 | BR70: Breakage Handling
A71: 6. Cabling | B71: 6. Cabling | C71: 46327 | D71: ='YN01'!$J$162 -> 37.378368 | E71: ='YN01'!$C$163 -> 2649.3919 | F71: =(16*176)+(3*144) -> 3248 | G71: ='YN01'!$H$162 -> 0.91596639 | H71: ='YN01'!$I$162 -> 0.84100611 | I71: =D71*E71*F71*G71*H71*0.00016 -> 39644.343 | J71: =BP!L30/DAY(EOMONTH(C71,0)) -> 31353.977 | L71: =J71/I71 -> 0.7908815 | M71: =IF((L71*F71)>F71,F71,(L71*F71)) -> 2568.7831 | N71: =M71 -> 2568.7831 | O71: =ROUNDUP(N71,0) -> 2569 | P71: =O71*'Manpower Allocation'!$D$38 -> 15.028017 | Q71: =P71*3 -> 45.084052 | R71: =ROUNDUP(Q71,0) -> 46 | S71: ='Manpower Allocation'!$D$44 -> 12 | T71: =R71+S71 -> 58 | U71: =I71/V71 -> 2086.5444 | V71: 19 | W71: =(16*88*2)+(3*72*2) -> 3248 | X71: =IF(J71>I71,V71,J71/U71) -> 15.026748 | Y71: =W71*L71 -> 2568.7831 | Z71: 1 | AA71: =Z71*X71 -> 15.026748 | AB71: =ROUNDUP(AA71,0) -> 16 | AC71: =ROUNDUP(AA71*3,0) -> 46 | BO71: =P71/1.5 -> 10.018678 | BP71: =BO71*3 -> 30.056034 | BR71: Cleaning
A72: 6. Cabling | B72: 6. Cabling | C72: 46357 | D72: ='YN01'!$J$162 -> 37.378368 | E72: ='YN01'!$C$163 -> 2649.3919 | F72: =(16*176)+(3*144) -> 3248 | G72: ='YN01'!$H$162 -> 0.91596639 | H72: ='YN01'!$I$162 -> 0.84100611 | I72: =D72*E72*F72*G72*H72*0.00016 -> 39644.343 | J72: =BP!M30/DAY(EOMONTH(C72,0)) -> 37743.216 | L72: =J72/I72 -> 0.95204543 | M72: =IF((L72*F72)>F72,F72,(L72*F72)) -> 3092.2436 | N72: =M72 -> 3092.2436 | O72: =ROUNDUP(N72,0) -> 3093 | P72: =O72*'Manpower Allocation'!$D$38 -> 18.093288 | Q72: =P72*3 -> 54.279865 | R72: =ROUNDUP(Q72,0) -> 55 | S72: ='Manpower Allocation'!$D$44 -> 12 | T72: =R72+S72 -> 67 | U72: =I72/V72 -> 2086.5444 | V72: 19 | W72: =(16*88*2)+(3*72*2) -> 3248 | X72: =IF(J72>I72,V72,J72/U72) -> 18.088863 | Y72: =W72*L72 -> 3092.2436 | Z72: 1 | AA72: =Z72*X72 -> 18.088863 | AB72: =ROUNDUP(AA72,0) -> 19 | AC72: =ROUNDUP(AA72*3,0) -> 55 | AY72: 14 | AZ72: 15 | BA72: 15 | BB72: 18 | BC72: 18 | BD72: 19 | BE72: 16 | BF72: 19 | BG72: 19 | BH72: 19 | BI72: 18 | BJ72: 19 | BK72: 11 | BO72: =P72/1.5 -> 12.062192 | BP72: =BO72*3 -> 36.186576
A73: 6. Cabling | B73: 6. Cabling | C73: 46388 | D73: ='YN01'!$J$162 -> 37.378368 | E73: ='YN01'!$C$163 -> 2649.3919 | F73: =(16*176)+(3*144) -> 3248 | G73: ='YN01'!$H$162 -> 0.91596639 | H73: ='YN01'!$I$162 -> 0.84100611 | I73: =D73*E73*F73*G73*H73*0.00016 -> 39644.343 | J73: =BP!N30/DAY(EOMONTH(C73,0)) -> 37545.075 | L73: =J73/I73 -> 0.94704749 | M73: =IF((L73*F73)>F73,F73,(L73*F73)) -> 3076.0102 | N73: =M73 -> 3076.0102 | O73: =ROUNDUP(N73,0) -> 3077 | P73: =O73*'Manpower Allocation'!$D$38 -> 17.999692 | Q73: =P73*3 -> 53.999076 | R73: =ROUNDUP(Q73,0) -> 54 | S73: ='Manpower Allocation'!$D$44 -> 12 | T73: =R73+S73 -> 66 | U73: =I73/V73 -> 2086.5444 | V73: 19 | W73: =(16*88*2)+(3*72*2) -> 3248 | X73: =IF(J73>I73,V73,J73/U73) -> 17.993902 | Y73: =W73*L73 -> 3076.0102 | Z73: 1 | AA73: =Z73*X73 -> 17.993902 | AB73: =ROUNDUP(AA73,0) -> 18 | AC73: =AB73*3 -> 54 | BO73: =P73/1.5 -> 11.999795 | BP73: =BO73*3 -> 35.999384 | BR73: =34/3 -> 11.333333
A74: 6. Cabling | B74: 6. Cabling | C74: 46419 | D74: ='YN01'!$J$162 -> 37.378368 | E74: ='YN01'!$C$163 -> 2649.3919 | F74: =(16*176)+(3*144) -> 3248 | G74: ='YN01'!$H$162 -> 0.91596639 | H74: ='YN01'!$I$162 -> 0.84100611 | I74: =D74*E74*F74*G74*H74*0.00016 -> 39644.343 | J74: =BP!O30/DAY(EOMONTH(C74,0)) -> 38907.62 | L74: =J74/I74 -> 0.9814167 | M74: =IF((L74*F74)>F74,F74,(L74*F74)) -> 3187.6414 | N74: =M74 -> 3187.6414 | O74: =ROUNDUP(N74,0) -> 3188 | P74: =O74*'Manpower Allocation'!$D$38 -> 18.649015 | Q74: =P74*3 -> 55.947044 | R74: =ROUNDUP(Q74,0) -> 56 | S74: ='Manpower Allocation'!$D$44 -> 12 | T74: =R74+S74 -> 68 | U74: =I74/V74 -> 2086.5444 | V74: 19 | W74: =(16*88*2)+(3*72*2) -> 3248 | X74: =IF(J74>I74,V74,J74/U74) -> 18.646917 | Y74: =W74*L74 -> 3187.6414 | Z74: 1 | AA74: =Z74*X74 -> 18.646917 | AB74: =ROUNDUP(AA74,0) -> 19 | AC74: =AB74*3 -> 57 | AD74: Standard formula will be followed from here onwards | AV74: =1*17*3 -> 51 | BO74: =P74/1.5 -> 12.432677 | BP74: =BO74*3 -> 37.29803
A75: 6. Cabling | B75: 6. Cabling | C75: 46447 | D75: ='YN01'!$J$162 -> 37.378368 | E75: ='YN01'!$C$163 -> 2649.3919 | F75: =(16*176)+(3*144) -> 3248 | G75: ='YN01'!$H$162 -> 0.91596639 | H75: ='YN01'!$I$162 -> 0.84100611 | I75: =D75*E75*F75*G75*H75*0.00016 -> 39644.343 | J75: =BP!P30/DAY(EOMONTH(C75,0)) -> 33353.914 | L75: =J75/I75 -> 0.84132845 | M75: =IF((L75*F75)>F75,F75,(L75*F75)) -> 2732.6348 | N75: =M75 -> 2732.6348 | O75: =ROUNDUP(N75,0) -> 2733 | P75: =O75*'Manpower Allocation'!$D$38 -> 15.987377 | Q75: =P75*3 -> 47.962131 | R75: =ROUNDUP(Q75,0) -> 48 | S75: ='Manpower Allocation'!$D$44 -> 12 | T75: =R75+S75 -> 60 | U75: =I75/V75 -> 2086.5444 | V75: 19 | W75: =(16*88*2)+(3*72*2) -> 3248 | X75: =IF(J75>I75,V75,J75/U75) -> 15.985241 | Y75: =W75*L75 -> 2732.6348 | Z75: 1 | AA75: =Z75*X75 -> 15.985241 | AB75: =ROUNDUP(AA75,0) -> 16 | AC75: =AB75*3 -> 48 | BO75: =P75/1.5 -> 10.658251 | BP75: =BO75*3 -> 31.974754
Q76: =AVERAGE(Q64:Q75) -> 51.717672 | R76: =ROUNDUP(Q76,0) -> 52 | BP76: =AVERAGE(BP64:BP75) -> 34.478448
A78: Section | B78: Machine | C78: Month | D78: Avg. Speed | E78: Avg. Denier | F78: Total Spindle | G78: Utilization | H78: Efficiency | I78: Capacity Per Day | J78: BP | L78: Spinder Req. | M78: Spinder Req. | N78: Winder Req. | O78: Winder Req. | P78: MP Req./Shift | Q78: MP Req./Day | R78: MP Req./Day | S78: Standard HC (Fix) | T78: Total Manpower Req. | U78: Capacity/machine | V78: Available M/C | W78: Available Spindles | X78: Req. M/C | Y78: Req. Spindles | Z78: HC Deployed/M/C | AA78: Total HC Req. /Shift | AB78: Total HC Req. /Shift | AC78: Total HC Req. /Day | AD78: Remarks | AN78: Associate | AO78: NAPs | AP78: CLM - MD | AW78: Avg MP | AY78: 45748 | AZ78: 45778 | BA78: 45809 | BB78: 45839 | BC78: 45870 | BD78: 45901 | BE78: 45931 | BF78: 45962 | BG78: 45992 | BH78: 46023 | BI78: 46054 | BJ78: 46082 | BK78: 46082
A79: 7. Heat Set | B79: Superba Heat Set | C79: 46113 | D79: ='YN01'!$K$333 -> 350 | E79: ='YN01'!$F$333 -> 2659.1722 | F79: ='YN01'!$N$333 -> 319.87518 | G79: ='YN01'!$I$333 -> 0.90136986 | H79: ='YN01'!$J$333 -> 0.85035903 | I79: =D79*E79*F79*G79*H79*0.00016 -> 36510.72 | J79: =(BP!E64+BP!E65)/DAY(EOMONTH(C79,0)) -> 36944.506 | L79: =J79/I79 -> 1.0118811 | M79: =IF((L79*F79)>F79,F79,(L79*F79)) -> 319.87518 | N79: =M79 -> 319.87518 | O79: =ROUNDUP(N79,0) -> 320 | P79: =O79*'Manpower Allocation'!$D$46 -> 17.297297 | Q79: =P79*3 -> 51.891892 | R79: =ROUNDUP(Q79,0) -> 52 | S79: ='Manpower Allocation'!$D$52 -> 12 | T79: =R79+S79 -> 64 | U79: =I79/V79 -> 7302.1439 | V79: 5 | W79: =72*5 -> 360 | X79: =IF(J79>I79,V79,J79/U79) -> 5 | Y79: =W79*L79 -> 364.27718 | Z79: 4 | AA79: =Z79*X79 -> 20 | AB79: =ROUNDUP(AA79,0) -> 20 | AC79: =ROUNDUP(AA79*3,0) -> 60 | AD79: 1 M/C ~ 72 Spindles = 1 Opt ~ 18 Spindle | AJ79: =J79/I79*6 -> 6.0712863 | AK79: =5*4*3+12 -> 72 | AN79: 44 | AO79: 24 | AP79: =T79-AN79-AO79 -> -4 | AQ79: =AN79/T79 -> 0.6875 | AR79: =AO79/T79 -> 0.375 | AS79: =AP79/T79 -> -0.0625 | AT79: =6*4*3 -> 72 | AU79: Operator | AV79: =R105 -> 47.916667 | AW79: 68 | AY79: =(3*6*3)+(5*3) -> 69 | AZ79: =(3*6*3)+(5*3) -> 69 | BA79: =(3*6*3)+(5*3) -> 69 | BB79: =(3*6*3)+(5*3) -> 69 | BC79: =(3*6*3)+(5*3) -> 69 | BD79: =(3*6*3)+(5*3) -> 69 | BE79: =(3*6*3)+(5*3) -> 69 | BF79: =(3*6*3)+(5*3) -> 69 | ... BJ79: =(3*6*3)+(5*3) -> 69 | BK79: =(3*5*3)+(4*3) -> 57 | BO79: =I18+J4 -> 38457.071 | BP79: =SUM(T18,T4,T33,T49,T64,T79,139,30,14) -> 493 | BQ79: =BO79/BP79 -> 78.006229
A80: 7. Heat Set | B80: Superba Heat Set | C80: 46143 | D80: ='YN01'!$K$333 -> 350 | E80: ='YN01'!$F$333 -> 2659.1722 | F80: ='YN01'!$N$333 -> 319.87518 | G80: ='YN01'!$I$333 -> 0.90136986 | H80: ='YN01'!$J$333 -> 0.85035903 | I80: =D80*E80*F80*G80*H80*0.00016 -> 36510.72 | J80: =(BP!F64+BP!F65)/DAY(EOMONTH(C80,0)) -> 33161.583 | L80: =J80/I80 -> 0.90826979 | M80: =IF((L80*F80)>F80,F80,(L80*F80)) -> 290.53296 | N80: =M80 -> 290.53296 | O80: =ROUNDUP(N80,0) -> 291 | P80: =O80*'Manpower Allocation'!$D$46 -> 15.72973 | Q80: =P80*3 -> 47.189189 | R80: =ROUNDUP(Q80,0) -> 48 | S80: ='Manpower Allocation'!$D$52 -> 12 | T80: =R80+S80 -> 60 | U80: =I80/V80 -> 7302.1439 | V80: 5 | W80: =72*5 -> 360 | X80: =IF(J80>I80,V80,J80/U80) -> 4.5413489 | Y80: =W80*L80 -> 326.97712 | Z80: 4 | AA80: =Z80*X80 -> 18.165396 | AB80: =ROUNDUP(AA80,0) -> 19 | AC80: =ROUNDUP(AA80*3,0) -> 55 | AJ80: =J80/I80*6 -> 5.4496187 | AK80: =5*4*3+12 -> 72 | AN80: 44 | AO80: 24 | AP80: =T80-AN80-AO80 -> -8 | AQ80: =AN80/T80 -> 0.73333333 | AR80: =AO80/T80 -> 0.4 | AS80: =AP80/T80 -> -0.13333333 | AU80: DOE | AV80: 3 | AW80: 0 | AX80: Data Automation | AY80: 0 | AZ80: 0 | BA80: 0 | BB80: 0 | BC80: 0 | BD80: 0 | BE80: 0 | BF80: 0 | BG80: 0 | BH80: 0 | BI80: 0 | BJ80: 0 | BK80: 0 | BO80: =I19+J5 -> 39465.07 | BP80: =SUM(T19,T5,T34,T50,T65,T80,139,30,14) -> 485 | BQ80: =BO80/BP80 -> 81.371279
A81: 7. Heat Set | B81: Superba Heat Set | C81: 46174 | D81: ='YN01'!$K$333 -> 350 | E81: ='YN01'!$F$333 -> 2659.1722 | F81: ='YN01'!$N$333 -> 319.87518 | G81: ='YN01'!$I$333 -> 0.90136986 | H81: ='YN01'!$J$333 -> 0.85035903 | I81: =D81*E81*F81*G81*H81*0.00016 -> 36510.72 | J81: =(BP!G64+BP!G65)/DAY(EOMONTH(C81,0)) -> 31323.721 | L81: =J81/I81 -> 0.85793219 | M81: =IF((L81*F81)>F81,F81,(L81*F81)) -> 274.43121 | N81: =M81 -> 274.43121 | O81: =ROUNDUP(N81,0) -> 275 | P81: =O81*'Manpower Allocation'!$D$46 -> 14.864865 | Q81: =P81*3 -> 44.594595 | R81: =ROUNDUP(Q81,0) -> 45 | S81: ='Manpower Allocation'!$D$52 -> 12 | T81: =R81+S81 -> 57 | U81: =I81/V81 -> 7302.1439 | V81: 5 | W81: =72*5 -> 360 | X81: =IF(J81>I81,V81,J81/U81) -> 4.2896609 | Y81: =W81*L81 -> 308.85559 | Z81: 4 | AA81: =Z81*X81 -> 17.158644 | AB81: =ROUNDUP(AA81,0) -> 18 | AC81: =ROUNDUP(AA81*3,0) -> 52 | AJ81: =J81/I81*6 -> 5.1475931 | AK81: =5*4*3+12 -> 72 | AN81: 44 | AO81: 24 | AP81: =T81-AN81-AO81 -> -11 | AQ81: =AN81/T81 -> 0.77192982 | AR81: =AO81/T81 -> 0.42105263 | AS81: =AP81/T81 -> -0.19298246 | AU81: Jobber | AV81: 3 | AW81: 3 | AY81: 3 | AZ81: 3 | BA81: 3 | BB81: 3 | BC81: 3 | BD81: 3 | BE81: 3 | BF81: 3 | BG81: 3 | BH81: 3 | BI81: 3 | BJ81: 3 | BK81: 3 | BO81: =I20+J6 -> 37879.825 | BP81: =SUM(T20,T6,T35,T51,T66,T81,139,30,14) -> 476 | BQ81: =BO81/BP81 -> 79.579464
A82: 7. Heat Set | B82: Superba Heat Set | C82: 46204 | D82: ='YN01'!$K$333 -> 350 | E82: ='YN01'!$F$333 -> 2659.1722 | F82: ='YN01'!$N$333 -> 319.87518 | G82: ='YN01'!$I$333 -> 0.90136986 | H82: ='YN01'!$J$333 -> 0.85035903 | I82: =D82*E82*F82*G82*H82*0.00016 -> 36510.72 | J82: =(BP!H64+BP!H65)/DAY(EOMONTH(C82,0)) -> 32311.931 | L82: =J82/I82 -> 0.88499848 | M82: =IF((L82*F82)>F82,F82,(L82*F82)) -> 283.08904 | N82: =M82 -> 283.08904 | O82: =ROUNDUP(N82,0) -> 284 | P82: =O82*'Manpower Allocation'!$D$46 -> 15.351351 | Q82: =P82*3 -> 46.054054 | R82: =ROUNDUP(Q82,0) -> 47 | S82: ='Manpower Allocation'!$D$52 -> 12 | T82: =R82+S82 -> 59 | U82: =I82/V82 -> 7302.1439 | V82: 5 | W82: =72*5 -> 360 | X82: =IF(J82>I82,V82,J82/U82) -> 4.4249924 | Y82: =W82*L82 -> 318.59945 | Z82: 4 | AA82: =Z82*X82 -> 17.69997 | AB82: =ROUNDUP(AA82,0) -> 18 | AC82: =AB82*3 -> 54 | AJ82: =J82/I82*6 -> 5.3099909 | AK82: =5.66*4*3+12 -> 79.92 | AN82: 44 | AO82: 24 | AP82: =T82-AN82-AO82 -> -9 | AQ82: =AN82/T82 -> 0.74576271 | AR82: =AO82/T82 -> 0.40677966 | AS82: =AP82/T82 -> -0.15254237 | AU82: Material Handler | AV82: 3 | AW82: 3 | AY82: 3 | AZ82: 3 | BA82: 3 | BB82: 3 | BC82: 3 | BD82: 3 | BE82: 3 | BF82: 3 | BG82: 3 | BH82: 3 | BI82: 3 | BJ82: 3 | BK82: 3 | BO82: =I21+J7 -> 38753.528 | BP82: =SUM(T21,T7,T36,T52,T67,T82,139,30,14) -> 481 | BQ82: =BO82/BP82 -> 80.568665
A83: 7. Heat Set | B83: Superba Heat Set | C83: 46235 | D83: ='YN01'!$K$333 -> 350 | E83: ='YN01'!$F$333 -> 2659.1722 | F83: ='YN01'!$N$333 -> 319.87518 | G83: ='YN01'!$I$333 -> 0.90136986 | H83: ='YN01'!$J$333 -> 0.85035903 | I83: =D83*E83*F83*G83*H83*0.00016 -> 36510.72 | J83: =(BP!I64+BP!I65)/DAY(EOMONTH(C83,0)) -> 36469.04 | L83: =J83/I83 -> 0.99885844 | M83: =IF((L83*F83)>F83,F83,(L83*F83)) -> 319.51002 | N83: =M83 -> 319.51002 | O83: =ROUNDUP(N83,0) -> 320 | P83: =O83*'Manpower Allocation'!$D$46 -> 17.297297 | Q83: =P83*3 -> 51.891892 | R83: =ROUNDUP(Q83,0) -> 52 | S83: ='Manpower Allocation'!$D$52 -> 12 | T83: =R83+S83 -> 64 | U83: =I83/V83 -> 7302.1439 | V83: 5 | W83: =72*5 -> 360 | X83: =IF(J83>I83,V83,J83/U83) -> 4.9942922 | Y83: =W83*L83 -> 359.58904 | Z83: 4 | AA83: =Z83*X83 -> 19.977169 | AB83: =ROUNDUP(AA83,0) -> 20 | AC83: =AB83*3 -> 60 | AJ83: =J83/I83*6 -> 5.9931506 | AK83: =4.66*4*3+12 -> 67.92 | AN83: 44 | AO83: 24 | AP83: =T83-AN83-AO83 -> -4 | AQ83: =AN83/T83 -> 0.6875 | AR83: =AO83/T83 -> 0.375 | AS83: =AP83/T83 -> -0.0625 | AU83: Paper Tube Sagrgation | AV83: 6 | AW83: 3 | AY83: 3 | AZ83: 3 | BA83: 3 | BB83: 3 | BC83: 3 | BD83: 3 | BE83: 3 | BF83: 3 | BG83: 3 | BH83: 3 | BI83: 3 | BJ83: 3 | BK83: 3 | BO83: =I22+J8 -> 40213.136 | BP83: =SUM(T22,T8,T37,T53,T68,T83,139,30,14) -> 494 | BQ83: =BO83/BP83 -> 81.40311
A84: 7. Heat Set | B84: Superba Heat Set | C84: 46266 | D84: ='YN01'!$K$333 -> 350 | E84: ='YN01'!$F$333 -> 2659.1722 | F84: ='YN01'!$N$333 -> 319.87518 | G84: ='YN01'!$I$333 -> 0.90136986 | H84: ='YN01'!$J$333 -> 0.85035903 | I84: =D84*E84*F84*G84*H84*0.00016 -> 36510.72 | J84: =(BP!J64+BP!J65)/DAY(EOMONTH(C84,0)) -> 35212.37 | L84: =J84/I84 -> 0.96443923 | M84: =IF((L84*F84)>F84,F84,(L84*F84)) -> 308.50017 | N84: =M84 -> 308.50017 | O84: =ROUNDUP(N84,0) -> 309 | P84: =O84*'Manpower Allocation'!$D$46 -> 16.702703 | Q84: =P84*3 -> 50.108108 | R84: =ROUNDUP(Q84,0) -> 51 | S84: ='Manpower Allocation'!$D$52 -> 12 | T84: =R84+S84 -> 63 | U84: =I84/V84 -> 7302.1439 | V84: 5 | W84: =72*5 -> 360 | X84: =IF(J84>I84,V84,J84/U84) -> 4.8221961 | Y84: =W84*L84 -> 347.19812 | Z84: 4 | AA84: =Z84*X84 -> 19.288785 | AB84: =ROUNDUP(AA84,0) -> 20 | AC84: =ROUNDUP(AA84*3,0) -> 58 | AJ84: =J84/I84*6 -> 5.7866354 | AK84: =6*4*3+12 -> 84 | AN84: 44 | AO84: 24 | AP84: =T84-AN84-AO84 -> -5 | AQ84: =AN84/T84 -> 0.6984127 | AR84: =AO84/T84 -> 0.38095238 | AS84: =AP84/T84 -> -0.079365079 | AU84: Fitter | AV84: 2 | AW84: 2 | AY84: 3 | AZ84: 3 | BA84: 3 | BB84: 3 | BC84: 3 | BD84: 3 | BE84: 3 | BF84: 3 | BG84: 3 | BH84: 3 | BI84: 3 | BJ84: 3 | BK84: 3 | BO84: =I23+J9 -> 45245.852 | BP84: =SUM(T23,T9,T38,T54,T69,T84,139,30,14) -> 498 | BQ84: =BO84/BP84 -> 90.855125
A85: 7. Heat Set | B85: Superba Heat Set | C85: 46296 | D85: ='YN01'!$K$333 -> 350 | E85: ='YN01'!$F$333 -> 2659.1722 | F85: ='YN01'!$N$333 -> 319.87518 | G85: ='YN01'!$I$333 -> 0.90136986 | H85: ='YN01'!$J$333 -> 0.85035903 | I85: =D85*E85*F85*G85*H85*0.00016 -> 36510.72 | J85: =(BP!K64+BP!K65)/DAY(EOMONTH(C85,0)) -> 30108.678 | L85: =J85/I85 -> 0.82465311 | M85: =IF((L85*F85)>F85,F85,(L85*F85)) -> 263.78606 | N85: =M85 -> 263.78606 | O85: =ROUNDUP(N85,0) -> 264 | P85: =O85*'Manpower Allocation'!$D$46 -> 14.27027 | Q85: =P85*3 -> 42.810811 | R85: =ROUNDUP(Q85,0) -> 43 | S85: ='Manpower Allocation'!$D$52 -> 12 | T85: =R85+S85 -> 55 | U85: =I85/V85 -> 7302.1439 | V85: 5 | W85: =72*5 -> 360 | X85: =IF(J85>I85,V85,J85/U85) -> 4.1232655 | Y85: =W85*L85 -> 296.87512 | Z85: 4 | AA85: =Z85*X85 -> 16.493062 | AB85: =ROUNDUP(AA85,0) -> 17 | AC85: =AB85*3 -> 51 | AJ85: =J85/I85*6 -> 4.9479187 | AK85: =5*4*3+12 -> 72 | AN85: 44 | AO85: 21 | AP85: =T85-AN85-AO85 -> -10 | AQ85: =AN85/T85 -> 0.8 | AR85: =AO85/T85 -> 0.38181818 | AS85: =AP85/T85 -> -0.18181818 | AU85: TOTAL | AV85: =SUM(AV79:AV84) -> 64.916667 | AW85: =SUM(AW79:AW84) -> 79 | AY85: =SUM(AY79:AY84) -> 81 | AZ85: =SUM(AZ79:AZ84) -> 81 | BA85: =SUM(BA79:BA84) -> 81 | BB85: =SUM(BB79:BB84) -> 81 | BC85: =SUM(BC79:BC84) -> 81 | BD85: =SUM(BD79:BD84) -> 81 | BE85: =SUM(BE79:BE84) -> 81 | BF85: =SUM(BF79:BF84) -> 81 | ... BK85: =SUM(BK79:BK84) -> 69 | BO85: =I24+J10 -> 41442.993 | BP85: =SUM(T24,T10,T39,T55,T70,T85,139,30,14) -> 479 | BQ85: =BO85/BP85 -> 86.519819
A86: 7. Heat Set | B86: Superba Heat Set | C86: 46327 | D86: ='YN01'!$K$333 -> 350 | E86: ='YN01'!$F$333 -> 2659.1722 | F86: ='YN01'!$N$333 -> 319.87518 | G86: ='YN01'!$I$333 -> 0.90136986 | H86: ='YN01'!$J$333 -> 0.85035903 | I86: =D86*E86*F86*G86*H86*0.00016 -> 36510.72 | J86: =(BP!L64+BP!L65)/DAY(EOMONTH(C86,0)) -> 30671.386 | L86: =J86/I86 -> 0.84006523 | M86: =IF((L86*F86)>F86,F86,(L86*F86)) -> 268.71601 | N86: =M86 -> 268.71601 | O86: =ROUNDUP(N86,0) -> 269 | P86: =O86*'Manpower Allocation'!$D$46 -> 14.540541 | Q86: =P86*3 -> 43.621622 | R86: =ROUNDUP(Q86,0) -> 44 | S86: ='Manpower Allocation'!$D$52 -> 12 | T86: =R86+S86 -> 56 | U86: =I86/V86 -> 7302.1439 | V86: 5 | W86: =72*5 -> 360 | X86: =IF(J86>I86,V86,J86/U86) -> 4.2003261 | Y86: =W86*L86 -> 302.42348 | Z86: 4 | AA86: =Z86*X86 -> 16.801305 | AB86: =ROUNDUP(AA86,0) -> 17 | AC86: =AB86*3 -> 51 | AJ86: =J86/I86*6 -> 5.0403914 | AK86: =5.33*4*3+12 -> 75.96 | AN86: 44 | AO86: 24 | AP86: =T86-AN86-AO86 -> -12 | AQ86: =AN86/T86 -> 0.78571429 | AR86: =AO86/T86 -> 0.42857143 | AS86: =AP86/T86 -> -0.21428571 | BO86: =I25+J11 -> 44359.706 | BP86: =SUM(T25,T11,T40,T56,T71,T86,139,30,14) -> 480 | BQ86: =BO86/BP86 -> 92.416055
A87: 7. Heat Set | B87: Superba Heat Set | C87: 46357 | D87: ='YN01'!$K$333 -> 350 | E87: ='YN01'!$F$333 -> 2659.1722 | F87: ='YN01'!$N$333 -> 319.87518 | G87: ='YN01'!$I$333 -> 0.90136986 | H87: ='YN01'!$J$333 -> 0.85035903 | I87: =D87*E87*F87*G87*H87*0.00016 -> 36510.72 | J87: =(BP!M64+BP!M65)/DAY(EOMONTH(C87,0)) -> 39099.956 | L87: =J87/I87 -> 1.0709172 | M87: =IF((L87*F87)>F87,F87,(L87*F87)) -> 319.87518 | N87: =M87 -> 319.87518 | O87: =ROUNDUP(N87,0) -> 320 | P87: =O87*'Manpower Allocation'!$D$46 -> 17.297297 | Q87: =P87*3 -> 51.891892 | R87: =ROUNDUP(Q87,0) -> 52 | S87: ='Manpower Allocation'!$D$52 -> 12 | T87: =R87+S87 -> 64 | U87: =I87/V87 -> 7302.1439 | V87: 5 | W87: =72*5 -> 360 | X87: =IF(J87>I87,V87,J87/U87) -> 5 | Y87: =W87*L87 -> 385.53018 | Z87: 4 | AA87: =Z87*X87 -> 20 | AB87: =ROUNDUP(AA87,0) -> 20 | AC87: =ROUNDUP(AA87*3,0) -> 60 | AJ87: =J87/I87*6 -> 6.4255029 | AK87: =6*4*3+12 -> 84 | AN87: 44 | AO87: 24 | AP87: =T87-AN87-AO87 -> -4 | AQ87: =AN87/T87 -> 0.6875 | AR87: =AO87/T87 -> 0.375 | AS87: =AP87/T87 -> -0.0625 | BO87: =I26+J12 -> 53966.897 | BP87: =SUM(T26,T12,T41,T57,T72,T87,139,30,14) -> 506 | BQ87: =BO87/BP87 -> 106.65395
A88: 7. Heat Set | B88: Superba Heat Set | C88: 46388 | D88: ='YN01'!$K$333 -> 350 | E88: ='YN01'!$F$333 -> 2659.1722 | F88: ='YN01'!$N$333 -> 319.87518 | G88: ='YN01'!$I$333 -> 0.90136986 | H88: ='YN01'!$J$333 -> 0.85035903 | I88: =D88*E88*F88*G88*H88*0.00016 -> 36510.72 | J88: =(BP!N64+BP!N65)/DAY(EOMONTH(C88,0)) -> 32022.662 | L88: =J88/I88 -> 0.87707563 | M88: =IF((L88*F88)>F88,F88,(L88*F88)) -> 280.55472 | N88: =M88 -> 280.55472 | O88: =ROUNDUP(N88,0) -> 281 | P88: =O88*'Manpower Allocation'!$D$46 -> 15.189189 | Q88: =P88*3 -> 45.567568 | R88: =ROUNDUP(Q88,0) -> 46 | S88: ='Manpower Allocation'!$D$52 -> 12 | T88: =R88+S88 -> 58 | U88: =I88/V88 -> 7302.1439 | V88: 5 | W88: =72*5 -> 360 | X88: =IF(J88>I88,V88,J88/U88) -> 4.3853782 | Y88: =W88*L88 -> 315.74723 | Z88: 4 | AA88: =Z88*X88 -> 17.541513 | AB88: =ROUNDUP(AA88,0) -> 18 | AC88: =AB88*3 -> 54 | AJ88: =J88/I88*6 -> 5.2624538 | AK88: =5*4*3+12 -> 72 | AN88: 44 | AO88: 24 | AP88: =T88-AN88-AO88 -> -10 | AQ88: =AN88/T88 -> 0.75862069 | AR88: =AO88/T88 -> 0.4137931 | AS88: =AP88/T88 -> -0.17241379 | BO88: =J27+J13 -> 50795.208 | BP88: =SUM(T27,T13,T42,T58,T73,T88,139,30,14) -> 494 | BQ88: =BO88/BP88 -> 102.82431
A89: 7. Heat Set | B89: Superba Heat Set | C89: 46419 | D89: ='YN01'!$K$333 -> 350 | E89: ='YN01'!$F$333 -> 2659.1722 | F89: ='YN01'!$N$333 -> 319.87518 | G89: ='YN01'!$I$333 -> 0.90136986 | H89: ='YN01'!$J$333 -> 0.85035903 | I89: =D89*E89*F89*G89*H89*0.00016 -> 36510.72 | J89: =(BP!O64+BP!O65)/DAY(EOMONTH(C89,0)) -> 35550.069 | L89: =J89/I89 -> 0.97368853 | M89: =IF((L89*F89)>F89,F89,(L89*F89)) -> 311.45879 | N89: =M89 -> 311.45879 | O89: =ROUNDUP(N89,0) -> 312 | P89: =O89*'Manpower Allocation'!$D$46 -> 16.864865 | Q89: =P89*3 -> 50.594595 | R89: =ROUNDUP(Q89,0) -> 51 | S89: ='Manpower Allocation'!$D$52 -> 12 | T89: =R89+S89 -> 63 | U89: =I89/V89 -> 7302.1439 | V89: 5 | W89: =72*5 -> 360 | X89: =IF(J89>I89,V89,J89/U89) -> 4.8684426 | Y89: =W89*L89 -> 350.52787 | Z89: 4 | AA89: =Z89*X89 -> 19.473771 | AB89: =ROUNDUP(AA89,0) -> 20 | AC89: =AB89*3 -> 60 | AJ89: =J89/I89*6 -> 5.8421312 | AK89: =5.5*4*3+12 -> 78 | AN89: 44 | AO89: 24 | AP89: =T89-AN89-AO89 -> -5 | AQ89: =AN89/T89 -> 0.6984127 | AR89: =AO89/T89 -> 0.38095238 | AS89: =AP89/T89 -> -0.079365079 | BO89: =J28+J14 -> 53126.833 | BP89: =SUM(T28,T14,T43,T59,T74,T89,139,30,14) -> 501 | BQ89: =BO89/BP89 -> 106.04158
A90: 7. Heat Set | B90: Superba Heat Set | C90: 46447 | D90: ='YN01'!$K$333 -> 350 | E90: ='YN01'!$F$333 -> 2659.1722 | F90: ='YN01'!$N$333 -> 319.87518 | G90: ='YN01'!$I$333 -> 0.90136986 | H90: ='YN01'!$J$333 -> 0.85035903 | I90: =D90*E90*F90*G90*H90*0.00016 -> 36510.72 | J90: =(BP!P64+BP!P65)/DAY(EOMONTH(C90,0)) -> 30369.831 | L90: =J90/I90 -> 0.83180588 | M90: =IF((L90*F90)>F90,F90,(L90*F90)) -> 266.07405 | N90: =M90 -> 266.07405 | O90: =ROUNDUP(N90,0) -> 267 | P90: =O90*'Manpower Allocation'!$D$46 -> 14.432432 | Q90: =P90*3 -> 43.297297 | R90: =ROUNDUP(Q90,0) -> 44 | S90: ='Manpower Allocation'!$D$52 -> 12 | T90: =R90+S90 -> 56 | U90: =I90/V90 -> 7302.1439 | V90: 5 | W90: =72*5 -> 360 | X90: =IF(J90>I90,V90,J90/U90) -> 4.1590294 | Y90: =W90*L90 -> 299.45012 | Z90: 4 | AA90: =Z90*X90 -> 16.636118 | AB90: =ROUNDUP(AA90,0) -> 17 | AC90: =AB90*3 -> 51 | AJ90: =J90/I90*6 -> 4.9908353 | AK90: =5*4*3+12 -> 72 | AN90: 44 | AO90: 24 | AP90: =T90-AN90-AO90 -> -12 | AQ90: =AN90/T90 -> 0.78571429 | AR90: =AO90/T90 -> 0.42857143 | AS90: =AP90/T90 -> -0.21428571 | BO90: =J29+J15 -> 44281.844 | BP90: =SUM(T29,T15,T44,T60,T75,T90,139,30,14) -> 484 | BQ90: =BO90/BP90 -> 91.491413
A92: Section | B92: Machine | C92: Month | D92: Avg. Speed | E92: Avg. Denier | F92: Total Spindle | G92: Utilization | H92: Efficiency | I92: Capacity Per Day | J92: BP | L92: Spinder Req. | M92: Spinder Req. | N92: M/C Req. | O92: Shift Req. | P92: MP Req./Shift | Q92: MP Req./Day | R92: MP Req./Day | S92: Standard HC (Fix) | T92: Total Manpower Req. | U92: Capacity/machine | V92: Available M/C | W92: Available Spindles | X92: Req. M/C | Y92: Req. Spindles | Z92: HC Deployed/M/C | AA92: Total HC Req. /Shift | AB92: Total HC Req. /Shift | AC92: Total HC Req. /Day | AD92: Remarks
A93: 7. Heat Set | B93: Power Heat Set | C93: 46113 | D93: ='YN01'!$K$362 -> 400 | E93: ='YN01'!$F$362 -> 2423.6344 | F93: ='YN01'!$L$362 -> 84 | G93: ='YN01'!$I$362 -> 0.83193277 | H93: ='YN01'!$J$362 -> 0.8 | I93: =D93*E93*F93*G93*H93*0.00016 -> 8671.7067 | J93: =(BP!$E$49)/DAY(EOMONTH(C93,0)) -> 3349.0098 | L93: =J93/I93 -> 0.38619961 | M93: =IF((L93*F93)>F93,F93,(L93*F93)) -> 32.440767 | N93: =M93/84 -> 0.38619961 | O93: =ROUND(N93/0.33,0) -> 1 | P93: =4 -> 4 | Q93: =P93*O93 -> 4 | R93: =ROUNDUP(Q93,0) -> 4 | S93: 0 | T93: =R93+S93 -> 4 | U93: =I93/V93 -> 8671.7067 | V93: 1 | W93: 84 | X93: =IF(J93>I93,V93,J93/U93) -> 0.38619961 | Y93: =W93*L93 -> 32.440767 | Z93: 4 | AA93: =Z93*X93 -> 1.5447985 | AB93: =ROUNDUP(AA93,0) -> 2 | AC93: =Z93*AF95 -> 8 | AD93: 1 M/C ~ 84 Spindles = 1 Opt ~ 21 Spindle | AH93: =IF(MOD(AA93,1)<0.34,MOD(AA93,1)*1,IF(AND(MOD(AA93,1)>0.33,MOD(AA93,1)<0.67),MOD(AA93,1)*2,MOD(AA93,1)*3))+ROUNDDOWN(AA93,0)*3 -> 4.0895969 | AI93: =IF(MOD(AA93,1)<0.34,1,IF(AND(MOD(AA93,1)>0.33,MOD(AA93,1)<0.67),2,3))*MOD(AA93,1)+ROUNDDOWN(AA93,0)*3 -> 4.0895969
A94: 7. Heat Set | B94: Power Heat Set | C94: 46143 | D94: ='YN01'!$K$362 -> 400 | E94: ='YN01'!$F$362 -> 2423.6344 | F94: ='YN01'!$L$362 -> 84 | G94: ='YN01'!$I$362 -> 0.83193277 | H94: ='YN01'!$J$362 -> 0.8 | I94: =D94*E94*F94*G94*H94*0.00016 -> 8671.7067 | J94: =(BP!$F$49)/DAY(EOMONTH(C94,0)) -> 2496.4783 | L94: =J94/I94 -> 0.28788777 | M94: =IF((L94*F94)>F94,F94,(L94*F94)) -> 24.182573 | N94: =M94/84 -> 0.28788777 | O94: =ROUND(N94/0.33,0) -> 1 | P94: =4 -> 4 | Q94: =P94*O94 -> 4 | R94: =ROUNDUP(Q94,0) -> 4 | S94: 0 | T94: =R94+S94 -> 4 | U94: =I94/V94 -> 8671.7067 | V94: 1 | W94: 84 | X94: =IF(J94>I94,V94,J94/U94) -> 0.28788777 | Y94: =W94*L94 -> 24.182573 | Z94: 4 | AA94: =Z94*X94 -> 1.1515511 | AB94: =ROUNDUP(AA94,0) -> 2 | AC94: =ROUNDUP(AA94*3,0) -> 4 | AE94: 0-0.33 | AF94: 1 | AG94: shift | AH94: =IF(MOD(AA94,1)<0.34,MOD(AA94,1)*1,IF(AND(MOD(AA94,1)>0.33,MOD(AA94,1)<0.67),MOD(AA94,1)*2,MOD(AA94,1)*3))+ROUNDDOWN(AA94,0)*3 -> 3.1515511 | AI94: =IF(MOD(AA94,1)<0.34,1,IF(AND(MOD(AA94,1)>0.33,MOD(AA94,1)<0.67),2,3))*MOD(AA94,1)+ROUNDDOWN(AA94,0)*3 -> 3.1515511 | AJ94: =3+0.15*1 -> 3.15
A95: 7. Heat Set | B95: Power Heat Set | C95: 46174 | D95: ='YN01'!$K$362 -> 400 | E95: ='YN01'!$F$362 -> 2423.6344 | F95: ='YN01'!$L$362 -> 84 | G95: ='YN01'!$I$362 -> 0.83193277 | H95: ='YN01'!$J$362 -> 0.8 | I95: =D95*E95*F95*G95*H95*0.00016 -> 8671.7067 | J95: =(BP!$G$49)/DAY(EOMONTH(C95,0)) -> 1543.1193 | L95: =J95/I95 -> 0.17794874 | M95: =IF((L95*F95)>F95,F95,(L95*F95)) -> 14.947694 | N95: =M95/84 -> 0.17794874 | O95: =ROUND(N95/0.33,0) -> 1 | P95: =4 -> 4 | Q95: =P95*O95 -> 4 | R95: =ROUNDUP(Q95,0) -> 4 | S95: 0 | T95: =R95+S95 -> 4 | U95: =I95/V95 -> 8671.7067 | V95: 1 | W95: 84 | X95: =IF(J95>I95,V95,J95/U95) -> 0.17794874 | Y95: =W95*L95 -> 14.947694 | Z95: 4 | AA95: =Z95*X95 -> 0.71179496 | AB95: =ROUNDUP(AA95,0) -> 1 | AC95: =Z95*AF94 -> 4 | AE95: 0.34-0.66 | AF95: 2 | AG95: shift | AH95: =IF(MOD(AA95,1)<0.34,MOD(AA95,1)*1,IF(AND(MOD(AA95,1)>0.33,MOD(AA95,1)<0.67),MOD(AA95,1)*2,MOD(AA95,1)*3))+ROUNDDOWN(AA95,0)*3 -> 2.1353849 | AI95: =IF(MOD(AA95,1)<0.34,1,IF(AND(MOD(AA95,1)>0.33,MOD(AA95,1)<0.67),2,3))*MOD(AA95,1)+ROUNDDOWN(AA95,0)*3 -> 2.1353849
A96: 7. Heat Set | B96: Power Heat Set | C96: 46204 | D96: ='YN01'!$K$362 -> 400 | E96: ='YN01'!$F$362 -> 2423.6344 | F96: ='YN01'!$L$362 -> 84 | G96: ='YN01'!$I$362 -> 0.83193277 | H96: ='YN01'!$J$362 -> 0.8 | I96: =D96*E96*F96*G96*H96*0.00016 -> 8671.7067 | J96: =(BP!$H$49)/DAY(EOMONTH(C96,0)) -> 2356.2428 | L96: =J96/I96 -> 0.27171615 | M96: =IF((L96*F96)>F96,F96,(L96*F96)) -> 22.824157 | N96: =M96/84 -> 0.27171615 | O96: =ROUND(N96/0.33,0) -> 1 | P96: =4 -> 4 | Q96: =P96*O96 -> 4 | R96: =ROUNDUP(Q96,0) -> 4 | S96: 0 | T96: =R96+S96 -> 4 | U96: =I96/V96 -> 8671.7067 | V96: 1 | W96: 84 | X96: =IF(J96>I96,V96,J96/U96) -> 0.27171615 | Y96: =W96*L96 -> 22.824157 | Z96: 4 | AA96: =Z96*X96 -> 1.0868646 | AB96: =ROUNDUP(AA96,0) -> 2 | AC96: =ROUNDUP(AA96*3,0) -> 4 | AE96: 0.67-1.00 | AF96: 3 | AG96: shift | AH96: =IF(MOD(AA96,1)<0.34,MOD(AA96,1)*1,IF(AND(MOD(AA96,1)>0.33,MOD(AA96,1)<0.67),MOD(AA96,1)*2,MOD(AA96,1)*3))+ROUNDDOWN(AA96,0)*3 -> 3.0868646 | AI96: =IF(MOD(AA96,1)<0.34,1,IF(AND(MOD(AA96,1)>0.33,MOD(AA96,1)<0.67),2,3))*MOD(AA96,1)+ROUNDDOWN(AA96,0)*3 -> 3.0868646
A97: 7. Heat Set | B97: Power Heat Set | C97: 46235 | D97: ='YN01'!$K$362 -> 400 | E97: ='YN01'!$F$362 -> 2423.6344 | F97: ='YN01'!$L$362 -> 84 | G97: ='YN01'!$I$362 -> 0.83193277 | H97: ='YN01'!$J$362 -> 0.8 | I97: =D97*E97*F97*G97*H97*0.00016 -> 8671.7067 | J97: =(BP!$I$49)/DAY(EOMONTH(C97,0)) -> 2497.963 | L97: =J97/I97 -> 0.28805898 | M97: =IF((L97*F97)>F97,F97,(L97*F97)) -> 24.196955 | N97: =M97/84 -> 0.28805898 | O97: =ROUND(N97/0.33,0) -> 1 | P97: =4 -> 4 | Q97: =P97*O97 -> 4 | R97: =ROUNDUP(Q97,0) -> 4 | S97: 0 | T97: =R97+S97 -> 4 | U97: =I97/V97 -> 8671.7067 | V97: 1 | W97: 84 | X97: =IF(J97>I97,V97,J97/U97) -> 0.28805898 | Y97: =W97*L97 -> 24.196955 | Z97: 4 | AA97: =Z97*X97 -> 1.1522359 | AB97: =ROUNDUP(AA97,0) -> 2 | AC97: =ROUNDUP(AA97*3,0) -> 4 | AH97: =IF(MOD(AA97,1)<0.34,MOD(AA97,1)*1,IF(AND(MOD(AA97,1)>0.33,MOD(AA97,1)<0.67),MOD(AA97,1)*2,MOD(AA97,1)*3))+ROUNDDOWN(AA97,0)*3 -> 3.1522359 | AI97: =IF(MOD(AA97,1)<0.34,1,IF(AND(MOD(AA97,1)>0.33,MOD(AA97,1)<0.67),2,3))*MOD(AA97,1)+ROUNDDOWN(AA97,0)*3 -> 3.1522359
A98: 7. Heat Set | B98: Power Heat Set | C98: 46266 | D98: ='YN01'!$K$362 -> 400 | E98: ='YN01'!$F$362 -> 2423.6344 | F98: ='YN01'!$L$362 -> 84 | G98: ='YN01'!$I$362 -> 0.83193277 | H98: ='YN01'!$J$362 -> 0.8 | I98: =D98*E98*F98*G98*H98*0.00016 -> 8671.7067 | J98: =(BP!$J$49)/DAY(EOMONTH(C98,0)) -> 2883.1571 | L98: =J98/I98 -> 0.33247862 | M98: =IF((L98*F98)>F98,F98,(L98*F98)) -> 27.928204 | N98: =M98/84 -> 0.33247862 | O98: =ROUND(N98/0.33,0) -> 1 | P98: =4 -> 4 | Q98: =P98*O98 -> 4 | R98: =ROUNDUP(Q98,0) -> 4 | S98: 0 | T98: =R98+S98 -> 4 | U98: =I98/V98 -> 8671.7067 | V98: 1 | W98: 84 | X98: =IF(J98>I98,V98,J98/U98) -> 0.33247862 | Y98: =W98*L98 -> 27.928204 | Z98: 4 | AA98: =Z98*X98 -> 1.3299145 | AB98: =ROUNDUP(AA98,0) -> 2 | AC98: =Z98*AF94 -> 4 | AH98: =IF(MOD(AA98,1)<0.34,MOD(AA98,1)*1,IF(AND(MOD(AA98,1)>0.33,MOD(AA98,1)<0.67),MOD(AA98,1)*2,MOD(AA98,1)*3))+ROUNDDOWN(AA98,0)*3 -> 3.3299145 | AI98: =IF(MOD(AA98,1)<0.34,1,IF(AND(MOD(AA98,1)>0.33,MOD(AA98,1)<0.67),2,3))*MOD(AA98,1)+ROUNDDOWN(AA98,0)*3 -> 3.3299145
A99: 7. Heat Set | B99: Power Heat Set | C99: 46296 | D99: ='YN01'!$K$362 -> 400 | E99: ='YN01'!$F$362 -> 2423.6344 | F99: ='YN01'!$L$362 -> 84 | G99: ='YN01'!$I$362 -> 0.83193277 | H99: ='YN01'!$J$362 -> 0.8 | I99: =D99*E99*F99*G99*H99*0.00016 -> 8671.7067 | J99: =(BP!$K$49)/DAY(EOMONTH(C99,0)) -> 2578.8494 | L99: =J99/I99 -> 0.2973866 | M99: =IF((L99*F99)>F99,F99,(L99*F99)) -> 24.980474 | N99: =M99/84 -> 0.2973866 | O99: =ROUND(N99/0.33,0) -> 1 | P99: =4 -> 4 | Q99: =P99*O99 -> 4 | R99: =ROUNDUP(Q99,0) -> 4 | S99: 0 | T99: =R99+S99 -> 4 | U99: =I99/V99 -> 8671.7067 | V99: 1 | W99: 84 | X99: =IF(J99>I99,V99,J99/U99) -> 0.2973866 | Y99: =W99*L99 -> 24.980474 | Z99: 4 | AA99: =Z99*X99 -> 1.1895464 | AB99: =ROUNDUP(AA99,0) -> 2 | AC99: =ROUNDUP(AA99*3,0) -> 4 | AH99: =IF(MOD(AA99,1)<0.34,MOD(AA99,1)*1,IF(AND(MOD(AA99,1)>0.33,MOD(AA99,1)<0.67),MOD(AA99,1)*2,MOD(AA99,1)*3))+ROUNDDOWN(AA99,0)*3 -> 3.1895464 | AI99: =IF(MOD(AA99,1)<0.34,1,IF(AND(MOD(AA99,1)>0.33,MOD(AA99,1)<0.67),2,3))*MOD(AA99,1)+ROUNDDOWN(AA99,0)*3 -> 3.1895464
A100: 7. Heat Set | B100: Power Heat Set | C100: 46327 | D100: ='YN01'!$K$362 -> 400 | E100: ='YN01'!$F$362 -> 2423.6344 | F100: ='YN01'!$L$362 -> 84 | G100: ='YN01'!$I$362 -> 0.83193277 | H100: ='YN01'!$J$362 -> 0.8 | I100: =D100*E100*F100*G100*H100*0.00016 -> 8671.7067 | J100: =(BP!$L$49)/DAY(EOMONTH(C100,0)) -> 4199.5937 | L100: =J100/I100 -> 0.48428687 | M100: =IF((L100*F100)>F100,F100,(L100*F100)) -> 40.680097 | N100: =M100/84 -> 0.48428687 | O100: =ROUND(N100/0.33,0) -> 1 | P100: =4 -> 4 | Q100: =P100*O100 -> 4 | R100: =ROUNDUP(Q100,0) -> 4 | S100: 0 | T100: =R100+S100 -> 4 | U100: =I100/V100 -> 8671.7067 | V100: 1 | W100: 84 | X100: =IF(J100>I100,V100,J100/U100) -> 0.48428687 | Y100: =W100*L100 -> 40.680097 | Z100: 4 | AA100: =Z100*X100 -> 1.9371475 | AB100: =ROUNDUP(AA100,0) -> 2 | AC100: =Z100*AF95 -> 8 | AH100: =IF(MOD(AA100,1)<0.34,MOD(AA100,1)*1,IF(AND(MOD(AA100,1)>0.33,MOD(AA100,1)<0.67),MOD(AA100,1)*2,MOD(AA100,1)*3))+ROUNDDOWN(AA100,0)*3 -> 5.8114424 | AI100: =IF(MOD(AA100,1)<0.34,1,IF(AND(MOD(AA100,1)>0.33,MOD(AA100,1)<0.67),2,3))*MOD(AA100,1)+ROUNDDOWN(AA100,0)*3 -> 5.8114424
A101: 7. Heat Set | B101: Power Heat Set | C101: 46357 | D101: ='YN01'!$K$362 -> 400 | E101: ='YN01'!$F$362 -> 2423.6344 | F101: ='YN01'!$L$362 -> 84 | G101: ='YN01'!$I$362 -> 0.83193277 | H101: ='YN01'!$J$362 -> 0.8 | I101: =D101*E101*F101*G101*H101*0.00016 -> 8671.7067 | J101: =(BP!$M$49)/DAY(EOMONTH(C101,0)) -> 4024.0522 | L101: =J101/I101 -> 0.46404385 | M101: =IF((L101*F101)>F101,F101,(L101*F101)) -> 38.979684 | N101: =M101/84 -> 0.46404385 | O101: =ROUND(N101/0.33,0) -> 1 | P101: =4 -> 4 | Q101: =P101*O101 -> 4 | R101: =ROUNDUP(Q101,0) -> 4 | S101: 0 | T101: =R101+S101 -> 4 | U101: =I101/V101 -> 8671.7067 | V101: 1 | W101: 84 | X101: =IF(J101>I101,V101,J101/U101) -> 0.46404385 | Y101: =W101*L101 -> 38.979684 | Z101: 4 | AA101: =Z101*X101 -> 1.8561754 | AB101: =ROUNDUP(AA101,0) -> 2 | AC101: =Z101*AF95 -> 8 | AH101: =IF(MOD(AA101,1)<0.34,MOD(AA101,1)*1,IF(AND(MOD(AA101,1)>0.33,MOD(AA101,1)<0.67),MOD(AA101,1)*2,MOD(AA101,1)*3))+ROUNDDOWN(AA101,0)*3 -> 5.5685262 | AI101: =IF(MOD(AA101,1)<0.34,1,IF(AND(MOD(AA101,1)>0.33,MOD(AA101,1)<0.67),2,3))*MOD(AA101,1)+ROUNDDOWN(AA101,0)*3 -> 5.5685262 | AJ101: =1*3+0.86*3 -> 5.58
A102: 7. Heat Set | B102: Power Heat Set | C102: 46388 | D102: ='YN01'!$K$362 -> 400 | E102: ='YN01'!$F$362 -> 2423.6344 | F102: ='YN01'!$L$362 -> 84 | G102: ='YN01'!$I$362 -> 0.83193277 | H102: ='YN01'!$J$362 -> 0.8 | I102: =D102*E102*F102*G102*H102*0.00016 -> 8671.7067 | J102: =(BP!$N$49)/DAY(EOMONTH(C102,0)) -> 4427.9416 | L102: =J102/I102 -> 0.51061939 | M102: =IF((L102*F102)>F102,F102,(L102*F102)) -> 42.892029 | N102: =M102/84 -> 0.51061939 | O102: =ROUND(N102/0.33,0) -> 2 | P102: =4 -> 4 | Q102: =P102*O102 -> 8 | R102: =ROUNDUP(Q102,0) -> 8 | S102: 0 | T102: =R102+S102 -> 8 | U102: =I102/V102 -> 8671.7067 | V102: 1 | W102: 84 | X102: =IF(J102>I102,V102,J102/U102) -> 0.51061939 | Y102: =W102*L102 -> 42.892029 | Z102: 4 | AA102: =Z102*X102 -> 2.0424776 | AB102: =ROUNDUP(AA102,0) -> 3 | AC102: =ROUNDUP(AA102*3,0) -> 7 | AH102: =IF(MOD(AA102,1)<0.34,MOD(AA102,1)*1,IF(AND(MOD(AA102,1)>0.33,MOD(AA102,1)<0.67),MOD(AA102,1)*2,MOD(AA102,1)*3))+ROUNDDOWN(AA102,0)*3 -> 6.0424776 | AI102: =IF(MOD(AA102,1)<0.34,1,IF(AND(MOD(AA102,1)>0.33,MOD(AA102,1)<0.67),2,3))*MOD(AA102,1)+ROUNDDOWN(AA102,0)*3 -> 6.0424776
A103: 7. Heat Set | B103: Power Heat Set | C103: 46419 | D103: ='YN01'!$K$362 -> 400 | E103: ='YN01'!$F$362 -> 2423.6344 | F103: ='YN01'!$L$362 -> 84 | G103: ='YN01'!$I$362 -> 0.83193277 | H103: ='YN01'!$J$362 -> 0.8 | I103: =D103*E103*F103*G103*H103*0.00016 -> 8671.7067 | J103: =(BP!$O$49)/DAY(EOMONTH(C103,0)) -> 4698.5491 | L103: =J103/I103 -> 0.54182519 | M103: =IF((L103*F103)>F103,F103,(L103*F103)) -> 45.513316 | N103: =M103/84 -> 0.54182519 | O103: =ROUND(N103/0.33,0) -> 2 | P103: =4 -> 4 | Q103: =P103*O103 -> 8 | R103: =ROUNDUP(Q103,0) -> 8 | S103: 0 | T103: =R103+S103 -> 8 | U103: =I103/V103 -> 8671.7067 | V103: 1 | W103: 84 | X103: =IF(J103>I103,V103,J103/U103) -> 0.54182519 | Y103: =W103*L103 -> 45.513316 | Z103: 4 | AA103: =Z103*X103 -> 2.1673008 | AB103: =ROUNDUP(AA103,0) -> 3 | AC103: =ROUNDUP(AA103*3,0) -> 7 | AH103: =IF(MOD(AA103,1)<0.34,MOD(AA103,1)*1,IF(AND(MOD(AA103,1)>0.33,MOD(AA103,1)<0.67),MOD(AA103,1)*2,MOD(AA103,1)*3))+ROUNDDOWN(AA103,0)*3 -> 6.1673008 | AI103: =IF(MOD(AA103,1)<0.34,1,IF(AND(MOD(AA103,1)>0.33,MOD(AA103,1)<0.67),2,3))*MOD(AA103,1)+ROUNDDOWN(AA103,0)*3 -> 6.1673008
A104: 7. Heat Set | B104: Power Heat Set | C104: 46447 | D104: ='YN01'!$K$362 -> 400 | E104: ='YN01'!$F$362 -> 2423.6344 | F104: ='YN01'!$L$362 -> 84 | G104: ='YN01'!$I$362 -> 0.83193277 | H104: ='YN01'!$J$362 -> 0.8 | I104: =D104*E104*F104*G104*H104*0.00016 -> 8671.7067 | J104: =(BP!$P$49)/DAY(EOMONTH(C104,0)) -> 4162.9382 | L104: =J104/I104 -> 0.48005984 | M104: =IF((L104*F104)>F104,F104,(L104*F104)) -> 40.325027 | N104: =M104/84 -> 0.48005984 | O104: =ROUND(N104/0.33,0) -> 1 | P104: =4 -> 4 | Q104: =P104*O104 -> 4 | R104: =ROUNDUP(Q104,0) -> 4 | S104: 0 | T104: =R104+S104 -> 4 | U104: =I104/V104 -> 8671.7067 | V104: 1 | W104: 84 | X104: =IF(J104>I104,V104,J104/U104) -> 0.48005984 | Y104: =W104*L104 -> 40.325027 | Z104: 4 | AA104: =Z104*X104 -> 1.9202394 | AB104: =ROUNDUP(AA104,0) -> 2 | AC104: =Z104*AF95 -> 8 | AH104: =IF(MOD(AA104,1)<0.34,MOD(AA104,1)*1,IF(AND(MOD(AA104,1)>0.33,MOD(AA104,1)<0.67),MOD(AA104,1)*2,MOD(AA104,1)*3))+ROUNDDOWN(AA104,0)*3 -> 5.7607181 | AI104: =IF(MOD(AA104,1)<0.34,1,IF(AND(MOD(AA104,1)>0.33,MOD(AA104,1)<0.67),2,3))*MOD(AA104,1)+ROUNDDOWN(AA104,0)*3 -> 5.7607181 | AJ104: =1*3+0.92*3 -> 5.76
R105: =AVERAGE(R79:R90) -> 47.916667
A106: Section | B106: Machine | C106: Month | D106: Avg. Speed | E106: Avg. Denier | F106: Total Spindle | G106: Utilization | H106: Efficiency | I106: Capacity Per Day | J106: BP | L106: M/C Req. | M106: M/C Req. | N106: M/C Req. | O106: - | P106: MP Req./Shift | Q106: MP Req./Day | R106: MP Req./Day | S106: Standard HC (Fix) | T106: Total Manpower Req. | U106: Capacity/machine | V106: Available M/C | W106: Available Spindles | X106: Req. M/C | Y106: Req. Spindles | Z106: HC Deployed/M/C | AA106: Total HC Req. /Shift | AB106: Total HC Req. /Shift | AC106: Total HC Req. /Day | AJ106: Associate | AK106: NAPs | AL106: CLM - MD | AM106: CLM - PR | AV106: For 1 M/c, 1 Operator, 1 Mender, 1 Creel work | AW106: Avg MP | AY106: 45748 | AZ106: 45778 | BA106: 45809 | BB106: 45839 | BC106: 45870 | BD106: 45901 | BE106: 45931 | BF106: 45962 | BG106: 45992 | BH106: 46023 | BI106: 46054 | BJ106: 46082
A107: Tufting | B107: 8.1 Tufting | C107: 46113 | G107: =Tufting!$G$23 -> 0.60821918 | H107: =Tufting!$F$23 -> 0.5555 | I107: ='Tufting 2'!$N$17 -> 63542.338 | J107: ='Tufting 2'!$B$17 -> 52035.402 | L107: =J107/I107 -> 0.81890915 | M107: ='Tufting 2'!$Q$17 -> 15.975789 | N107: =ROUND(M107,0) -> 16 | R107: ='Tufting 2'!$AQ$16 -> 108.5 | S107: ='Manpower Allocation'!$D$69 -> 59 | T107: =R107+S107 -> 167.5 | U107: =I107/V107 -> 63542.338 | V107: 1 | Z107: 1 | AJ107: 60 | AK107: 66 | AL107: =T107-(AJ107+AK107+AM107) -> 29.5 | AM107: 12 | AT107: =SUM('Manpower Allocation'!#REF!)+Q107 -> #REF! | AU107: Operator | AV107: =R120 -> 106 | AW107: =14*2.5*3 -> 105 | AX107: For 1 M/c, 1 Operator, 0.5 Mender, 1 Creel work | AY107: =AY119*2.5*3 -> 90 | AZ107: =AZ119*2.5*3 -> 97.5 | BA107: =BA119*2.5*3 -> 97.5 | BB107: =BB119*2.5*3 -> 97.5 | BC107: =BC119*2.5*3 -> 105 | BD107: =BD119*2.5*3 -> 120 | BE107: =BE119*2.5*3 -> 97.5 | BF107: =BF119*2.5*3 -> 112.5 | ... BK107: =BK119*2.5*3 -> 75 | BP107: =J107/T107 -> 310.65911
A108: Tufting | B108: 8.1 Tufting | C108: 46143 | G108: =Tufting!$G$23 -> 0.60821918 | H108: =Tufting!$F$23 -> 0.5555 | I108: ='Tufting 2'!$N$17 -> 63542.338 | J108: ='Tufting 2'!$C$17 -> 45259.705 | L108: =J108/I108 -> 0.71227636 | M108: ='Tufting 2'!$R$17 -> 13.267005 | N108: =ROUND(M108,0) -> 13 | R108: ='Tufting 2'!$AR$16 -> 106 | S108: ='Manpower Allocation'!$D$69 -> 59 | T108: =R108+S108 -> 165 | U108: =I108/V108 -> #DIV/0! | AJ108: 60 | AK108: 66 | AL108: =T108-(AJ108+AK108+AM108) -> 27 | AM108: 12 | AT108: =SUM('Manpower Allocation'!#REF!)+Q108 -> #REF! | AU108: Jobber | AV108: 4 | AW108: 3 | AY108: 3 | AZ108: 3 | BA108: 3 | BB108: 3 | BC108: 3 | BD108: 3 | BE108: 3 | BF108: 3 | BG108: 3 | BH108: 3 | BI108: 3 | BJ108: 3 | BK108: 3 | BO108: =14*2.5*3 -> 105 | BP108: =J108/T108 -> 274.30124
...

Sheet Reqd_MC
A1: Section | B1: Machine | C1: Month | D1: Capacity/Day | E1: Capacity/MC | F1: BP/Month | G1: BP/Day | H1: Available_MC | I1: Reqd_MC
A2: BCF | B2: BCF | C2: 46113 | D2: ='Sectionwise Working'!I4 -> 21686.572 | E2: =D2/H2 -> 2710.8215 | F2: =BP_Strucured!B2 -> 190053.56 | G2: =F2/DAY(EOMONTH(C2,0)) -> 6335.1186 | H2: 8 | I2: =IF(G2>D2,H2,G2/E2) -> 2.3369737
A3: POY | B3: POY | C3: 46113 | D3: ='Sectionwise Working'!I18 -> 32121.952 | E3: =D3/H3 -> 2676.8293 | F3: =BP_Strucured!B6 -> 1518410 | G3: =F3/DAY(EOMONTH(C3,0)) -> 50613.668 | H3: 12 | I3: =IF(G3>D3,H3,G3/E3) -> 12
A4: Texturizing | B4: Texturizing | C4: 46113 | D4: ='Sectionwise Working'!I33 -> 29388.133 | E4: =D4/H4 -> 3673.5166 | F4: =BP_Strucured!B7 -> 1442558.3 | G4: =F4/DAY(EOMONTH(C4,0)) -> 48085.277 | H4: 8 | I4: =IF(G4>D4,H4,G4/E4) -> 8
A5: Parallel Winding | B5: Parallel Winding | C5: 46113 | D5: ='Sectionwise Working'!I49 -> 14098.76 | E5: =D5/H5 -> 3524.69 | F5: =BP_Strucured!B8 -> 772731.27 | G5: =F5/DAY(EOMONTH(C5,0)) -> 25757.709 | H5: 4 | I5: =IF(G5>D5,H5,G5/E5) -> 4
A6: Cabling | B6: Cabling | C6: 46113 | D6: 39644.343 | E6: =D6/H6 -> 2086.5444 | F6: =BP_Strucured!B3 -> 1238788.5 | G6: =F6/DAY(EOMONTH(C6,0)) -> 41292.949 | H6: 19 | I6: =IF(G6>D6,H6,G6/E6) -> 19
A7: Heat Set | B7: Superba Heat Set | C7: 46113 | D7: ='Sectionwise Working'!I79 -> 36510.72 | E7: =D7/H7 -> 7302.1439 | F7: =BP_Strucured!B5 -> 1108335.2 | G7: =F7/DAY(EOMONTH(C7,0)) -> 36944.506 | H7: 5 | I7: =IF(G7>D7,H7,G7/E7) -> 5
A8: Heat Set | B8: Power Heat Set | C8: 46113 | D8: ='Sectionwise Working'!I93 -> 8671.7067 | E8: =D8/H8 -> 8671.7067 | F8: =BP_Strucured!B4 -> 100470.29 | G8: =F8/DAY(EOMONTH(C8,0)) -> 3349.0098 | H8: 1 | I8: =IF(G8>D8,H8,G8/E8) -> 0.38619961
A9: Printing | B9: Printing-Chromojet | C9: 46113 | D9: ='Sectionwise Working'!I139 -> 3314.4422 | E9: =D9/H9 -> 3314.4422 | F9: =BP_Strucured!B13 -> 112252.91 | G9: =F9/DAY(EOMONTH(C9,0)) -> 3741.7637 | H9: 1 | I9: =IF(G9>D9,H9,G9/E9) -> 1
A10: Printing | B10: Printing-Digital | C10: 46113 | D10: ='Sectionwise Working'!I152 -> 2480.0256 | E10: =D10/H10 -> 2480.0256 | F10: =BP_Strucured!B14 -> 24776.395 | G10: =F10/DAY(EOMONTH(C10,0)) -> 825.87982 | H10: 1 | I10: =IF(G10>D10,H10,G10/E10) -> 0.33301262
A11: Coating | B11: Carpet Tiles | C11: 46113 | D11: ='Sectionwise Working'!I168 -> 14758.225 | E11: =D11/H11 -> 14758.225 | F11: =BP_Strucured!B15 -> 96326.288 | G11: =F11/DAY(EOMONTH(C11,0)) -> 3210.8763 | H11: 1 | I11: =IF(G11>D11,H11,G11/E11) -> 0.21756521
A12: Coating | B12: W2W | C12: 46113 | D12: ='Sectionwise Working'!I182 -> 19608.37 | E12: =D12/H12 -> 19608.37 | F12: =BP_Strucured!B16 -> 129572.2 | G12: =F12/DAY(EOMONTH(C12,0)) -> 4319.0735 | H12: 1 | I12: =IF(G12>D12,H12,G12/E12) -> 0.22026683
A13: COPs | B13: COPs | C13: 46113 | D13: ='Sectionwise Working'!I307 -> 8432.052 | E13: =D13/H13 -> 2108.013 | F13: =BP_Strucured!B17 -> 96546.648 | G13: =F13/DAY(EOMONTH(C13,0)) -> 3218.2216 | H13: 4 | I13: =IF(G13>D13,H13,G13/E13) -> 1.5266612
A14: PTST | B14: PTST | C14: 46113 | D14: ='Sectionwise Working'!I322 -> 6355.8246 | E14: =D14/H14 -> 423.72164 | F14: =BP_Strucured!B18 -> 96546.648 | G14: =F14/DAY(EOMONTH(C14,0)) -> 3218.2216 | H14: 15 | I14: =IF(G14>D14,H14,G14/E14) -> 7.5951316
A15: Assembly Winder | B15: Assembly Winder | C15: 46113 | D15: ='Sectionwise Working'!I337 -> 21534.376 | E15: =D15/H15 -> 5383.5939 | F15: =BP_Strucured!B11 -> 168676.95 | G15: =F15/DAY(EOMONTH(C15,0)) -> 5622.565 | H15: 4 | I15: =ROUNDUP(IF(G15>D15,H15,G15/E15),0) -> 2
A16: TFO | B16: TFO | C16: 46113 | D16: ='Sectionwise Working'!I352 -> 11869.222 | E16: =D16/H16 -> 2373.8444 | F16: =BP_Strucured!B12 -> 168676.95 | G16: =F16/DAY(EOMONTH(C16,0)) -> 5622.565 | H16: 5 | I16: =IF(G16>D16,H16,G16/E16) -> 2.3685482
A17: Autoclave | B17: Autoclave | C17: 46113 | D17: ='Sectionwise Working'!I367 -> 7570.8155 | E17: =D17/H17 -> 7570.8155 | F17: =BP_Strucured!B10 -> 72130.301 | G17: =F17/DAY(EOMONTH(C17,0)) -> 2404.3434 | H17: 1 | I17: =IF(G17>D17,H17,G17/E17) -> 0.3175805
A18: Multiply | B18: Multiply | C18: 46113 | D18: ='Sectionwise Working'!I288 -> 11869.222 | E18: =D18/H18 -> #DIV/0! | F18: =BP_Strucured!B9 -> 96546.648 | G18: =F18/DAY(EOMONTH(C18,0)) -> 3218.2216 | I18: =IF(G18>D18,H18,G18/E18) -> #DIV/0!

Sheet Hyderabad
A1: Location | B1: Business | C1: Section | D1: Sr_No | E1: Dept_Machine_Name | F1: Designation | G1: Machine_Count | H1: Manpower_Base_Qty | I1: N_shifts | J1: W | K1: Workload | L1: Formulas | M1: BE_Scientific_Manpower | N1: Operator_Type | O1: Contractors | P1: Company_Associate | Q1: BE_Final_Manpower | R1: General_Shift | S1: Shift_A | T1: Shift_B | U1: Shift_C | V1: Reliever | W1: Remarks
A2: Hyderabad | B2: Flooring | C2: BCF | D2: 1 | E2: BCF | F2: Operator | G2: =Reqd_MC!I2 -> 2.3369737 | I2: 3 | J2: 0.8 | K2: 0.8 operators/machine - 2.5 winders/operator (2 winders/machine) | M2: =IF(MOD(G2*J2,1)<0.3,ROUNDUP(G2*J2*3,0),ROUNDUP(G2*J2,0)*3) -> 6 | Q2: =M2 -> 6
A3: Hyderabad | B3: Flooring | C3: BCF | D3: 2 | E3: BCF | F3: Material Handling | I3: 3 | M3: 3 | Q3: =M3 -> 3
A4: Hyderabad | B4: Flooring | C4: BCF | D4: 3 | E4: BCF | F4: Spinning - Operator | I4: 3 | M4: 4 | Q4: =M4 -> 4
A5: Hyderabad | B5: Flooring | C5: BCF | D5: 4 | E5: BCF | F5: Data Entry | I5: 3 | M5: 0 | Q5: =M5 -> 0
A6: Hyderabad | B6: Flooring | C6: BCF | D6: 5 | E6: BCF | F6: G-Burnout | I6: 3 | M6: 4 | Q6: =M6 -> 4
A7: Hyderabad | B7: Flooring | C7: BCF | D7: 6 | E7: BCF | F7: H-DRYER (BCF+POY) | I7: 3 | M7: 3 | Q7: =M7 -> 3
A8: Hyderabad | B8: Flooring | C8: BCF | D8: 7 | E8: BCF | F8: Chips Charging | I8: 3 | M8: 3 | O8: 1 | Q8: =M8 -> 3
A9: Hyderabad | B9: Flooring | C9: POY | D9: 1 | E9: POY | F9: Operator | G9: =Reqd_MC!I3 -> 12 | H9: 2 | I9: 3 | J9: 0.5 | K9: 0.5 operator/machine | M9: =IF(MOD(G9*J9,1)<0.3,ROUNDUP(G9*J9*3,0),ROUNDUP(G9*J9,0)*3) -> 18 | Q9: =M9 -> 18
A10: Hyderabad | B10: Flooring | C10: POY | D10: 2 | E10: POY | F10: Chips Charging | I10: 3 | M10: 3 | O10: 1 | Q10: =M10 -> 3
A11: Hyderabad | B11: Flooring | C11: POY | D11: 3 | E11: POY | F11: Dryer | I11: 3 | M11: 6 | Q11: =M11 -> 6
A12: Hyderabad | B12: Flooring | C12: POY | D12: 4 | E12: POY | F12: Spinning + Control Room | I12: 3 | M12: 9 | Q12: =M12 -> 9
A13: Hyderabad | B13: Flooring | C13: POY | D13: 5 | E13: POY | F13: Data Entry | I13: 3 | M13: 1 | Q13: =M13 -> 1
A14: Hyderabad | B14: Flooring | C14: POY | D14: 6 | E14: POY | F14: Burn Out | I14: 3 | M14: 6 | Q14: =M14 -> 6
A15: Hyderabad | B15: Flooring | C15: POY | D15: 7 | E15: POY | F15: PD Sample (M/C will install after 5 Month) | I15: 3 | Q15: =M15 -> 0
A16: Hyderabad | B16: Flooring | C16: Texturizing | D16: 1 | E16: Texturizing | F16: Operator | G16: =Reqd_MC!I4 -> 8 | I16: 3 | J16: 2.5625 | K16: 2.5625 operator/machine | M16: =IF(MOD(G16*J16,1)<0.3,ROUNDUP(G16*J16*3,0),ROUNDUP(G16*J16,0)*3) -> 63 | O16: 1 | Q16: =M16 -> 63
A17: Hyderabad | B17: Flooring | C17: Texturizing | D17: 2 | E17: Texturizing | F17: Helper | I17: 3 | M17: 9 | O17: 1 | Q17: =M17 -> 9
A18: Hyderabad | B18: Flooring | C18: Texturizing | D18: 3 | E18: Texturizing | F18: DOE | I18: 3 | O18: 1 | Q18: =M18 -> 0
A19: Hyderabad | B19: Flooring | C19: Texturizing | D19: 4 | E19: Texturizing | F19: Jobber | I19: 3 | M19: 3 | O19: 1 | Q19: =M19 -> 3
A20: Hyderabad | B20: Flooring | C20: Texturizing | D20: 5 | E20: Texturizing | F20: Fitter | I20: 3 | M20: 3 | O20: 1 | Q20: =M20 -> 3
A21: Hyderabad | B21: Flooring | C21: Texturizing | D21: 6 | E21: Texturizing | F21: Material Handler | I21: 3 | M21: 3 | O21: 1 | Q21: =M21 -> 3
A22: Hyderabad | B22: Flooring | C22: Texturizing | D22: 7 | E22: Texturizing | F22: Paper Tube Sagrigation | I22: 3 | M22: 1 | O22: 1 | Q22: =M22 -> 1
A23: Hyderabad | B23: Flooring | C23: Texturizing | D23: 8 | E23: Texturizing | F23: Roping (Mandays) | I23: 3 | M23: 3 | O23: 1 | Q23: =M23 -> 3
A24: Hyderabad | B24: Flooring | C24: Parallel Winding | D24: 1 | E24: Parallel Winding | F24: Operator | G24: =Reqd_MC!H5 -> 4 | I24: 3 | J24: 2 | K24: 2 operator/machine | M24: =IF(MOD(G24*J24,1)<0.3,ROUNDUP(G24*J24*3,0),ROUNDUP(G24*J24,0)*3) -> 24 | O24: 1 | Q24: =M24 -> 24
A25: Hyderabad | B25: Flooring | C25: Parallel Winding | D25: 2 | E25: Parallel Winding | F25: Jobber | I25: 3 | M25: 3 | O25: 1 | Q25: =M25 -> 3
A26: Hyderabad | B26: Flooring | C26: Cabling | D26: 1 | E26: Cabling | F26: Operator | G26: =Reqd_MC!H6 -> 19 | I26: 3 | J26: 1 | K26: 1 operator/machine | M26: =IF(MOD(G26*J26,1)<0.3,ROUNDUP(G26*J26*3,0),ROUNDUP(G26*J26,0)*3) -> 57 | O26: 1 | Q26: =M26 -> 57
A27: Hyderabad | B27: Flooring | C27: Cabling | D27: 2 | E27: Cabling | F27: DOE | I27: 3 | M27: =0 -> 0 | O27: 1 | Q27: =M27 -> 0
A28: Hyderabad | B28: Flooring | C28: Cabling | D28: 3 | E28: Cabling | F28: Jobber | I28: 3 | M28: =1*3 -> 3 | O28: 1 | Q28: =M28 -> 3
A29: Hyderabad | B29: Flooring | C29: Cabling | D29: 4 | E29: Cabling | F29: Fitter | I29: 3 | M29: =1*3 -> 3 | O29: 1 | Q29: =M29 -> 3
A30: Hyderabad | B30: Flooring | C30: Cabling | D30: 5 | E30: Cabling | F30: Material Handler | I30: 3 | M30: =1*3 -> 3 | O30: 1 | Q30: =M30 -> 3
A31: Hyderabad | B31: Flooring | C31: Cabling | D31: 6 | E31: Cabling | F31: Helper | I31: 3 | M31: =1*3 -> 3 | O31: 1 | Q31: =M31 -> 3
A32: Hyderabad | B32: Flooring | C32: Heat Set | D32: 1 | E32: Superba Heat Set | F32: Operator | G32: =Reqd_MC!H7 -> 5 | I32: 3 | J32: 4 | K32: 4 operator/machine | M32: =IF(MOD(G32*J32,1)<0.3,ROUNDUP(G32*J32*3,0),ROUNDUP(G32*J32,0)*3) -> 60 | Q32: =M32 -> 60
A33: Hyderabad | B33: Flooring | C33: Heat Set | D33: 2 | E33: Superba Heat Set | F33: DOE | I33: 3 | M33: 0 | Q33: =M33 -> 0
A34: Hyderabad | B34: Flooring | C34: Heat Set | D34: 3 | E34: Superba Heat Set | F34: Jobber | I34: 3 | M34: 3 | Q34: =M34 -> 3
A35: Hyderabad | B35: Flooring | C35: Heat Set | D35: 4 | E35: Superba Heat Set | F35: Material Handler | I35: 3 | M35: 3 | O35: 1 | Q35: =M35 -> 3
A36: Hyderabad | B36: Flooring | C36: Heat Set | D36: 5 | E36: Superba Heat Set | F36: Paper Tube Sagrgation | I36: 3 | M36: 3 | O36: 1 | Q36: =M36 -> 3
A37: Hyderabad | B37: Flooring | C37: Heat Set | D37: 6 | E37: Superba Heat Set | F37: Fitter | I37: 3 | M37: 3 | Q37: =M37 -> 3
A38: Hyderabad | B38: Flooring | C38: Heat Set | D38: 1 | E38: Power Heat Set | F38: Operator | G38: =Reqd_MC!H8 -> 1 | I38: 3 | J38: 4 | K38: 4 operator/machine | M38: =IF(MOD(G38*J38,1)<0.3,ROUNDUP(G38*J38*3,0),ROUNDUP(G38*J38,0)*3) -> 12 | Q38: =M38 -> 12
A39: Hyderabad | B39: Flooring | C39: Printing | D39: 1 | E39: Printing-Chromojet | F39: Operator | G39: =Reqd_MC!I9 -> 1 | I39: 3 | J39: 9 | K39: 9 operator/machine | M39: =IF(G39<=0.33,1,(IF(G39<=0.66,2,3)))*J39 -> 27 | Q39: =M39 -> 27
A40: Hyderabad | B40: Flooring | C40: Printing | D40: 2 | E40: Printing-Chromojet | F40: Sample Machine | I40: 3 | M40: 6 | Q40: =M40 -> 6
A41: Hyderabad | B41: Flooring | C41: Printing | D41: 1 | E41: Printing-Digital | F41: Operator | G41: =Reqd_MC!I10 -> 0.33301262 | I41: 3 | J41: 6 | K41: 6 operator/machine | M41: =IF(G41<=0.33,1,(IF(G41<=0.66,2,3)))*J41 -> 12 | Q41: =M41 -> 12
A42: Hyderabad | B42: Flooring | C42: Printing | D42: 2 | E42: Printing-Digital | F42: Fork lift | I42: 3 | M42: 3 | Q42: =M42 -> 3
A43: Hyderabad | B43: Flooring | C43: Coating | D43: 1 | E43: Coating - Carpet Tiles | F43: Operator | G43: =Reqd_MC!I11 -> 0.21756521 | I43: 3 | J43: 21 | K43: 21 operator/machine | M43: =IF(G43<=0.33,1,(IF(G43<=0.66,2,3)))*J43 -> 21 | Q43: =M43 -> 21
A44: Hyderabad | B44: Flooring | C44: Coating | D44: 2 | E44: Coating - Carpet Tiles | F44: Calcium Loading | I44: 3 | M44: 2 | Q44: =M44 -> 2
A45: Hyderabad | B45: Flooring | C45: Coating | D45: 3 | E45: Coating - Carpet Tiles | F45: Pearl Mill | I45: 3 | M45: 5 | Q45: =M45 -> 5
A46: Hyderabad | B46: Flooring | C46: Coating | D46: 4 | E46: Coating - Carpet Tiles | F46: Compounding | I46: 3 | M46: 5 | Q46: =M46 -> 5
A47: Hyderabad | B47: Flooring | C47: Coating | D47: 1 | E47: Coating - W2W | F47: Operator | G47: =Reqd_MC!I12 -> 0.22026683 | I47: 3 | J47: 10 | K47: 10 operator/machine | M47: =IF(G47<=0.33,1,(IF(G47<=0.66,2,3)))*J47 -> 10 | Q47: =M47 -> 10
A48: Hyderabad | B48: Flooring | C48: Coating | D48: 2 | E48: Coating - W2W | F48: MP for Rework | I48: 3 | M48: 9 | Q48: =M48 -> 9
A49: Hyderabad | B49: Flooring | C49: Coating | D49: 3 | E49: Coating - W2W | F49: Forklift Driver | I49: 3 | M49: 6 | Q49: =M49 -> 6
A50: Hyderabad | B50: Flooring | C50: Coating | D50: 4 | E50: Coating - W2W | F50: Side Matching | I50: 3 | M50: 8 | Q50: =M50 -> 8
A51: Hyderabad | B51: Flooring | C51: Coating | D51: 5 | E51: Coating - W2W | F51: TPR | I51: 3 | M51: 6 | Q51: =M51 -> 6
A52: Hyderabad | B52: Flooring | C52: Coating | D52: 6 | E52: Coating - W2W | F52: Rerolling | I52: 3 | M52: 6 | Q52: =M52 -> 6
A53: Hyderabad | B53: Flooring | C53: TQM | D53: 1 | F53: Yarn | I53: 3 | M53: 34 | Q53: =M53 -> 34
A54: Hyderabad | B54: Flooring | C54: TQM | D54: 2 | F54: Tufting | I54: 3 | M54: 3 | Q54: =M54 -> 3
A55: Hyderabad | B55: Flooring | C55: TQM | D55: 3 | F55: Printing | I55: 3 | M55: 3 | Q55: =M55 -> 3
A56: Hyderabad | B56: Flooring | C56: TQM | D56: 4 | F56: Coating | I56: 3 | M56: 19 | Q56: =M56 -> 19
A57: Hyderabad | B57: Flooring | C57: TQM | D57: 5 | F57: CSP | I57: 3 | M57: 37 | Q57: =M57 -> 37
A58: Hyderabad | B58: Flooring | C58: TQM | D58: 6 | F58: SPC | I58: 3 | M58: 4 | Q58: =M58 -> 4
A59: Hyderabad | B59: Flooring | C59: Engg. | D59: 1 | F59: ASRS - Instrument | I59: 3 | M59: 1 | Q59: =M59 -> 1
A60: Hyderabad | B60: Flooring | C60: Engg. | D60: 2 | I60: 3 | Q60: =M60 -> 0
A61: Hyderabad | B61: Flooring | C61: Engg. | D61: 3 | F61: Electrical - outside HT Yard | I61: 3 | M61: - | Q61: =M61 -> -
A62: Hyderabad | B62: Flooring | C62: Engg. | D62: 4 | F62: Electrical - Sub Station (HT/PCC) | I62: 3 | M62: 3 | Q62: =M62 -> 3
A63: Hyderabad | B63: Flooring | C63: Engg. | D63: 5 | F63: Electrical - Transformer / PCC / PDB / MLDB / Capacitors / Motors for Utilities | I63: 3 | M63: 1 | Q63: =M63 -> 1
A64: Hyderabad | B64: Flooring | C64: Engg. | D64: 6 | F64: Utility O &M - WTP/ETP/Fire hydrant/LNG | I64: 3 | M64: 6 | Q64: =M64 -> 6
A65: Hyderabad | B65: Flooring | C65: Engg. | D65: 7 | F65: Utility - Civil | I65: 3 | M65: 1 | Q65: =M65 -> 1
A66: Hyderabad | B66: Flooring | C66: Engg. | D66: 8 | F66: Utility - DG Operations | I66: 3 | M66: 2 | Q66: =M66 -> 2
A67: Hyderabad | B67: Flooring | C67: Engg. | D67: 9 | F67: Utility - Pump House | I67: 3 | M67: 2 | Q67: =M67 -> 2
A68: Hyderabad | B68: Flooring | C68: Engg. | D68: 10 | F68: Utility O &M - Boiler, CHP,MEE | I68: 3 | M68: 3 | Q68: =M68 -> 3
A69: Hyderabad | B69: Flooring | C69: Engg. | D69: 11 | F69: Utility O &M - Compressors/ chillers | I69: 3 | M69: 3 | Q69: =M69 -> 3
A70: Hyderabad | B70: Flooring | C70: Engg. | D70: 12 | F70: Utility O &M - HVAC/N2 plant | I70: 3 | M70: 4 | Q70: =M70 -> 4
A71: Hyderabad | B71: Flooring | C71: Engg. | D71: 13 | F71: Utility O &M - PM Activities | I71: 3 | M71: 0 | Q71: =M71 -> 0
A72: Hyderabad | B72: Flooring | C72: Engg. | D72: 14 | F72: Utility O &M- Instrument | I72: 3 | M72: 2 | Q72: =M72 -> 2
A73: Hyderabad | B73: Flooring | C73: Engg. | D73: 15 | F73: Insrument lab | I73: 3 | Q73: =M73 -> 0
A74: Hyderabad | B74: Flooring | C74: Engg. | D74: 16 | F74: WAMIL - Boiler - Husk and Coal Handling | I74: 3 | M74: 8 | Q74: =M74 -> 8
A75: Hyderabad | B75: Flooring | C75: Engg. | D75: 17 | F75: Wamil ETP | I75: 3 | M75: 2 | Q75: =M75 -> 2
A76: Hyderabad | B76: Flooring | C76: Engg. | D76: 18 | F76: Wamil TFH | I76: 3 | M76: 7 | Q76: =M76 -> 7
A77: Hyderabad | B77: Flooring | C77: Engg. | D77: 19 | F77: WFL Boiler - Husk and Coal Handling | I77: 3 | M77: 9 | Q77: =M77 -> 9
A78: Hyderabad | B78: Flooring | C78: Engg. | D78: 20 | F78: Turner | I78: 3 | M78: 2 | Q78: =M78 -> 2
A79: Hyderabad | B79: Flooring | C79: Engg. | D79: 21 | F79: Milling/ Grinding | I79: 3 | M79: 1 | Q79: =M79 -> 1
A80: Hyderabad | B80: Flooring | C80: Engg. | D80: 22 | F80: Fitter | I80: 3 | M80: 1 | Q80: =M80 -> 1
A81: Hyderabad | B81: Flooring | C81: Engg. | D81: 23 | F81: Welder | I81: 3 | M81: 2 | Q81: =M81 -> 2
A82: Hyderabad | B82: Flooring | C82: Engg. | D82: 24 | F82: Carpenter | I82: 3 | M82: 1 | Q82: =M82 -> 1
A83: Hyderabad | B83: Flooring | C83: Engg. | D83: 25 | F83: Rigger | I83: 3 | M83: 2 | Q83: =M83 -> 2
A84: Hyderabad | B84: Flooring | C84: Engg. | D84: 26 | F84: Yarn | I84: 3 | M84: 28 | Q84: =M84 -> 28
A85: Hyderabad | B85: Flooring | C85: Engg. | D85: 27 | F85: T&C | I85: 3 | M85: 22 | Q85: =M85 -> 22
A86: Hyderabad | B86: Flooring | C86: Engg. | D86: 28 | I86: 3 | M86: 4 | Q86: =M86 -> 4
A87: Hyderabad | B87: Flooring | C87: R&D (PD) | D87: 1 | F87: Yarn | I87: 3 | M87: 3 | Q87: =M87 -> 3
A88: Hyderabad | B88: Flooring | C88: R&D (PD) | D88: 2 | F88: Tufting | I88: 3 | M88: 3 | Q88: =M88 -> 3
A89: Hyderabad | B89: Flooring | C89: R&D (PD) | D89: 3 | F89: Printing | I89: 3 | M89: 3 | Q89: =M89 -> 3
A90: Hyderabad | B90: Flooring | C90: R&D (PD) | D90: 4 | F90: Coating | I90: 3 | M90: 24 | Q90: =M90 -> 24
A91: Hyderabad | B91: Flooring | C91: R&D (PD) | D91: 5 | F91: SPC | I91: 3 | M91: 6 | Q91: =M91 -> 6
A92: Hyderabad | B92: Flooring | C92: SCM (Stores & WH) | D92: 1 | F92: Common | I92: 3 | M92: 30 | Q92: =M92 -> 30
A93: Hyderabad | B93: Flooring | C93: SCM (Stores & WH) | D93: 2 | F93: Yarn(CL+PR) | I93: 3 | M93: 9 | Q93: =M93 -> 9
A94: Hyderabad | B94: Flooring | C94: SCM (Stores & WH) | D94: 3 | F94: Tufting BAILING -PR | I94: 3 | M94: 0 | Q94: =M94 -> 0
A95: Hyderabad | B95: Flooring | C95: SCM (Stores & WH) | D95: 4 | F95: Coating UNLOADING-PR | I95: 3 | M95: 0 | Q95: =M95 -> 0
A96: Hyderabad | B96: Flooring | C96: SCM (Stores & WH) | D96: 5 | F96: Tufting and Coating (CL+PR) | I96: 3 | M96: 63 | Q96: =M96 -> 63
A97: Hyderabad | B97: Flooring | C97: SCM (Stores & WH) | D97: 6 | F97: SPC | I97: 3 | M97: 17 | Q97: =M97 -> 17
A98: Hyderabad | B98: Flooring | C98: Common | D98: 1 | F98: PPC | I98: 3 | M98: 5 | Q98: =M98 -> 5
... A102: Hyderabad | B102: Flooring | C102: Common | D102: 5 | F102: TRAINER | I102: 3 | M102: 6 | Q102: =M102 -> 6
A103: Hyderabad | B103: Flooring | C103: COPs | D103: 1 | E103: COPs | F103: Operator | G103: =Reqd_MC!I13 -> 1.5266612 | I103: 3 | J103: 1.5 | M103: =ROUNDUP(G103*J103,0)*3 -> 9 | Q103: =M103 -> 9 | W103: Here first logic is only applied
...

Sheet Manpower Allocation
C1: Category | D1: HC | N1: Multiply
A2: BCF | B2: Winder Operator | C2: Associate 80% | E2: -7 | F2: Multiskilling - POY 250 and 300 Denier Operator will be develop as multiskill for BCF and POY | N2: =1.5*10*3 -> 45 | O2: Operator PTST
A3: BCF | B3: Material Handling | C3: NAPs | D3: 3 | N3: =2*2*3 -> 12 | O3: Servo winder
A4: BCF | B4: Spinning - Operator | C4: Associate | D4: 4 | N4: =2*3*3 -> 18 | O4: TFO
A5: BCF | B5: Data Entry | C5: Associate | D5: 0 | E5: -1 | N5: =4*3*3 -> 36 | O5: Assembly
A6: BCF | B6: G-Burnout | C6: Associate | D6: 4 | E6: -1 | N6: =2*1*2 -> 4 | O6: Auto Clave
A7: BCF | B7: H-DRYER (BCF+POY) | C7: Associate | D7: 3 | E7: -2 | N7: =4*3 -> 12 | O7: Helper | P7: =N7 -> 12 | Q7: =4*3 -> 12
A8: BCF | B8: Chips Charging | C8: CLM MD | D8: 3 | N8: 3 | O8: Fitter | P8: =N8 -> 3 | Q8: =1*3 -> 3
D9: =SUM(D3:D8) -> 17 | N9: 3 | O9: Jobber | P9: =N9 -> 3 | Q9: =1*3 -> 3
N10: 3 | O10: DEO | P10: =N10 -> 3 | Q10: 0
A11: POY | B11: Takeup (Winder) | C11: Associate 80% | N11: 3 | O11: HR | P11: =N11 -> 3 | Q11: 1
A12: POY | B12: Chips Charging | C12: CLM MD | D12: 3 | G12: 90 Min Doff - 480 180 min Doff - 300 | M12: =SUM(N7:N11) -> 24 | N12: =SUM(N2:N11) -> 139 | O12: TOTAL | P12: =SUM(P7:P11) -> 24 | Q12: =SUM(Q7:Q11) -> 19
A13: POY | B13: Dryer | C13: Associate | D13: 6 | E13: 6
A14: POY | B14: Spinning + Control Room | C14: Associate | D14: 9
A15: POY | B15: Data Entry | C15: Associate | D15: 1 | N15: Texturizing M/C and Denier Planning
A16: POY | B16: Burn Out | C16: Associate | D16: 6 | N16: M/C | O16: Side | P16: Denier | Q16: HC/Shift/Side | R16: HC/Day
A17: POY | B17: PD Sample (M/C will install after 5 Month) | C17: Associate | N17: 1 | O17: A | P17: 1200 | Q17: 3 | R17: =Q17*3 -> 9
D18: =SUM(D12:D17) -> 25 | N18: 1 | O18: B | P18: 1200 | Q18: 2 | R18: =Q18*3 -> 6
N19: 2 | O19: A | P19: 1200 | Q19: 2 | R19: =Q19*3 -> 6
A20: Tex | B20: Operator | C20: CLM PR | N20: 2 | O20: B | P20: 1200 | Q20: 2 | R20: =Q20*3 -> 6
A21: Tex | B21: Helper | C21: CLM PR | D21: 9 | N21: 5 | O21: A | P21: 1800 | Q21: 3 | R21: =Q21*3 -> 9
A22: Tex | B22: DOE | C22: CLM PR | M22: Data Automation | N22: 5 | O22: B | P22: 1800 | Q22: 3 | R22: =Q22*3 -> 9
A23: Tex | B23: Jobber | C23: CLM PR | D23: 3 | N23: 6 | O23: A | P23: 300 | Q23: 1.5 | R23: =Q23*3 -> 4.5
A24: Tex | B24: Fitter | C24: CLM PR | D24: 3 | N24: 6 | O24: B | P24: 300 | Q24: 1.5 | R24: =Q24*3 -> 4.5
A25: Tex | B25: Material Handler | C25: CLM PR | D25: 3 | N25: 7 | O25: A | P25: 1200 | Q25: 2 | R25: =Q25*3 -> 6
A26: Tex | B26: Paper Tube Sagrigation | C26: CLM PR | D26: 1 | N26: 7 | O26: B | P26: 1200 | Q26: 2 | R26: =Q26*3 -> 6
A27: Tex | B27: Roping (Mandays) | C27: CLM PR | D27: 3 | N27: 8 | O27: A | P27: 1200 | Q27: 2 | R27: =Q27*3 -> 6
B28: Total | D28: =SUM(D21:D27) -> 22 | N28: 8 | O28: B | P28: 1200 | Q28: 2 | R28: =Q28*3 -> 6
N29: 3/4 Sample | Q29: 1 | R29: =Q29*3 -> 3
R30: =SUM(R17:R29) -> 81 | S30: 20.5
R31: 22
A32: PW | B32: Operator | C32: CLM PR | D32: =2/44 -> 0.045454545 | R32: =R30+R31 -> 103
A33: PW | B33: Jobber | C33: CLM PR | D33: 3
B37: Cabling
A38: Cabling | B38: Operator | C38: CLM PR | D38: =19/(16*176+3*144) -> 0.0058497537
A39: Cabling | B39: DOE | C39: CLM PR | D39: =0 -> 0
A40: Cabling | B40: Jobber | C40: CLM PR | D40: =1*3 -> 3
A41: Cabling | B41: Fitter | C41: CLM PR | D41: =1*3 -> 3
A42: Cabling | B42: Material Handler | C42: CLM PR | D42: =1*3 -> 3
A43: Cabling | B43: Helper | C43: CLM PR | D43: =1*3 -> 3
D44: =SUM(D39:D43) -> 12
B45: Heat Setting | F45: =((6*3*3)+(5*3))/((72*5)+84)/3 -> 0.051801802
A46: Heat Set | B46: Operator | C46: Associate 60% | D46: =24/444 -> 0.054054054 | G46: =4*6*3*0.6 -> 43.2 | H46: =4*6*3*0.4 -> 28.8
A47: Heat Set | B47: DOE | D47: 0
A48: Heat Set | B48: Jobber | C48: Associate | D48: =1*3 -> 3 | G48: 3
A49: Heat Set | B49: Material Handler | C49: CLM - MD | D49: =1*3 -> 3
A50: Heat Set | B50: Paper Tube Sagrgation | C50: NAPS/CLM MD | D50: =1*3 -> 3 | H50: 3
A51: Heat Set | B51: Fitter | C51: Associate | D51: =1*3 -> 3 | G51: 3
B52: Total | D52: =SUM(D47:D51) -> 12 | G52: 1 Associate, 1 NAPs, .5 MD | H52: 2 Associate, 1 NAPs, .5 MD
G53: 2.5 | H53: 3.5
G54: =G53*12*3 -> 90 | H54: =H53*2*3 -> 21
B55: Tufting | E55: Actual | G55: Associate | H55: NAPs | I55: CLM - MD | J55: CLM - PR
A56: Tufting | B56: Operator and Helper | C56: Associate + NAPs + CLM | D56: =((16*2.5)+(2*3.5))/18 -> 2.6111111 | G56: =(1*12*3)+(2*2*3) -> 48 | H56: =(1*12*3)+(1*2*3) -> 42 | I56: =(0.5*14*3) -> 21 | L56: =N56 -> 90 | N56: =10*1*3+2*2*3+(8*3)+(8*3) -> 90
A57: Tufting | B57: Jobber | C57: Associate | D57: =1*3 -> 3 | G57: 3 | L57: =1*3 -> 3 | N57: 3
A58: Tufting | B58: MHE | C58: CLM - MD | D58: =5 -> 5 | I58: 5 | L58: =5 -> 5 | N58: 5
A59: Tufting | B59: Material Handler | C59: CLM/NAPs | D59: =0 -> 0 | L59: =0 -> 0 | N59: 0
A60: Tufting | B60: Blade Grinder | C60: Associate | D60: 3 | G60: 3 | L60: 3 | N60: 3
A61: Tufting | B61: Technician | C61: Associate | D61: =2*3 -> 6 | G61: 6 | L61: =2*3 -> 6 | N61: 6
A62: Tufting | B62: Rewinding and Bit Winding | C62: CLM/NAPs | D62: =7*3 -> 21 | E62: (1 Asso, 5 Naps, 1 CLM- MD) | G62: 3 | H62: 15 | I62: 3 | L62: =7*3 -> 21 | N62: 21
A63: Tufting | B63: Yarn Clearance | C63: CLM/NAPs | D63: =2*3 -> 6 | E63: NAPs | H63: 6 | L63: =2*3 -> 6 | N63: 6
A64: Tufting | B64: Roll Packing | C64: Associate | D64: 3 | E64: NAPs | H64: 3 | L64: 3 | M64: can be done be operator. | N64: 3
A65: Tufting | B65: Rope | C65: CLM-PR | D65: =4*3 -> 12 | E65: CLM-PR | J65: 12 | L65: =4*3 -> 12 | N65: =SUM(N56:N64) -> 137
A66: Tufting | B66: Process Control | D66: 0 | G66: =SUM(G56:G65) -> 63 | H66: =SUM(H56:H65) -> 66 | I66: =SUM(I56:I65) -> 29 | J66: =SUM(J56:J65) -> 12 | K66: =SUM(G66:J66) -> 170 | L66: 0 | N66: 12
G67: =G66/$K$66 -> 0.37058824 | H67: =H66/$K$66 -> 0.38823529 | I67: =I66/$K$66 -> 0.17058824 | J67: =J66/$K$66 -> 0.070588235 | L67: =SUM(L56:L66) -> 149 | N67: 3
G68: 59.5 | H68: 45.458333 | I68: 45.541667 | J68: 12
D69: =SUM(D57:D66) -> 59 | H69: 66 | I69: =91-H69 -> 25
H70: =H69-H68 -> 20.541667 | I70: =I68-I69 -> 20.541667 | J70: =I70*7000 -> 143791.67
A72: Tufting | B72: Changeover Crew
B79: Chromojet | E79: Associate | F79: Naps | G79: MD
A80: Chromojet | B80: Unwinding and Stitching | C80: Associate/NAPs | D80: 2 | E80: 1 | F80: 1 | H80: =E80*3 -> 3 | I80: =F80*3 -> 3 | J80: =G80*3 -> 0
A81: Chromojet | B81: Operator | C81: Associate | D81: 2 | E81: 2 | H81: =E81*3 -> 6 | I81: =F81*3 -> 0 | J81: =G81*3 -> 0
A82: Chromojet | B82: Washing & Dryer | C82: Associate | D82: 1 | E82: 1 | H82: =E82*3 -> 3 | I82: =F82*3 -> 0 | J82: =G82*3 -> 0
A83: Chromojet | B83: Winder | C83: Associate | D83: 1 | E83: 1 | H83: =E83*3 -> 3 | I83: =F83*3 -> 0 | J83: =G83*3 -> 0
A84: Chromojet | B84: Color Kitchen | C84: Associate | D84: 3 | E84: 2 | F84: 1 | H84: =E84*3 -> 6 | I84: =F84*3 -> 3 | J84: =G84*3 -> 0
D85: =SUM(D80:D84) -> 9 | E85: =SUM(E80:E84) -> 7 | F85: =SUM(F80:F84) -> 2 | H85: =SUM(H80:H84) -> 21 | I85: =SUM(I80:I84) -> 6 | J85: =SUM(J80:J84) -> 0
B87: Digital Printing
A88: Digital | B88: Stitching | C88: Associate/NAPs | D88: 2 | E88: 1 | F88: 1 | H88: =E88*3 -> 3 | I88: =F88*3 -> 3 | J88: =G88*3 -> 0
A89: Digital | B89: Pre-Treatment | C89: Associate | D89: 1 | E89: 1 | H89: =E89*3 -> 3 | I89: =F89*3 -> 0 | J89: =G89*3 -> 0
A90: Digital | B90: Head - Printing | C90: Associate | D90: 1 | E90: 1 | H90: =E90*3 -> 3 | I90: =F90*3 -> 0 | J90: =G90*3 -> 0
A91: Digital | B91: Dryer | C91: Associate | D91: 1 | F91: 1 | H91: =E91*3 -> 0 | I91: =F91*3 -> 3 | J91: =G91*3 -> 0
A92: Digital | B92: Winder | C92: Associate | D92: 1 | F92: 1 | H92: =E92*3 -> 0 | I92: =F92*3 -> 3 | J92: =G92*3 -> 0
D93: =SUM(D88:D92) -> 6 | H93: =SUM(H88:H92) -> 9 | I93: =SUM(I88:I92) -> 9 | J93: =SUM(J88:J92) -> 0
A95: Printing | B95: Sample M/C | C95: Associate/NAPs | D95: 6 | E95: 1 | F95: 1 | H95: =E95*3 -> 3 | I95: =F95*3 -> 3 | J95: =G95*3 -> 0
H96: =H95+H85 -> 24 | I96: =I95+I85 -> 9 | J96: =J95+J85 -> 0
H97: =H96/3*2 -> 16 | I97: =I96/3*2 -> 6
A98: Printing | B98: Fork lift | C98: CLM MD | D98: 3 | G98: 1 | H98: =E98*3 -> 0 | I98: =F98*3 -> 0 | J98: =G98*3 -> 3
D99: =SUM(D97:D98) -> 3 | H99: =SUM(H80:H98) -> 103 | I99: =SUM(I80:I98) -> 48 | J99: =SUM(J80:J98) -> 3
B101: CT | D101: =SUM(D102:D118) -> 21
A102: Coating | B102: Stitching | C102: Associate/Naps | D102: 2
A103: Coating | B103: Topical | C103: Associate | D103: 1
A104: Coating | B104: Latex (Carpet Precoat) | C104: Associate/Naps | D104: 2
A105: Coating | B105: Shearing | C105: Associate | D105: 1
A106: Coating | B106: PVC Operator | C106: Associate | D106: 1
A107: Coating | B107: Glass Scrim/non woven Pad | C107: Associate | D107: 1
A108: Coating | B108: Material Loading | C108: CLM MD | D108: 1
A109: Coating | B109: Selvage Cutter | C109: Associate | D109: 0
A110: Coating | B110: Extruder Main Operator | C110: Associate | D110: 1
A111: Coating | B111: Die Cutting | C111: Associate | D111: 1
A112: Coating | B112: Selvage Retrack | D112: 0
A113: Coating | B113: Inspection/Segrigation | C113: NAPS | D113: 1
...

Sheet Workmen Category
B1: 46113 | H1: 46143 | N1: 46174 | T1: 46204 | Z1: 46235 | AF1: 46266 | AL1: 46296 | AR1: 46327 | AX1: 46357 | BD1: 46388 | BJ1: 46419 | BP1: 46447 | BX1: Average 2026-27 | CE1: Piece Rate Costing | CI1: Soft Flooring | CQ1: Hard Flooring
A2: ='Monthly HC & Prodn Working'!B2 -> Section | B2: ='Monthly HC & Prodn Working'!D2 -> 46113 | C2: Associate | D2: NAPs | E2: CLM - MD | F2: CLM - PR | G2: Total | H2: ='Monthly HC & Prodn Working'!E2 -> 46143 | I2: Associate | J2: NAPs | K2: CLM - MD | L2: CLM - PR | M2: Total | N2: ='Monthly HC & Prodn Working'!F2 -> 46174 | O2: Associate | P2: NAPs | Q2: CLM - MD | R2: CLM - PR | S2: Total | T2: ='Monthly HC & Prodn Working'!G2 -> 46204 | U2: Associate | V2: NAPs | W2: CLM - MD | X2: CLM - PR | Y2: Total | Z2: ='Monthly HC & Prodn Working'!H2 -> 46235 | AA2: Associate | AB2: NAPs | AC2: CLM - MD | AD2: CLM - PR | AE2: Total | AF2: ='Monthly HC & Prodn Working'!I2 -> 46266 | AG2: Associate | AH2: NAPs | AI2: CLM - MD | AJ2: CLM - PR | AK2: Total | AL2: ='Monthly HC & Prodn Working'!J2 -> 46296 | AM2: Associate | AN2: NAPs | AO2: CLM - MD | AP2: CLM - PR | AQ2: Total | AR2: ='Monthly HC & Prodn Working'!K2 -> 46327 | AS2: Associate | AT2: NAPs | AU2: CLM - MD | AV2: CLM - PR | AW2: Total | AX2: ='Monthly HC & Prodn Working'!L2 -> 46357 | AY2: Associate | AZ2: NAPs | BA2: CLM - MD | BB2: CLM - PR | BC2: Total | BD2: ='Monthly HC & Prodn Working'!M2 -> 46388 | BE2: Associate | BF2: NAPs | BG2: CLM - MD | BH2: CLM - PR | BI2: Total | BJ2: ='Monthly HC & Prodn Working'!N2 -> 46419 | BK2: Associate | BL2: NAPs | BM2: CLM - MD | BN2: CLM - PR | BO2: Total | BP2: ='Monthly HC & Prodn Working'!O2 -> 46447 | BQ2: Associate | BR2: NAPs | BS2: CLM - MD | BT2: CLM - PR | BU2: Total | BW2: Avg Prodn | BX2: Avg | BY2: Associate | BZ2: NAPs | CA2: CLM - MD | CB2: CLM - PR | CC2: Total | CD2: Remarks | CE2: Expected Budget (as per HR @24,596) | CF2: Expected Budget (as per Piece Rate) | CI2: Month | CJ2: Total HC | CK2: Associate | CL2: NAPs | CM2: CLM - MD | CN2: CLM - PR | CQ2: Month | CR2: Total HC | CS2: Associate | CT2: NAPs | CU2: CLM - MD | CV2: CLM - PR | DA2: ='Monthly HC & Prodn Working'!Q2 -> 46113 | DB2: ='Monthly HC & Prodn Working'!R2 -> 46143 | DC2: ='Monthly HC & Prodn Working'!S2 -> 46174 | DD2: ='Monthly HC & Prodn Working'!T2 -> 46204 | DE2: ='Monthly HC & Prodn Working'!U2 -> 46235 | DF2: ='Monthly HC & Prodn Working'!V2 -> 46266 | DG2: ='Monthly HC & Prodn Working'!W2 -> 46296 | DH2: ='Monthly HC & Prodn Working'!X2 -> 46327 | ... DL2: ='Monthly HC & Prodn Working'!AB2 -> 46447
A3: ='Monthly HC & Prodn Working'!B3 -> 1. POY | B3: ='Monthly HC & Prodn Working'!D3 -> 43 | C3: 35 | D3: 5 | E3: 3 | G3: =SUM(C3:F3) -> 43 | H3: ='Monthly HC & Prodn Working'!E3 -> 43 | I3: 35 | J3: 5 | K3: 3 | M3: =SUM(I3:L3) -> 43 | N3: ='Monthly HC & Prodn Working'!F3 -> 43 | O3: 35 | P3: 5 | Q3: 3 | S3: =SUM(O3:R3) -> 43 | T3: ='Monthly HC & Prodn Working'!G3 -> 43 | U3: 35 | V3: 5 | W3: 3 | Y3: =SUM(U3:X3) -> 43 | Z3: ='Monthly HC & Prodn Working'!H3 -> 43 | AA3: 35 | AB3: 5 | AC3: 3 | AE3: =SUM(AA3:AD3) -> 43 | AF3: ='Monthly HC & Prodn Working'!I3 -> 43 | AG3: 35 | AH3: 5 | AI3: 3 | AK3: =SUM(AG3:AJ3) -> 43 | AL3: ='Monthly HC & Prodn Working'!J3 -> 43 | AM3: 35 | AN3: 5 | AO3: 3 | AQ3: =SUM(AM3:AP3) -> 43 | AR3: ='Monthly HC & Prodn Working'!K3 -> 43 | AS3: 35 | AT3: 5 | AU3: 3 | AW3: =SUM(AS3:AV3) -> 43 | AX3: ='Monthly HC & Prodn Working'!L3 -> 43 | AY3: 35 | AZ3: 5 | BA3: 3 | BC3: =SUM(AY3:BB3) -> 43 | BD3: ='Monthly HC & Prodn Working'!M3 -> 43 | BE3: 35 | BF3: 5 | BG3: 3 | BI3: =SUM(BE3:BH3) -> 43 | BJ3: ='Monthly HC & Prodn Working'!N3 -> 43 | BK3: 35 | BL3: 5 | BM3: 3 | BO3: =SUM(BK3:BN3) -> 43 | BP3: ='Monthly HC & Prodn Working'!O3 -> 43 | BQ3: 35 | BR3: 5 | BS3: 3 | BU3: =SUM(BQ3:BT3) -> 43 | BW3: ='Monthly HC & Prodn Working'!AC3 -> 37828.86 | BX3: =IFERROR((AVERAGE(B3,H3,N3,T3,Z3,AF3,AL3,AR3,AX3,BD3,BJ3,BP3)),"") -> 43 | BY3: =IFERROR((AVERAGE(C3,I3,O3,U3,AA3,AG3,AM3,AS3,AY3,BE3,BK3,BQ3)),"") -> 35 | BZ3: =IFERROR((AVERAGE(D3,J3,P3,V3,AB3,AH3,AN3,AT3,AZ3,BF3,BL3,BR3)),"") -> 5 | CA3: =IFERROR((AVERAGE(E3,K3,Q3,W3,AC3,AI3,AO3,AU3,BA3,BG3,BM3,BS3)),"") -> 3 | CB3: =IFERROR((AVERAGE(F3,L3,R3,X3,AD3,AJ3,AP3,AV3,BB3,BH3,BN3,BT3)),"") | CC3: =IFERROR((AVERAGE(G3,M3,S3,Y3,AE3,AK3,AQ3,AW3,BC3,BI3,BO3,BU3)),"") -> 43 | CD3: All | CG3: OK. If Extra Sample Add, will provide 3 HC Per Day | CI3: 46113 | CJ3: =B29 -> 1637.5 | CK3: =C29 -> 519 | CL3: =D29 -> 270 | CM3: =E29 -> 277.5 | CN3: =F29 -> 591 | CQ3: 46113 | CR3: =B38 -> 66 | CS3: =C38 -> 32 | CT3: =D38 -> 0 | CU3: =E38 -> 20 | CV3: =F38 -> 14 | CY3: 29307.048 | DA3: ='Monthly HC & Prodn Working'!Q3 -> 50613.668 | DB3: ='Monthly HC & Prodn Working'!R3 -> 40984.507 | DC3: ='Monthly HC & Prodn Working'!S3 -> 35678.92 | DD3: ='Monthly HC & Prodn Working'!T3 -> 48507.406 | DE3: ='Monthly HC & Prodn Working'!U3 -> 37814.245 | DF3: ='Monthly HC & Prodn Working'!V3 -> 35651.419 | DG3: ='Monthly HC & Prodn Working'!W3 -> 37403.159 | DH3: ='Monthly HC & Prodn Working'!X3 -> 34395.261 | ... DL3: ='Monthly HC & Prodn Working'!AB3 -> 29715.511 | DM3: =SUM(DA3:DL3) -> 453946.32
A4: ='Monthly HC & Prodn Working'!B4 -> 2. BCF | B4: ='Monthly HC & Prodn Working'!D4 -> 23 | C4: 18 | D4: =B4-C4-E4 -> 2 | E4: 3 | G4: =SUM(C4:F4) -> 23 | H4: ='Monthly HC & Prodn Working'!E4 -> 25 | I4: 18 | J4: =H4-I4-K4 -> 4 | K4: 3 | M4: =SUM(I4:L4) -> 25 | N4: ='Monthly HC & Prodn Working'!F4 -> 23 | O4: 18 | P4: =N4-O4-Q4 -> 2 | Q4: 3 | S4: =SUM(O4:R4) -> 23 | T4: ='Monthly HC & Prodn Working'!G4 -> 23 | U4: 18 | V4: =T4-U4-W4 -> 2 | W4: 3 | Y4: =SUM(U4:X4) -> 23 | Z4: ='Monthly HC & Prodn Working'!H4 -> 25 | AA4: 18 | AB4: =Z4-AA4-AC4 -> 4 | AC4: 3 | AE4: =SUM(AA4:AD4) -> 25 | AF4: ='Monthly HC & Prodn Working'!I4 -> 29 | AG4: 18 | AH4: =AF4-AG4-AI4 -> 8 | AI4: 3 | AK4: =SUM(AG4:AJ4) -> 29 | AL4: ='Monthly HC & Prodn Working'!J4 -> 26 | AM4: 18 | AN4: =AL4-AM4-AO4 -> 5 | AO4: 3 | AQ4: =SUM(AM4:AP4) -> 26 | AR4: ='Monthly HC & Prodn Working'!K4 -> 29 | AS4: 18 | AT4: =AR4-AS4-AU4 -> 8 | AU4: 3 | AW4: =SUM(AS4:AV4) -> 29 | AX4: ='Monthly HC & Prodn Working'!L4 -> 38 | AY4: 30 | AZ4: =AX4-AY4-BA4 -> 5 | BA4: 3 | BC4: =SUM(AY4:BB4) -> 38 | BD4: ='Monthly HC & Prodn Working'!M4 -> 33 | BE4: 25 | BF4: =BD4-BE4-BG4 -> 5 | BG4: 3 | BI4: =SUM(BE4:BH4) -> 33 | BJ4: ='Monthly HC & Prodn Working'!N4 -> 33 | BK4: 25 | BL4: =BJ4-BK4-BM4 -> 5 | BM4: 3 | BO4: =SUM(BK4:BN4) -> 33 | BP4: ='Monthly HC & Prodn Working'!O4 -> 31 | BQ4: 24 | BR4: =BP4-BQ4-BS4 -> 4 | BS4: 3 | BU4: =SUM(BQ4:BT4) -> 31 | BW4: ='Monthly HC & Prodn Working'!AC4 -> 11641.995 | BX4: =IFERROR((AVERAGE(B4,H4,N4,T4,Z4,AF4,AL4,AR4,AX4,BD4,BJ4,BP4)),"") -> 28.166667 | BY4: =IFERROR((AVERAGE(C4,I4,O4,U4,AA4,AG4,AM4,AS4,AY4,BE4,BK4,BQ4)),"") -> 20.666667 | BZ4: =IFERROR((AVERAGE(D4,J4,P4,V4,AB4,AH4,AN4,AT4,AZ4,BF4,BL4,BR4)),"") -> 4.5 | CA4: =IFERROR((AVERAGE(E4,K4,Q4,W4,AC4,AI4,AO4,AU4,BA4,BG4,BM4,BS4)),"") -> 3 | CB4: =IFERROR((AVERAGE(F4,L4,R4,X4,AD4,AJ4,AP4,AV4,BB4,BH4,BN4,BT4)),"") | CC4: =IFERROR((AVERAGE(G4,M4,S4,Y4,AE4,AK4,AQ4,AW4,BC4,BI4,BO4,BU4)),"") -> 28.166667 | CD4: 11 Winder | CI4: 46143 | CJ4: =H29 -> 1627 | CK4: =I29 -> 518 | CL4: =J29 -> 267 | CM4: =K29 -> 275 | CN4: =L29 -> 585 | CQ4: 46143 | CR4: =CR3 -> 66 | CS4: =CS3 -> 32 | CT4: =CT3 -> 0 | CU4: =CU3 -> 20 | CV4: =CV3 -> 14 | CY4: 27055.372 | DA4: ='Monthly HC & Prodn Working'!Q4 -> 6335.1186 | DB4: ='Monthly HC & Prodn Working'!R4 -> 7343.1179 | DC4: ='Monthly HC & Prodn Working'!S4 -> 5757.8727 | DD4: ='Monthly HC & Prodn Working'!T4 -> 6631.5757 | DE4: ='Monthly HC & Prodn Working'!U4 -> 8091.1841 | DF4: ='Monthly HC & Prodn Working'!V4 -> 13123.9 | DG4: ='Monthly HC & Prodn Working'!W4 -> 9321.041 | DH4: ='Monthly HC & Prodn Working'!X4 -> 12237.754 | ... DL4: ='Monthly HC & Prodn Working'!AB4 -> 14566.333 | DM4: =SUM(DA4:DL4) -> 139703.94
A5: ='Monthly HC & Prodn Working'!B5 -> 3. Texturizing | B5: ='Monthly HC & Prodn Working'!D5 -> 84 | F5: =B5 -> 84 | G5: =SUM(C5:F5) -> 84 | H5: ='Monthly HC & Prodn Working'!E5 -> 84 | L5: =H5 -> 84 | M5: =SUM(I5:L5) -> 84 | N5: ='Monthly HC & Prodn Working'!F5 -> 84 | R5: =N5 -> 84 | S5: =SUM(O5:R5) -> 84 | T5: ='Monthly HC & Prodn Working'!G5 -> 84 | X5: =T5 -> 84 | Y5: =SUM(U5:X5) -> 84 | Z5: ='Monthly HC & Prodn Working'!H5 -> 84 | AD5: =Z5 -> 84 | AE5: =SUM(AA5:AD5) -> 84 | AF5: ='Monthly HC & Prodn Working'!I5 -> 84 | AJ5: =AF5 -> 84 | AK5: =SUM(AG5:AJ5) -> 84 | AL5: ='Monthly HC & Prodn Working'!J5 -> 84 | AP5: =AL5 -> 84 | AQ5: =SUM(AM5:AP5) -> 84 | AR5: ='Monthly HC & Prodn Working'!K5 -> 84 | AV5: =AR5 -> 84 | AW5: =SUM(AS5:AV5) -> 84 | AX5: ='Monthly HC & Prodn Working'!L5 -> 84 | BB5: =AX5 -> 84 | BC5: =SUM(AY5:BB5) -> 84 | BD5: ='Monthly HC & Prodn Working'!M5 -> 84 | BH5: =BD5 -> 84 | BI5: =SUM(BE5:BH5) -> 84 | BJ5: ='Monthly HC & Prodn Working'!N5 -> 84 | BN5: =BJ5 -> 84 | BO5: =SUM(BK5:BN5) -> 84 | BP5: ='Monthly HC & Prodn Working'!O5 -> 84 | BT5: =BP5 -> 84 | BU5: =SUM(BQ5:BT5) -> 84 | BW5: ='Monthly HC & Prodn Working'!AC5 -> 37771.136 | BX5: =IFERROR((AVERAGE(B5,H5,N5,T5,Z5,AF5,AL5,AR5,AX5,BD5,BJ5,BP5)),"") -> 84 | BY5: =IFERROR((AVERAGE(C5,I5,O5,U5,AA5,AG5,AM5,AS5,AY5,BE5,BK5,BQ5)),"") | BZ5: =IFERROR((AVERAGE(D5,J5,P5,V5,AB5,AH5,AN5,AT5,AZ5,BF5,BL5,BR5)),"") | CA5: =IFERROR((AVERAGE(E5,K5,Q5,W5,AC5,AI5,AO5,AU5,BA5,BG5,BM5,BS5)),"") | CB5: =IFERROR((AVERAGE(F5,L5,R5,X5,AD5,AJ5,AP5,AV5,BB5,BH5,BN5,BT5)),"") -> 84 | CC5: =IFERROR((AVERAGE(G5,M5,S5,Y5,AE5,AK5,AQ5,AW5,BC5,BI5,BO5,BU5)),"") -> 84 | CD5: All | CE5: =CB5*24596*12 -> 24792768 | CF5: =BV5*2.49*30*12 -> 0 | CI5: 46174 | CJ5: =N29 -> 1607.5 | CK5: =O29 -> 519 | CL5: =P29 -> 258 | CM5: =Q29 -> 267.5 | CN5: =R29 -> 578 | CQ5: 46174 | CR5: =CR4 -> 66 | CS5: =CS4 -> 32 | CT5: =CT4 -> 0 | CU5: =CU4 -> 20 | CV5: =CV4 -> 14 | CY5: 28660.128 | DA5: ='Monthly HC & Prodn Working'!Q5 -> 48085.277 | DB5: ='Monthly HC & Prodn Working'!R5 -> 40196.04 | DC5: ='Monthly HC & Prodn Working'!S5 -> 38656.901 | DD5: ='Monthly HC & Prodn Working'!T5 -> 40295.114 | DE5: ='Monthly HC & Prodn Working'!U5 -> 43144.011 | DF5: ='Monthly HC & Prodn Working'!V5 -> 38015.306 | DG5: ='Monthly HC & Prodn Working'!W5 -> 37561.646 | DH5: ='Monthly HC & Prodn Working'!X5 -> 34406.077 | ... DL5: ='Monthly HC & Prodn Working'!AB5 -> 29814.29
A6: ='Monthly HC & Prodn Working'!B6 -> 4. Parallel Winding | B6: ='Monthly HC & Prodn Working'!D6 -> 27 | F6: =B6 -> 27 | G6: =SUM(C6:F6) -> 27 | H6: ='Monthly HC & Prodn Working'!E6 -> 27 | L6: =H6 -> 27 | M6: =SUM(I6:L6) -> 27 | N6: ='Monthly HC & Prodn Working'!F6 -> 27 | R6: =N6 -> 27 | S6: =SUM(O6:R6) -> 27 | T6: ='Monthly HC & Prodn Working'!G6 -> 27 | X6: =T6 -> 27 | Y6: =SUM(U6:X6) -> 27 | Z6: ='Monthly HC & Prodn Working'!H6 -> 27 | AD6: =Z6 -> 27 | AE6: =SUM(AA6:AD6) -> 27 | AF6: ='Monthly HC & Prodn Working'!I6 -> 27 | AJ6: =AF6 -> 27 | AK6: =SUM(AG6:AJ6) -> 27 | AL6: ='Monthly HC & Prodn Working'!J6 -> 27 | AP6: =AL6 -> 27 | AQ6: =SUM(AM6:AP6) -> 27 | AR6: ='Monthly HC & Prodn Working'!K6 -> 27 | AV6: =AR6 -> 27 | AW6: =SUM(AS6:AV6) -> 27 | AX6: ='Monthly HC & Prodn Working'!L6 -> 27 | BB6: =AX6 -> 27 | BC6: =SUM(AY6:BB6) -> 27 | BD6: ='Monthly HC & Prodn Working'!M6 -> 27 | BH6: =BD6 -> 27 | BI6: =SUM(BE6:BH6) -> 27 | BJ6: ='Monthly HC & Prodn Working'!N6 -> 27 | BN6: =BJ6 -> 27 | BO6: =SUM(BK6:BN6) -> 27 | BP6: ='Monthly HC & Prodn Working'!O6 -> 27 | BT6: =BP6 -> 27 | BU6: =SUM(BQ6:BT6) -> 27 | BW6: ='Monthly HC & Prodn Working'!AC6 -> 21152.914 | BX6: =IFERROR((AVERAGE(B6,H6,N6,T6,Z6,AF6,AL6,AR6,AX6,BD6,BJ6,BP6)),"") -> 27 | BY6: =IFERROR((AVERAGE(C6,I6,O6,U6,AA6,AG6,AM6,AS6,AY6,BE6,BK6,BQ6)),"") | BZ6: =IFERROR((AVERAGE(D6,J6,P6,V6,AB6,AH6,AN6,AT6,AZ6,BF6,BL6,BR6)),"") | CA6: =IFERROR((AVERAGE(E6,K6,Q6,W6,AC6,AI6,AO6,AU6,BA6,BG6,BM6,BS6)),"") | CB6: =IFERROR((AVERAGE(F6,L6,R6,X6,AD6,AJ6,AP6,AV6,BB6,BH6,BN6,BT6)),"") -> 27 | CC6: =IFERROR((AVERAGE(G6,M6,S6,Y6,AE6,AK6,AQ6,AW6,BC6,BI6,BO6,BU6)),"") -> 27 | CD6: All | CE6: =CB6*24596*12 -> 7969104 | CF6: =BV6*1.9*30*12 -> 0 | CI6: 46204 | CJ6: =T29 -> 1622.5 | CK6: =U29 -> 522 | CL6: =V29 -> 262 | CM6: =W29 -> 275.5 | CN6: =X29 -> 580 | CQ6: 46204 | CR6: =CR5 -> 66 | CS6: =CS5 -> 32 | CT6: =CT5 -> 0 | CU6: =CU5 -> 20 | CV6: =CV5 -> 14 | CY6: 37349.861 | DA6: ='Monthly HC & Prodn Working'!Q6 -> 25757.709 | DB6: ='Monthly HC & Prodn Working'!R6 -> 21764.218 | DC6: ='Monthly HC & Prodn Working'!S6 -> 20261.879 | DD6: ='Monthly HC & Prodn Working'!T6 -> 22493.296 | DE6: ='Monthly HC & Prodn Working'!U6 -> 21203.283 | DF6: ='Monthly HC & Prodn Working'!V6 -> 21151.793 | DG6: ='Monthly HC & Prodn Working'!W6 -> 19854.218 | DH6: ='Monthly HC & Prodn Working'!X6 -> 18321.187 | ... DL6: ='Monthly HC & Prodn Working'!AB6 -> 19632.218
A7: ='Monthly HC & Prodn Working'!B7 -> Rewinding | B7: ='Monthly HC & Prodn Working'!D7 -> 15 | C7: 2 | E7: 13 | G7: =SUM(C7:F7) -> 15 | H7: ='Monthly HC & Prodn Working'!E7 -> 15 | I7: 2 | K7: 13 | M7: =SUM(I7:L7) -> 15 | N7: ='Monthly HC & Prodn Working'!F7 -> 15 | O7: 2 | Q7: 13 | S7: =SUM(O7:R7) -> 15 | T7: ='Monthly HC & Prodn Working'!G7 -> 15 | U7: 2 | W7: 13 | Y7: =SUM(U7:X7) -> 15 | Z7: ='Monthly HC & Prodn Working'!H7 -> 15 | AA7: 2 | AC7: 13 | AE7: =SUM(AA7:AD7) -> 15 | AF7: ='Monthly HC & Prodn Working'!I7 -> 15 | AG7: 2 | AI7: 13 | AK7: =SUM(AG7:AJ7) -> 15 | AL7: ='Monthly HC & Prodn Working'!J7 -> 15 | AM7: 2 | AO7: 13 | AQ7: =SUM(AM7:AP7) -> 15 | AR7: ='Monthly HC & Prodn Working'!K7 -> 15 | AS7: 2 | AU7: 13 | AW7: =SUM(AS7:AV7) -> 15 | AX7: ='Monthly HC & Prodn Working'!L7 -> 15 | AY7: 2 | BA7: 13 | BC7: =SUM(AY7:BB7) -> 15 | BD7: ='Monthly HC & Prodn Working'!M7 -> 15 | BE7: 2 | BG7: 13 | BI7: =SUM(BE7:BH7) -> 15 | BJ7: ='Monthly HC & Prodn Working'!N7 -> 15 | BK7: 2 | BM7: 13 | BO7: =SUM(BK7:BN7) -> 15 | BP7: ='Monthly HC & Prodn Working'!O7 -> 15 | BQ7: 2 | BS7: 13 | BU7: =SUM(BQ7:BT7) -> 15 | BW7: ='Monthly HC & Prodn Working'!AC7 -> 0 | BX7: =IFERROR((AVERAGE(B7,H7,N7,T7,Z7,AF7,AL7,AR7,AX7,BD7,BJ7,BP7)),"") -> 15 | BY7: =IFERROR((AVERAGE(C7,I7,O7,U7,AA7,AG7,AM7,AS7,AY7,BE7,BK7,BQ7)),"") -> 2 | BZ7: =IFERROR((AVERAGE(D7,J7,P7,V7,AB7,AH7,AN7,AT7,AZ7,BF7,BL7,BR7)),"") | CA7: =IFERROR((AVERAGE(E7,K7,Q7,W7,AC7,AI7,AO7,AU7,BA7,BG7,BM7,BS7)),"") -> 13 | CB7: =IFERROR((AVERAGE(F7,L7,R7,X7,AD7,AJ7,AP7,AV7,BB7,BH7,BN7,BT7)),"") | CC7: =IFERROR((AVERAGE(G7,M7,S7,Y7,AE7,AK7,AQ7,AW7,BC7,BI7,BO7,BU7)),"") -> 15 | CI7: 46235 | CJ7: =Z29 -> 1666.5 | CK7: =AA29 -> 525 | CL7: =AB29 -> 278 | CM7: =AC29 -> 272.5 | CN7: =AD29 -> 611 | CQ7: 46235 | CR7: =CR6 -> 66 | CS7: =CS6 -> 32 | CT7: =CT6 -> 0 | CU7: =CU6 -> 20 | CV7: =CV6 -> 14 | CY7: 44727.18 | DA7: ='Monthly HC & Prodn Working'!Q7 -> 0 | DB7: ='Monthly HC & Prodn Working'!R7 -> 0 | DC7: ='Monthly HC & Prodn Working'!S7 -> 0 | DD7: ='Monthly HC & Prodn Working'!T7 -> 0 | DE7: ='Monthly HC & Prodn Working'!U7 -> 0 | DF7: ='Monthly HC & Prodn Working'!V7 -> 0 | DG7: ='Monthly HC & Prodn Working'!W7 -> 0 | DH7: ='Monthly HC & Prodn Working'!X7 -> 0 | ... DL7: ='Monthly HC & Prodn Working'!AB7 -> 0
A8: ='Monthly HC & Prodn Working'!B8 -> 5. Multiply | B8: ='Monthly HC & Prodn Working'!D8 -> 107 | F8: =B8 -> 107 | G8: =SUM(C8:F8) -> 107 | H8: ='Monthly HC & Prodn Working'!E8 -> 121 | L8: =H8 -> 121 | M8: =SUM(I8:L8) -> 121 | N8: ='Monthly HC & Prodn Working'!F8 -> 128 | R8: =N8 -> 128 | S8: =SUM(O8:R8) -> 128 | T8: ='Monthly HC & Prodn Working'!G8 -> 110 | X8: =T8 -> 110 | Y8: =SUM(U8:X8) -> 110 | Z8: ='Monthly HC & Prodn Working'!H8 -> 125 | AD8: =Z8 -> 125 | AE8: =SUM(AA8:AD8) -> 125 | AF8: ='Monthly HC & Prodn Working'!I8 -> 121 | AJ8: =AF8 -> 121 | AK8: =SUM(AG8:AJ8) -> 121 | AL8: ='Monthly HC & Prodn Working'!J8 -> 128 | AP8: =AL8 -> 128 | AQ8: =SUM(AM8:AP8) -> 128 | AR8: ='Monthly HC & Prodn Working'!K8 -> 138 | AV8: =AR8 -> 138 | AW8: =SUM(AS8:AV8) -> 138 | AX8: ='Monthly HC & Prodn Working'!L8 -> 161 | BB8: =AX8 -> 161 | BC8: =SUM(AY8:BB8) -> 161 | BD8: ='Monthly HC & Prodn Working'!M8 -> 113 | BH8: =BD8 -> 113 | BI8: =SUM(BE8:BH8) -> 113 | BJ8: ='Monthly HC & Prodn Working'!N8 -> 131 | BN8: =BJ8 -> 131 | BO8: =SUM(BK8:BN8) -> 131 | BP8: ='Monthly HC & Prodn Working'!O8 -> 107 | BT8: =BP8 -> 107 | BU8: =SUM(BQ8:BT8) -> 107 | BW8: ='Monthly HC & Prodn Working'!AC8 -> 4829.4533 | BX8: =IFERROR((AVERAGE(B8,H8,N8,T8,Z8,AF8,AL8,AR8,AX8,BD8,BJ8,BP8)),"") -> 124.16667 | BY8: =IFERROR((AVERAGE(C8,I8,O8,U8,AA8,AG8,AM8,AS8,AY8,BE8,BK8,BQ8)),"") | BZ8: =IFERROR((AVERAGE(D8,J8,P8,V8,AB8,AH8,AN8,AT8,AZ8,BF8,BL8,BR8)),"") | CA8: =IFERROR((AVERAGE(E8,K8,Q8,W8,AC8,AI8,AO8,AU8,BA8,BG8,BM8,BS8)),"") | CB8: =IFERROR((AVERAGE(F8,L8,R8,X8,AD8,AJ8,AP8,AV8,BB8,BH8,BN8,BT8)),"") -> 124.16667 | CC8: =IFERROR((AVERAGE(G8,M8,S8,Y8,AE8,AK8,AQ8,AW8,BC8,BI8,BO8,BU8)),"") -> 124.16667 | CE8: =CB8*24596*12 -> 36648040 | CF8: =BW8*22*30*12 -> 38249270 | CI8: 46266 | CJ8: =AF29 -> 1669.5 | CK8: =AG29 -> 522 | CL8: =AH29 -> 288 | CM8: =AI29 -> 287.5 | CN8: =AJ29 -> 591 | CQ8: 46266 | CR8: =CR7 -> 66 | CS8: =CS7 -> 32 | CT8: =CT7 -> 0 | CU8: =CU7 -> 20 | CV8: =CV7 -> 14 | CY8: 57325.257 | DA8: ='Monthly HC & Prodn Working'!Q8 -> 3218.2216 | DB8: ='Monthly HC & Prodn Working'!R8 -> 4320.0494 | DC8: ='Monthly HC & Prodn Working'!S8 -> 4862.0171 | DD8: ='Monthly HC & Prodn Working'!T8 -> 3418.4592 | DE8: ='Monthly HC & Prodn Working'!U8 -> 4856.3501 | DF8: ='Monthly HC & Prodn Working'!V8 -> 4531.8126 | DG8: ='Monthly HC & Prodn Working'!W8 -> 5257.8924 | DH8: ='Monthly HC & Prodn Working'!X8 -> 7080.4784 | ... DL8: ='Monthly HC & Prodn Working'!AB8 -> 3556.446
A9: ='Monthly HC & Prodn Working'!B9 -> TFO | B9: ='Monthly HC & Prodn Working'!D9 -> 0 | G9: =SUM(C9:F9) -> 0 | H9: ='Monthly HC & Prodn Working'!E9 -> 0 | M9: =SUM(I9:L9) -> 0 | N9: ='Monthly HC & Prodn Working'!F9 -> 0 | S9: =SUM(O9:R9) -> 0 | T9: ='Monthly HC & Prodn Working'!G9 -> 0 | Y9: =SUM(U9:X9) -> 0 | Z9: ='Monthly HC & Prodn Working'!H9 -> 0 | AE9: =SUM(AA9:AD9) -> 0 | AF9: ='Monthly HC & Prodn Working'!I9 -> 0 | AK9: =SUM(AG9:AJ9) -> 0 | AL9: ='Monthly HC & Prodn Working'!J9 -> 0 | AQ9: =SUM(AM9:AP9) -> 0 | AR9: ='Monthly HC & Prodn Working'!K9 -> 0 | AW9: =SUM(AS9:AV9) -> 0 | AX9: ='Monthly HC & Prodn Working'!L9 -> 0 | BC9: =SUM(AY9:BB9) -> 0 | BD9: ='Monthly HC & Prodn Working'!M9 -> 0 | BI9: =SUM(BE9:BH9) -> 0 | BJ9: ='Monthly HC & Prodn Working'!N9 -> 0 | BO9: =SUM(BK9:BN9) -> 0 | BP9: ='Monthly HC & Prodn Working'!O9 -> 0 | BU9: =SUM(BQ9:BT9) -> 0 | BW9: ='Monthly HC & Prodn Working'!AC9 -> 7407.3248 | BX9: =IFERROR((AVERAGE(B9,H9,N9,T9,Z9,AF9,AL9,AR9,AX9,BD9,BJ9,BP9)),"") -> 0 | BY9: =IFERROR((AVERAGE(C9,I9,O9,U9,AA9,AG9,AM9,AS9,AY9,BE9,BK9,BQ9)),"") | BZ9: =IFERROR((AVERAGE(D9,J9,P9,V9,AB9,AH9,AN9,AT9,AZ9,BF9,BL9,BR9)),"") | CA9: =IFERROR((AVERAGE(E9,K9,Q9,W9,AC9,AI9,AO9,AU9,BA9,BG9,BM9,BS9)),"") | CB9: =IFERROR((AVERAGE(F9,L9,R9,X9,AD9,AJ9,AP9,AV9,BB9,BH9,BN9,BT9)),"") | CC9: =IFERROR((AVERAGE(G9,M9,S9,Y9,AE9,AK9,AQ9,AW9,BC9,BI9,BO9,BU9)),"") -> 0 | CI9: 46296 | CJ9: =AL29 -> 1650.5 | CK9: =AM29 -> 527 | CL9: =AN29 -> 273 | CM9: =AO29 -> 279.5 | CN9: =AP29 -> 588 | CQ9: 46296 | CR9: =CR8 -> 66 | CS9: =CS8 -> 32 | CT9: =CT8 -> 0 | CU9: =CU8 -> 20 | CV9: =CV8 -> 14 | CY9: 72117.178 | DA9: ='Monthly HC & Prodn Working'!Q9 -> 5622.565 | DB9: ='Monthly HC & Prodn Working'!R9 -> 6890.4035 | DC9: ='Monthly HC & Prodn Working'!S9 -> 7301.7362 | DD9: ='Monthly HC & Prodn Working'!T9 -> 6087.6182 | DE9: ='Monthly HC & Prodn Working'!U9 -> 7138.4185 | DF9: ='Monthly HC & Prodn Working'!V9 -> 6981.9548 | DG9: ='Monthly HC & Prodn Working'!W9 -> 8056.8772 | DH9: ='Monthly HC & Prodn Working'!X9 -> 8173.2849 | ... DL9: ='Monthly HC & Prodn Working'!AB9 -> 5910.8985
A10: ='Monthly HC & Prodn Working'!B10 -> Auto Clave | B10: ='Monthly HC & Prodn Working'!D10 -> 0 | G10: =SUM(C10:F10) -> 0 | H10: ='Monthly HC & Prodn Working'!E10 -> 0 | M10: =SUM(I10:L10) -> 0 | N10: ='Monthly HC & Prodn Working'!F10 -> 0 | S10: =SUM(O10:R10) -> 0 | T10: ='Monthly HC & Prodn Working'!G10 -> 0 | Y10: =SUM(U10:X10) -> 0 | Z10: ='Monthly HC & Prodn Working'!H10 -> 0 | AE10: =SUM(AA10:AD10) -> 0 | AF10: ='Monthly HC & Prodn Working'!I10 -> 0 | AK10: =SUM(AG10:AJ10) -> 0 | AL10: ='Monthly HC & Prodn Working'!J10 -> 0 | AQ10: =SUM(AM10:AP10) -> 0 | AR10: ='Monthly HC & Prodn Working'!K10 -> 0 | AW10: =SUM(AS10:AV10) -> 0 | AX10: ='Monthly HC & Prodn Working'!L10 -> 0 | BC10: =SUM(AY10:BB10) -> 0 | BD10: ='Monthly HC & Prodn Working'!M10 -> 0 | BI10: =SUM(BE10:BH10) -> 0 | BJ10: ='Monthly HC & Prodn Working'!N10 -> 0 | BO10: =SUM(BK10:BN10) -> 0 | BP10: ='Monthly HC & Prodn Working'!O10 -> 0 | BU10: =SUM(BQ10:BT10) -> 0 | BW10: ='Monthly HC & Prodn Working'!AC10 -> 2577.8715 | BX10: =IFERROR((AVERAGE(B10,H10,N10,T10,Z10,AF10,AL10,AR10,AX10,BD10,BJ10,BP10)),"") -> 0 | BY10: =IFERROR((AVERAGE(C10,I10,O10,U10,AA10,AG10,AM10,AS10,AY10,BE10,BK10,BQ10)),"") | BZ10: =IFERROR((AVERAGE(D10,J10,P10,V10,AB10,AH10,AN10,AT10,AZ10,BF10,BL10,BR10)),"") | CA10: =IFERROR((AVERAGE(E10,K10,Q10,W10,AC10,AI10,AO10,AU10,BA10,BG10,BM10,BS10)),"") | CB10: =IFERROR((AVERAGE(F10,L10,R10,X10,AD10,AJ10,AP10,AV10,BB10,BH10,BN10,BT10)),"") | CC10: =IFERROR((AVERAGE(G10,M10,S10,Y10,AE10,AK10,AQ10,AW10,BC10,BI10,BO10,BU10)),"") -> 0 | CF10: =BW10*8.25*30*12 -> 7656278.3 | CI10: 46327 | CJ10: =AR29 -> 1606.5 | CK10: =AS29 -> 522 | CL10: =AT29 -> 267 | CM10: =AU29 -> 274 | CN10: =AV29 -> 563.5 | CQ10: 46327 | CR10: =CR9 -> 66 | CS10: =CS9 -> 32 | CT10: =CT9 -> 0 | CU10: =CU9 -> 20 | CV10: =CV9 -> 14 | CY10: 74386.186 | DA10: ='Monthly HC & Prodn Working'!Q10 -> 2404.3434 | DB10: ='Monthly HC & Prodn Working'!R10 -> 2570.3541 | DC10: ='Monthly HC & Prodn Working'!S10 -> 2439.7191 | DD10: ='Monthly HC & Prodn Working'!T10 -> 2669.159 | DE10: ='Monthly HC & Prodn Working'!U10 -> 2282.0684 | DF10: ='Monthly HC & Prodn Working'!V10 -> 2450.1422 | DG10: ='Monthly HC & Prodn Working'!W10 -> 2798.9847 | DH10: ='Monthly HC & Prodn Working'!X10 -> 1092.8065 | ... DL10: ='Monthly HC & Prodn Working'!AB10 -> 2354.4525
A11: ='Monthly HC & Prodn Working'!B11 -> 6. Cabling | B11: ='Monthly HC & Prodn Working'!D11 -> 69 | F11: =B11 -> 69 | G11: =SUM(C11:F11) -> 69 | H11: ='Monthly HC & Prodn Working'!E11 -> 63 | L11: =H11 -> 63 | M11: =SUM(I11:L11) -> 63 | N11: ='Monthly HC & Prodn Working'!F11 -> 59 | R11: =N11 -> 59 | S11: =SUM(O11:R11) -> 59 | T11: ='Monthly HC & Prodn Working'!G11 -> 62 | X11: =T11 -> 62 | Y11: =SUM(U11:X11) -> 62 | Z11: ='Monthly HC & Prodn Working'!H11 -> 68 | AD11: =Z11 -> 68 | AE11: =SUM(AA11:AD11) -> 68 | AF11: ='Monthly HC & Prodn Working'!I11 -> 69 | AJ11: =AF11 -> 69 | AK11: =SUM(AG11:AJ11) -> 69 | AL11: ='Monthly HC & Prodn Working'!J11 -> 61 | AP11: =AL11 -> 61 | AQ11: =SUM(AM11:AP11) -> 61 | AR11: ='Monthly HC & Prodn Working'!K11 -> 58 | AV11: =AR11 -> 58 | AW11: =SUM(AS11:AV11) -> 58 | AX11: ='Monthly HC & Prodn Working'!L11 -> 67 | BB11: =AX11 -> 67 | BC11: =SUM(AY11:BB11) -> 67 | BD11: ='Monthly HC & Prodn Working'!M11 -> 66 | BH11: =BD11 -> 66 | BI11: =SUM(BE11:BH11) -> 66 | BJ11: ='Monthly HC & Prodn Working'!N11 -> 68 | BN11: =BJ11 -> 68 | BO11: =SUM(BK11:BN11) -> 68 | BP11: ='Monthly HC & Prodn Working'!O11 -> 60 | BT11: =BP11 -> 60 | BU11: =SUM(BQ11:BT11) -> 60 | BW11: ='Monthly HC & Prodn Working'!AC11 -> 36103.398 | BX11: =IFERROR((AVERAGE(B11,H11,N11,T11,Z11,AF11,AL11,AR11,AX11,BD11,BJ11,BP11)),"") -> 64.166667 | BY11: =IFERROR((AVERAGE(C11,I11,O11,U11,AA11,AG11,AM11,AS11,AY11,BE11,BK11,BQ11)),"") | BZ11: =IFERROR((AVERAGE(D11,J11,P11,V11,AB11,AH11,AN11,AT11,AZ11,BF11,BL11,BR11)),"") | CA11: =IFERROR((AVERAGE(E11,K11,Q11,W11,AC11,AI11,AO11,AU11,BA11,BG11,BM11,BS11)),"") | CB11: =IFERROR((AVERAGE(F11,L11,R11,X11,AD11,AJ11,AP11,AV11,BB11,BH11,BN11,BT11)),"") -> 64.166667 | CC11: =IFERROR((AVERAGE(G11,M11,S11,Y11,AE11,AK11,AQ11,AW11,BC11,BI11,BO11,BU11)),"") -> 64.166667 | CD11: 18 M/C | CE11: =CB11*24596*12 -> 18938920 | CF11: =BW11*1.71*30*12 -> 22225252 | CI11: 46357 | CJ11: =AX29 -> 1633.5 | CK11: =AY29 -> 542 | CL11: =AZ29 -> 282 | CM11: =BA29 -> 293 | CN11: =BB29 -> 536.5 | CQ11: 46357 | CR11: =CR10 -> 66 | CS11: =CS10 -> 32 | CT11: =CT10 -> 0 | CU11: =CU10 -> 20 | CV11: =CV10 -> 14 | CY11: 54424.173 | DA11: ='Monthly HC & Prodn Working'!Q11 -> 41292.949 | DB11: ='Monthly HC & Prodn Working'!R11 -> 34846.489 | DC11: ='Monthly HC & Prodn Working'!S11 -> 32022.756 | DD11: ='Monthly HC & Prodn Working'!T11 -> 34633.558 | DE11: ='Monthly HC & Prodn Working'!U11 -> 38506.102 | DF11: ='Monthly HC & Prodn Working'!V11 -> 39007.078 | DG11: ='Monthly HC & Prodn Working'!W11 -> 34028.048 | DH11: ='Monthly HC & Prodn Working'!X11 -> 31353.977 | ... DL11: ='Monthly HC & Prodn Working'!AB11 -> 33353.914
